Workbook
Name EscenarioActivo: Escenarios!$B$4

Sheet Dashboard
A1: DASHBOARD — Super Meseros | H1: ⚡ ESCENARIO | J1: Año 1 | K1: Año 2 | L1: Año 3 | M1: Año 4 | N1: Año 5
A2: Métricas financieras y operativas · Datos dinámicos vinculados al modelo · Escenario activo: | F2: =CHOOSE(Escenarios!B4,"PESIMISTA","BASE","OPTIMISTA") | H2: =CHOOSE(Escenarios!B4,"PESIMISTA","BASE","OPTIMISTA") | I2: Ingresos | J2: =B5 | K2: =C5 | L2: =D5 | M2: =E5 | N2: =F5
H3: =HYPERLINK("#Escenarios!B4","✏️ Cambiar escenario →") | I3: EBITDA | J3: =B10 | K3: =C10 | L3: =D10 | M3: =E10 | N3: =F10
A4: P&L ANUAL | B4: Año 1 | C4: Año 2 | D4: Año 3 | E4: Año 4 | F4: Año 5 | G4: Total 60m | I4: Utilidad Neta | J4: =B11 | K4: =C11 | L4: =D11 | M4: =E11 | N4: =F11
A5: Ingresos | B5: =SUM('Estados Financieros'!B8:M8) | C5: =SUM('Estados Financieros'!N8:Y8) | D5: =SUM('Estados Financieros'!Z8:AK8) | E5: =SUM('Estados Financieros'!AL8:AW8) | F5: =SUM('Estados Financieros'!AX8:BI8) | G5: ='Estados Financieros'!BJ8
A6: Costos Directos | B6: =SUM('Estados Financieros'!B11:M11) | C6: =SUM('Estados Financieros'!N11:Y11) | D6: =SUM('Estados Financieros'!Z11:AK11) | E6: =SUM('Estados Financieros'!AL11:AW11) | F6: =SUM('Estados Financieros'!AX11:BI11) | G6: ='Estados Financieros'!BJ11 | J6: Año 1 | K6: Año 2 | L6: Año 3 | M6: Año 4 | N6: Año 5
A7: Utilidad Bruta | B7: =B5-B6 | C7: =C5-C6 | D7: =D5-D6 | E7: =E5-E6 | F7: =F5-F6 | G7: =G5-G6 | I7: Restaurantes activos | J7: =B15 | K7: =C15 | L7: =D15 | M7: =E15 | N7: =F15
A8: CAC y GTM | B8: =SUM('Estados Financieros'!B16:M16) | C8: =SUM('Estados Financieros'!N16:Y16) | D8: =SUM('Estados Financieros'!Z16:AK16) | E8: =SUM('Estados Financieros'!AL16:AW16) | F8: =SUM('Estados Financieros'!AX16:BI16) | G8: ='Estados Financieros'!BJ16
A9: OPEX | B9: =SUM('Estados Financieros'!B21:M21) | C9: =SUM('Estados Financieros'!N21:Y21) | D9: =SUM('Estados Financieros'!Z21:AK21) | E9: =SUM('Estados Financieros'!AL21:AW21) | F9: =SUM('Estados Financieros'!AX21:BI21) | G9: ='Estados Financieros'!BJ21 | J9: Año 1 | K9: Año 2 | L9: Año 3 | M9: Año 4 | N9: Año 5
A10: EBITDA | B10: =SUM('Estados Financieros'!B22:M22) | C10: =SUM('Estados Financieros'!N22:Y22) | D10: =SUM('Estados Financieros'!Z22:AK22) | E10: =SUM('Estados Financieros'!AL22:AW22) | F10: =SUM('Estados Financieros'!AX22:BI22) | G10: ='Estados Financieros'!BJ22 | I10: Margen Bruto | J10: =B17 | K10: =C17 | L10: =D17 | M10: =E17 | N10: =F17
A11: Utilidad Neta | B11: =SUM('Estados Financieros'!B25:M25) | C11: =SUM('Estados Financieros'!N25:Y25) | D11: =SUM('Estados Financieros'!Z25:AK25) | E11: =SUM('Estados Financieros'!AL25:AW25) | F11: =SUM('Estados Financieros'!AX25:BI25) | G11: ='Estados Financieros'!BJ25 | I11: Margen EBITDA | J11: =B18 | K11: =C18 | L11: =D18 | M11: =E18 | N11: =F18
A12: Caja Final | B12: ='Estados Financieros'!M31 | C12: ='Estados Financieros'!Y31 | D12: ='Estados Financieros'!AK31 | E12: ='Estados Financieros'!AW31 | F12: ='Estados Financieros'!BI31 | G12: ='Estados Financieros'!BJ31 | I12: Margen Neto | J12: =B19 | K12: =C19 | L12: =D19 | M12: =E19 | N12: =F19
A14: KPIs OPERATIVOS | B14: Año 1 | C14: Año 2 | D14: Año 3 | E14: Año 4 | F14: Año 5 | J14: Año 1 | K14: Año 2 | L14: Año 3 | M14: Año 4 | N14: Año 5
A15: Rest. activos (fin año) | B15: ='Estados Financieros'!M35 | C15: ='Estados Financieros'!Y35 | D15: ='Estados Financieros'!AK35 | E15: ='Estados Financieros'!AW35 | F15: ='Estados Financieros'!BI35 | I15: Costos Directos | J15: =B6 | K15: =C6 | L15: =D6 | M15: =E6 | N15: =F6
A16: Meseros activos (fin año) | B16: ='Estados Financieros'!M36 | C16: ='Estados Financieros'!Y36 | D16: ='Estados Financieros'!AK36 | E16: ='Estados Financieros'!AW36 | F16: ='Estados Financieros'!BI36 | I16: CAC y GTM | J16: =B8 | K16: =C8 | L16: =D8 | M16: =E8 | N16: =F8
A17: Margen Bruto | B17: =IF(B5=0,0,B7/B5) | C17: =IF(C5=0,0,C7/C5) | D17: =IF(D5=0,0,D7/D5) | E17: =IF(E5=0,0,E7/E5) | F17: =IF(F5=0,0,F7/F5) | I17: OPEX | J17: =B9 | K17: =C9 | L17: =D9 | M17: =E9 | N17: =F9
A18: Margen EBITDA | B18: =IF(B5=0,0,B10/B5) | C18: =IF(C5=0,0,C10/C5) | D18: =IF(D5=0,0,D10/D5) | E18: =IF(E5=0,0,E10/E5) | F18: =IF(F5=0,0,F10/F5) | I18: EBITDA | J18: =B10 | K18: =C10 | L18: =D10 | M18: =E10 | N18: =F10
A19: Margen Neto | B19: =IF(B5=0,0,B11/B5) | C19: =IF(C5=0,0,C11/C5) | D19: =IF(D5=0,0,D11/D5) | E19: =IF(E5=0,0,E11/E5) | F19: =IF(F5=0,0,F11/F5)
J20: Año 1 | K20: Año 2 | L20: Año 3 | M20: Año 4 | N20: Año 5
A21: VALORACIÓN & DEAL STRUCTURE | D21: ALIANZAS ACTIVAS | E21: Estado | F21: Rest/mes | I21: Restaurantes activos | J21: =B15 | K21: =C15 | L21: =D15 | M21: =E15 | N21: =F15
A22: Valoración Pre-Money (ponderada) | B22: =Valoración!C52 | D22: Coca-Cola | E22: =IF(Palancas!B13=1,"✅ ON","❌ OFF") | F22: =IF(Palancas!B13=1,Palancas!B16,0) | I22: Caja Final | J22: =B12 | K22: =C12 | L22: =D12 | M22: =E12 | N22: =F12
A23: Monto a levantar | B23: =Valoración!C56 | D23: ACODRES | E23: =IF(Palancas!F13=1,"✅ ON","❌ OFF") | F23: =IF(Palancas!F13=1,Palancas!F16,0)
A24: Valoración Post-Money | B24: =Valoración!C57 | D24: Bavaria | E24: =IF(Palancas!B21=1,"✅ ON","❌ OFF") | F24: =IF(Palancas!B21=1,Palancas!B24,0)
A25: Dilución del fundador | B25: =Valoración!C58 | D25: FEMSA | E25: =IF(Palancas!F21=1,"✅ ON","❌ OFF") | F25: =IF(Palancas!F21=1,Palancas!F24,0)
A26: ARR Pipeline | B26: =Valoración!C33 | D26: CC Florida | E26: =IF(Palancas!B29=1,"✅ ON","❌ OFF") | F26: =IF(Palancas!B29=1,Palancas!B32,0)
A27: ARR Modelo Año 1 | B27: =Valoración!C36
A28: Restaurantes mes 60 | B28: =Valoración!C40 | D28: Total alianzas/mes | E28: =COUNTIF(E22:E26,"✅ ON") | F28: =SUM(F22:F26)

Sheet Unit Economics
A1: UNIT ECONOMICS — Simulador por Restaurante | D1: ⚡ ESCENARIO
C2: =CHOOSE(Escenarios!B4,"PESIMISTA","BASE","OPTIMISTA") | D2: =HYPERLINK("#Escenarios!B4","✏️ Cambiar →")
A3: 📊 INPUT DEL INVERSIONISTA
A5: Número de restaurantes | B5: 1 | C5: ← Cambie este número
A7: PARÁMETROS BASE (1 Restaurante) | C7: Valor | D7: Fuente
A8: Meseros promedio por restaurante | C8: ='Supuestos Generales'!B19 | D8: Supuestos B19
A9: % de meseros activos | C9: ='Supuestos Generales'!B20 | D9: Supuestos B20
A10: Meseros activos por restaurante | C10: =C8*C9 | D10: Calculado
A11: Marcas promedio por restaurante | C11: ='Supuestos Generales'!B28 | D11: Supuestos B28
A13: INGRESOS ONE-OFF (por restaurante nuevo) | C13: USD | D13: Fuente
A14: SetUp Fee | C14: ='Supuestos Generales'!B24 | D14: Supuestos B24
A15: Entry Fee (por marca) | C15: ='Supuestos Generales'!B25*C11 | D15: B25 × marcas
A16: Total Ingresos One-Off | C16: =C14+C15 | D16: Suma
A18: INGRESOS RECURRENTES / MES (por restaurante) | C18: USD/mes | D18: Fuente
A19: SaaS Fee Restaurante (por mesero activo) | C19: ='Supuestos Generales'!B26*C10 | D19: B26 × activos
A20: SaaS Fee Marcas (por mesero activo × marcas) | C20: ='Supuestos Generales'!B27*C10*C11 | D20: B27 × activos × marcas
A21: Fee Upgrade de Plan | C21: ='Supuestos Generales'!B59*'Supuestos Generales'!B60 | D21: B59 × B60 (% upgrade × fee)
A22: Super Monedas — Restaurantes (bruto) | C22: ='Supuestos Generales'!B31*C10 | D22: B31 × activos
A23: Super Monedas — Marcas (bruto) | C23: ='Supuestos Generales'!B32*C10*C11 | D23: B32 × activos × marcas
A24: Total Super Monedas (bruto) | C24: =C22+C23
A25: Ingreso neto Super Monedas (breakage + margen) | C25: =C24*('Supuestos Generales'!B34+'Supuestos Generales'!B33*'Supuestos Generales'!B35) | D25: breakage + margen redención
A27: Total Ingresos Recurrentes / Mes | C27: =C19+C20+C21+C24 | D27: Suma SaaS + SM neto
A28: Ingreso Anualizado (1 restaurante) | C28: =C27*12 | D28: Recurrente × 12
A30: ESCALAMIENTO — Total por Número de Restaurantes | C30: USD | D30: Fórmula
A31: Restaurantes | C31: =B5 | D31: ← Input B5
A32: Total Ingresos One-Off | C32: =C16*C31 | D32: One-off × restaurantes
A33: Total Ingresos Recurrentes / Mes | C33: =C27*C31 | D33: Recurrente × restaurantes
A34: Total Ingreso Anualizado | C34: =C28*C31 | D34: Anualizado × restaurantes
A36: Ingreso recurrente mensual por restaurante (referencia) | C36: =C27 | D36: Constante

Sheet Resumen Escenarios
A1: MASTER WAITERS (Super Meseros) | G1: ⚡ ESCENARIO
A2: Resumen de Escenarios Financieros · Modelo v4.0 · Datos dinámicos vinculados al modelo · Copiar y pegar en pitch deck | G2: =CHOOSE(Escenarios!B4,"PESIMISTA","BASE","OPTIMISTA")
G3: =HYPERLINK("#Escenarios!B4","✏️ Cambiar escenario →")
A5: 1. CONTEXTO DEL MODELO
A6: Horizonte: 60 meses (5 años). Caja inicial: $500,000 USD. Ramp-up lineal de alianzas (12–24 meses según escenario). Segmentación por tamaño de restaurante (Pricing v2.5).
A8: Fuentes de Ingresos: SetUp Fee ($500/rest), Entry Fee ($300/rest-marca), SaaS Fee (ARPU ponderado por segmento), Fee Upgrade ($50 × %upgrade), Super Monedas (programa gamificado).
A10: Alianzas Estratégicas Contempladas
A11: Alianza | B11: Pipeline | C11: Mercado | D11: Descripción
A12: Coca-Cola | B12: 5,000 rest. | C12: Colombia | D12: Exclusividad confirmada
A13: ACODRES | B13: 12,000 rest. | C13: Colombia | D13: Gremio de restaurantes
A14: Bavaria | B14: 4,500 rest. | C14: Colombia | D14: Interés en implementar SM
A15: FEMSA Ventures | B15: 50,000 rest. | C15: México | D15: Interés en invertir
A16: Coca-Cola Florida | B16: 5,000 rest. | C16: USA | D16: Piloto → expansión
A18: 2. DEFINICIÓN DE ESCENARIOS
A19: Parámetro | B19: 🔴 Pesimista | C19: 🟡 Base | D19: 🟢 Optimista
A20: Alianzas activas | B20: =DF140 | C20: =DF167 | D20: =DF194
A21: Rest/mes por alianza | B21: =CHOOSE(1,Escenarios!$D$49) | C21: =CHOOSE(1,Escenarios!$E$49) | D21: =CHOOSE(1,Escenarios!$F$49)
A22: Meses de ramp-up | B22: =Escenarios!D51 | C22: =Escenarios!E51 | D22: =Escenarios!F51
A23: Churn mensual | B23: =Escenarios!D17 | C23: =Escenarios!E17 | D23: =Escenarios!F17
A24: Meseros ponderados/rest | B24: =BP140 | C24: =BP167 | D24: =BP194
A25: ARPU neto ponderado | B25: =BS140 | C25: =BS167 | D25: =BS194
A26: % meseros activos | B26: =Escenarios!D18 | C26: =Escenarios!E18 | D26: =Escenarios!F18
A27: Marcas por restaurante | B27: =Escenarios!D21 | C27: =Escenarios!E21 | D27: =Escenarios!F21
A28: % Restaurantes Pequeños | B28: =Escenarios!D28 | C28: =Escenarios!E28 | D28: =Escenarios!F28
A29: % Restaurantes Medianos | B29: =Escenarios!D29 | C29: =Escenarios!E29 | D29: =Escenarios!F29
A30: % Restaurantes Grandes | B30: =Escenarios!D30 | C30: =Escenarios!E30 | D30: =Escenarios!F30
A31: % Upgrade de Plan | B31: =Escenarios!D31 | C31: =Escenarios!E31 | D31: =Escenarios!F31
A32: OPEX factor | B32: =Escenarios!D34 | C32: =Escenarios!E34 | D32: =Escenarios!F34
A34: 3. RESULTADOS FINANCIEROS — COMPARATIVO A 60 MESES
A35: Métrica | B35: 🔴 Pesimista | C35: 🟡 Base | D35: 🟢 Optimista | E35: Ratio Opt/Pes
A36: Restaurantes activos (mes 60) | B36: =DG140 | C36: =DG167 | D36: =DG194 | E36: =IF(OR(B36<=0,D36<=0),"n.m.",D36/B36)
A37: Ingresos totales (60m) | B37: =DH140 | C37: =DH167 | D37: =DH194 | E37: =IF(OR(B37<=0,D37<=0),"n.m.",D37/B37)
A38: Costos directos (60m) | B38: =DI140 | C38: =DI167 | D38: =DI194 | E38: =IF(OR(B38<=0,D38<=0),"n.m.",D38/B38)
A39: Utilidad bruta (60m) | B39: =DJ140 | C39: =DJ167 | D39: =DJ194 | E39: =IF(OR(B39<=0,D39<=0),"n.m.",D39/B39)
A40: Margen bruto | B40: =IF(DH140=0,0,DJ140/DH140) | C40: =IF(DH167=0,0,DJ167/DH167) | D40: =IF(DH194=0,0,DJ194/DH194) | E40: =IF(OR(B40<=0,D40<=0),"n.m.",D40/B40)
A41: EBITDA acumulado (60m) | B41: =DK140 | C41: =DK167 | D41: =DK194 | E41: =IF(OR(B41<=0,D41<=0),"n.m.",D41/B41)
A42: Margen EBITDA | B42: =IF(DH140=0,0,DK140/DH140) | C42: =IF(DH167=0,0,DK167/DH167) | D42: =IF(DH194=0,0,DK194/DH194) | E42: =IF(OR(B42<=0,D42<=0),"n.m.",D42/B42)
A43: Utilidad neta (60m) | B43: =DL140 | C43: =DL167 | D43: =DL194 | E43: =IF(OR(B43<=0,D43<=0),"n.m.",D43/B43)
A44: Margen neto | B44: =IF(DH140=0,0,DL140/DH140) | C44: =IF(DH167=0,0,DL167/DH167) | D44: =IF(DH194=0,0,DL194/DH194) | E44: =IF(OR(B44<=0,D44<=0),"n.m.",D44/B44)
A45: Caja final (mes 60) | B45: =DM140 | C45: =DM167 | D45: =DM194 | E45: =IF(OR(B45<=0,D45<=0),"n.m.",D45/B45)
A46: ROI sobre $500K | B46: =DM140/500000 | C46: =DM167/500000 | D46: =DM194/500000 | E46: =IF(OR(B46<=0,D46<=0),"n.m.",D46/B46)
A47: ARR Año 5 | B47: =DN140 | C47: =DN167 | D47: =DN194 | E47: =IF(OR(B47<=0,D47<=0),"n.m.",D47/B47)
A48: EBITDA Año 1 | B48: =DO140 | C48: =DO167 | D48: =DO194 | E48: =IF(OR(B48<=0,D48<=0),"n.m.",D48/B48)
A49: EBITDA Año 5 | B49: =DP140 | C49: =DP167 | D49: =DP194 | E49: =IF(OR(B49<=0,D49<=0),"n.m.",D49/B49)
A50: → Los tres escenarios son rentables y generan caja positiva. Revenue Base concilia 1:1 con modelo principal.
A52: 3.1 UNIT ECONOMICS: ¿QUÉ GENERA CADA RESTAURANTE?
A53: Super Meseros monetiza cada restaurante a través de: (1) fees one-time, (2) fees recurrentes por mesero (ARPU ponderado por segmento), (3) Fee Upgrade de plan, y (4) Super Monedas.
A55: Parámetros unitarios por escenario
A56: Parámetro | B56: 🔴 Pesimista | C56: 🟡 Base | D56: 🟢 Optimista
A57: Meseros ponderados por restaurante | B57: =BP140 | C57: =BP167 | D57: =BP194
A58: % de meseros activos | B58: =Escenarios!D18 | C58: =Escenarios!E18 | D58: =Escenarios!F18
A59: Meseros activos por restaurante | B59: =BP140*Escenarios!D18 | C59: =BP167*Escenarios!E18 | D59: =BP194*Escenarios!F18
A60: ARPU neto ponderado (restaurante) | B60: =BS140 | C60: =BS167 | D60: =BS194
A61: ARPU marcas (por mesero) | B61: =Escenarios!D20 | C61: =Escenarios!E20 | D61: =Escenarios!F20
A62: Marcas promedio por restaurante | B62: =Escenarios!D21 | C62: =Escenarios!E21 | D62: =Escenarios!F21
A63: % Upgrade de Plan | B63: =Escenarios!D31 | C63: =Escenarios!E31 | D63: =Escenarios!F31
A65: Ingresos recurrentes mensuales por restaurante activo
A66: Concepto | B66: 🔴 Pesimista | C66: 🟡 Base | D66: 🟢 Optimista
A67: SaaS Fee Restaurante | B67: =BP140*Escenarios!D18*BS140 | C67: =BP167*Escenarios!E18*BS167 | D67: =BP194*Escenarios!F18*BS194
A68: SaaS Fee Marcas | B68: =BP140*Escenarios!D18*Escenarios!D21*Escenarios!D20 | C68: =BP167*Escenarios!E18*Escenarios!E21*Escenarios!E20 | D68: =BP194*Escenarios!F18*Escenarios!F21*Escenarios!F20
A69: Fee Upgrade de Plan ($50 × %upgrade) | B69: =Escenarios!D31*'Supuestos Generales'!B60 | C69: =Escenarios!E31*'Supuestos Generales'!B60 | D69: =Escenarios!F31*'Supuestos Generales'!B60
A70: Super Monedas Restaurantes (bruto) | B70: =BP140*Escenarios!D18*Escenarios!D22 | C70: =BP167*Escenarios!E18*Escenarios!E22 | D70: =BP194*Escenarios!F18*Escenarios!F22
A71: Super Monedas Marcas (bruto) | B71: =BP140*Escenarios!D18*Escenarios!D21*Escenarios!D23 | C71: =BP167*Escenarios!E18*Escenarios!E21*Escenarios!E23 | D71: =BP194*Escenarios!F18*Escenarios!F21*Escenarios!F23
A72: TOTAL INGRESO RECURRENTE / MES | B72: =SUM(B67:B71) | C72: =SUM(C67:C71) | D72: =SUM(D67:D71)
A73: INGRESO ANUALIZADO 1 RESTAURANTE | B73: =B72*12 | C73: =C72*12 | D73: =D72*12
A74: ="➤ Cada restaurante genera entre "&TEXT(B72,"$#,##0")&" y "&TEXT(D72,"$#,##0")&" mensuales de ingreso recurrente ("&TEXT(B73,"$#,##0")&" a "&TEXT(D73,"$#,##0")&" anualizados)."
A76: 4. P&L RESUMIDO POR AÑO (Escenario Activo)
A77: Concepto | B77: Año 1 | C77: Año 2 | D77: Año 3 | E77: Año 4 | F77: Año 5 | G77: Total 60m
A78: Ingresos Totales | B78: =SUM('Estados Financieros'!B8:M8) | C78: =SUM('Estados Financieros'!N8:Y8) | D78: =SUM('Estados Financieros'!Z8:AK8) | E78: =SUM('Estados Financieros'!AL8:AW8) | F78: =SUM('Estados Financieros'!AX8:BI8) | G78: ='Estados Financieros'!BJ8
A79: Costos Directos | B79: =SUM('Estados Financieros'!B11:M11) | C79: =SUM('Estados Financieros'!N11:Y11) | D79: =SUM('Estados Financieros'!Z11:AK11) | E79: =SUM('Estados Financieros'!AL11:AW11) | F79: =SUM('Estados Financieros'!AX11:BI11) | G79: ='Estados Financieros'!BJ11
A80: Utilidad Bruta | B80: =B78-B79 | C80: =C78-C79 | D80: =D78-D79 | E80: =E78-E79 | F80: =F78-F79 | G80: =G78-G79
A81: Margen Bruto | B81: =IF(B78=0,0,B80/B78) | C81: =IF(C78=0,0,C80/C78) | D81: =IF(D78=0,0,D80/D78) | E81: =IF(E78=0,0,E80/E78) | F81: =IF(F78=0,0,F80/F78) | G81: =IF(G78=0,0,G80/G78)
A82: CAC y GTM | B82: =SUM('Estados Financieros'!B16:M16) | C82: =SUM('Estados Financieros'!N16:Y16) | D82: =SUM('Estados Financieros'!Z16:AK16) | E82: =SUM('Estados Financieros'!AL16:AW16) | F82: =SUM('Estados Financieros'!AX16:BI16) | G82: ='Estados Financieros'!BJ16
A83: OPEX Fijo | B83: =SUM('Estados Financieros'!B21:M21) | C83: =SUM('Estados Financieros'!N21:Y21) | D83: =SUM('Estados Financieros'!Z21:AK21) | E83: =SUM('Estados Financieros'!AL21:AW21) | F83: =SUM('Estados Financieros'!AX21:BI21) | G83: ='Estados Financieros'!BJ21
A84: EBITDA | B84: =SUM('Estados Financieros'!B22:M22) | C84: =SUM('Estados Financieros'!N22:Y22) | D84: =SUM('Estados Financieros'!Z22:AK22) | E84: =SUM('Estados Financieros'!AL22:AW22) | F84: =SUM('Estados Financieros'!AX22:BI22) | G84: ='Estados Financieros'!BJ22
A86: 5. ARR POR AÑO — 3 ESCENARIOS
A87: Año | B87: 🔴 Pesimista | C87: 🟡 Base | D87: 🟢 Optimista
A88: Año 1 | B88: =(INDEX(B154:BI154,12)-INDEX(B150:BI150,12))*12 | C88: =(INDEX(B181:BI181,12)-INDEX(B177:BI177,12))*12 | D88: =(INDEX(B208:BI208,12)-INDEX(B204:BI204,12))*12
A89: Año 2 | B89: =(INDEX(B154:BI154,24)-INDEX(B150:BI150,24))*12 | C89: =(INDEX(B181:BI181,24)-INDEX(B177:BI177,24))*12 | D89: =(INDEX(B208:BI208,24)-INDEX(B204:BI204,24))*12
A90: Año 3 | B90: =(INDEX(B154:BI154,36)-INDEX(B150:BI150,36))*12 | C90: =(INDEX(B181:BI181,36)-INDEX(B177:BI177,36))*12 | D90: =(INDEX(B208:BI208,36)-INDEX(B204:BI204,36))*12
A91: Año 4 | B91: =(INDEX(B154:BI154,48)-INDEX(B150:BI150,48))*12 | C91: =(INDEX(B181:BI181,48)-INDEX(B177:BI177,48))*12 | D91: =(INDEX(B208:BI208,48)-INDEX(B204:BI204,48))*12
A92: Año 5 | B92: =(INDEX(B154:BI154,60)-INDEX(B150:BI150,60))*12 | C92: =(INDEX(B181:BI181,60)-INDEX(B177:BI177,60))*12 | D92: =(INDEX(B208:BI208,60)-INDEX(B204:BI204,60))*12
A93: ARR = Ingreso recurrente del último mes del año × 12. Incluye SaaS fees + Fee Upgrade + Super Monedas.
A95: 6. EBITDA ANUAL — 3 ESCENARIOS
A96: Año | B96: 🔴 Pesimista | C96: 🟡 Base | D96: 🟢 Optimista
A97: Año 1 | B97: =SUM(C163:N163) | C97: =SUM(C190:N190) | D97: =SUM(C217:N217)
A98: Año 2 | B98: =SUM(O163:Z163) | C98: =SUM(O190:Z190) | D98: =SUM(O217:Z217)
A99: Año 3 | B99: =SUM(AA163:AL163) | C99: =SUM(AA190:AL190) | D99: =SUM(AA217:AL217)
A100: Año 4 | B100: =SUM(AM163:AX163) | C100: =SUM(AM190:AX190) | D100: =SUM(AM217:AX217)
A101: Año 5 | B101: =SUM(AY163:BJ163) | C101: =SUM(AY190:BJ190) | D101: =SUM(AY217:BJ217)
A103: 7. MÉTRICAS CLAVE PARA VALUACIÓN
A104: Rondas pre-seed/seed en LATAM SaaS: 0.5x–3x ARR (sin tracción), 3x–8x ARR (con tracción + anchor investor).
A106: Métrica | B106: 🔴 Pesimista | C106: 🟡 Base | D106: 🟢 Optimista
A107: ARR Año 1 | B107: =B88 | C107: =C88 | D107: =D88
A108: ARR Año 2 | B108: =B89 | C108: =C89 | D108: =D89
A109: Valuación @ 1x ARR Año 2 | B109: =B89 | C109: =C89 | D109: =D89
A110: Valuación @ 3x ARR Año 1 | B110: =B88*3 | C110: =C88*3 | D110: =D88*3
A111: Valuación @ 5x ARR Año 1 | B111: =B88*5 | C111: =C88*5 | D111: =D88*5
A112: EBITDA Año 2 | B112: =B98 | C112: =C98 | D112: =D98
A113: Valuación @ 10x EBITDA Año 2 | B113: =B98*10 | C113: =C98*10 | D113: =D98*10
...

Sheet Documentación
A1: DOCUMENTACIÓN DEL MODELO FINANCIERO
A2: Super Meseros — Plataforma SaaS B2B2C para Meseros de Restaurante
A3: Versión 4.0 | Marzo 2026 | Horizonte: 60 meses | Incluye: Ramp-up lineal, Palancas dinámicas, CAC alianzas, Valoración dinámica, Unit Economics, Dashboard, Referidos editables (B68), Comparativo 3 escenarios, Margen SM por escenario, SM params por escenario, Directos ajustados Pes/Base, Segmentación de restaurantes (Pricing v2.5), Fee Upgrade de Plan
A5: TABLA DE CONTENIDOS
A6: 1. Resumen Ejecutivo | B6: Fila 23
A7: 2. Arquitectura del Modelo | B7: Fila 41
A8: 3. Supuestos Generales (Parámetros) | B8: Fila 64
A9: 4. Motor de Onboarding y Crecimiento | B9: Fila 148
A10: 5. Modelo de Ingresos | B10: Fila 221
A11: 6. Estructura de Costos | B11: Fila 253
A12: 7. CAC y Go-to-Market | B12: Fila 297
A13: 8. Estados Financieros (P&L + Cash Flow) | B13: Fila 353
A14: 9. Análisis de Escenarios | B14: Fila 392
A15: 10. Tablas de Sensibilidad | B15: Fila 447
A16: 11. Sistema de Palancas de Crecimiento | B16: Fila 475
A17: 12. Valoración Interactiva | B17: Fila 508 (+12b. Unit Economics: Fila 528)
... A21: 16–19. Supuestos, Guía de Uso, Glosario, Política de Costos | B21: Filas 673+ (16: F673, 17: F701, 18: F726, 19: F746)
A23: 1. RESUMEN EJECUTIVO
A25: Super Meseros es una plataforma SaaS B2B2C que conecta restaurantes, marcas y meseros mediante tecnología, gamificación y Super Monedas. El modelo proyecta 60 meses de operación con crecimiento orgánico en 5 fases + 5 palancas de alianzas estratégicas vinculadas al escenario activo (Pesimista: 2 alianzas CC+ACODRES, Base: 2 alianzas CC+ACODRES, Optimista: 5 alianzas). Las alianzas incorporan un ramp-up lineal gradual (Pes: 24m, Base: 18m, Opt: 12m). El margen de Super Meseros sobre redención de SM es diferenciado por escenario (Pes 10%, Base 15%, Opt 15%). Los 5 parámetros de SM (compra rest/marcas, % redención, breakage, % efectivo) son variables por escenario (v3.8). Directos orgánicos ajustados: Pes 2/4/8/14/20, Base 3/5/9/15/22. Los referidos son editables (Sup.Gen B68=2). Incluye CAC diferenciado para alianzas ($60/rest), hoja de Valoración dinámica con ponderación editable (C23=30% Pipeline), hoja Unit Economics para inversionista, y Dashboard 100% dinámico con 5 gráficos.
A27: MÉTRICAS CLAVE DEL CASO BASE (Escenario Base — 2 alianzas activas: CC + ACODRES a 25 rest/mes, ramp-up 18m, directos 3/5/9/15/22, B68=2, Margen SM 15%, 90 rest/EM, 65 rest/CS)
A29: Métrica | B29: Valor
A30: Total Ingresos (60 meses) | B30: $161,002,698 USD
A31: Total Costos Directos (60 meses) | B31: $96,741,485 USD
A32: Utilidad Bruta (60 meses) | B32: $64,261,213 USD
A33: Margen Bruto promedio | B33: 0.399
A34: EBITDA acumulado (60 meses) | B34: $49,146,081 USD
A35: Margen EBITDA promedio | B35: 0.305
A36: Caja Final (Mes 60) | B36: $32,378,658 USD
A37: Caja Inicial (Funding) | B37: $500,000 USD
A38: ROI sobre inversión inicial | B38: 6,476% ($32.4M / $500K)
A39: Restaurantes activos (Mes 60) | B39: 5383
A41: 2. ARQUITECTURA DEL MODELO
A43: El modelo se compone de 9 hojas interconectadas. Todos los parámetros fluyen desde Supuestos Generales hacia las hojas operativas y financieras.
A45: Hoja | B45: Función
A46: 1. Supuestos Generales | B46: Parámetros centrales del modelo (113 filas)
A47: 2. Onboarding | B47: Crecimiento: restaurantes orgánicos + alianzas + referidos, meseros, marcas
A48: 3. Ingresos | B48: One-Off (SetUp + Entry) + Recurrentes (SaaS + Super Monedas)
A49: 4. Costos Directos | B49: Variables + Engagement + CS (reclasificado de OPEX)
A50: 5. CAC y GTM | B50: Costos de adquisición directos + alianzas ($60/rest), comisiones, publicidad, LTV/CAC
A51: 6. OPEX | B51: Costos fijos con step-ups condicionales a EBITDA + Gerente + Licencia
A52: 7. Estados Financieros | B52: P&L + Cash Flow + KPIs operativos (60 meses + TOTAL)
A53: 8. Escenarios | B53: Selector Pesimista/Base/Optimista + 2 tablas sensibilidad (588 CHOOSE)
A54: 9. Palancas | B54: 5 alianzas con toggle ON/OFF: CC, ACODRES, Bavaria, FEMSA, CC Florida. CAC alianzas $60/rest. Solapamiento 35%.
A55: 10. Valoración | B55: 3 métodos + 3 tablas sensibilidad. Pipeline 76,500 rest (vinculado a Palancas). Unit economics dinámicos con escenario.
A56: 11. Escenarios (resumen) | B56: 5 tablas dinámicas para inversionista: Ingresos semestrales, ARR por año, P&L anual, Crecimiento rest por canal, Unit Economics
... A61: 16. Unit Economics | B61: Simulador unitario por restaurante con input editable (B5), indicador de escenario con colores, escalamiento dinámico
A64: 3. SUPUESTOS GENERALES (PARÁMETROS)
A66: Todos los parámetros se definen en la hoja "Supuestos Generales" y se referencian dinámicamente. Los valores azules son inputs del usuario; los escenarios los sobrescriben via VLOOKUP.
A68: PARÁMETROS GENERALES
A69: Parámetro | B69: Valor
A70: Mes de inicio | B70: 1
A71: Horizonte del modelo | B71: 60 meses (5 años)
A72: Moneda | B72: USD
A73: Caja inicial (funding) | B73: 500000
A75: RAMPA DE ONBOARDING POR FASE
A76: Fase | B76: Pes / Base / Opt
A77: Fase 1 — Piloto (Mes 1–3) | B77: 2 / 3 / 3 restaurantes/mes
A78: Fase 2 — Tracción (Mes 4–6) | B78: 4 / 5 / 6 restaurantes/mes
A79: Fase 3 — Crecimiento (Mes 7–12) | B79: 8 / 9 / 10 restaurantes/mes
A80: Fase 4 — Consolidación (Mes 13–24) | B80: 14 / 15 / 18 restaurantes/mes
A81: Fase 5 — Madurez orgánica (Mes 25–60) | B81: 20 / 22 / 27 restaurantes/mes
A83: RESTAURANTES Y MESEROS
A84: Parámetro | B84: Valor
A85: Churn mensual de restaurantes | B85: 0.03
A86: Meseros promedio por restaurante | B86: 8
A87: % de meseros activos | B87: 0.85
A88: Churn mensual de meseros | B88: 0.05
A90: FEES E INGRESOS
A91: Parámetro | B91: Valor
A92: SetUp Fee por restaurante (one-time) | B92: 500
A93: Entry Fee por restaurante-marca (one-time) | B93: 300
A94: ARPU mensual por mesero (restaurante) | B94: 15
A95: ARPU mensual por mesero (marcas) | B95: 10
A96: Marcas promedio por restaurante | B96: 2.0 (crece 1%/mes)
A98: SEGMENTACIÓN POR TAMAÑO DE RESTAURANTE (Pricing v2.5)
A99: Integrado desde el Modelo de Pricing Super Meseros v2.5. Permite diferenciar fee, meseros y comportamiento por tamaño.
A101: Segmento
A102: Pequeños: Fee Base $12/mes, Meseros típicos 5, Mix varía por escenario (Pes=70%, Base=50%, Opt=35%)
A103: Medianos: Fee Base $25/mes, Meseros típicos 10, Mix varía por escenario (Pes=25%, Base=35%, Opt=35%)
A104: Grandes: Fee Base $45/mes, Meseros típicos 25, Mix varía por escenario (Pes=5%, Base=15%, Opt=30%)
A106: Cálculo ARPU Ponderado
A107: ARPU Bruto = ∑(Fee_Base_i × Mix_i) para i = Peq, Med, Gra
A108: % Descuento = f(meseros ponderados, marcas/rest) — descuento automático por volumen
A109: ARPU Neto = ARPU Bruto × (1 - % Descuento) → Supuestos Generales!B56
A110: Meseros Ponderados = ∑(Meseros_tipicos_i × Mix_i) → Supuestos Generales!B57
A112: Fee Upgrade de Plan
... A120: SUPER MONEDAS
A121: Parámetro | B121: Valor
A122: Compra Super Monedas por restaurante | B122: Pes $25 / Base $35 / Opt $50 por mesero/mes
A123: Compra Super Monedas por marca | B123: Pes $10 / Base $20 / Opt $25 por mesero/mes
A124: % redimidas por meseros | B124: Pes 90% / Base 85% / Opt 80%
A125: % breakage (vencen) | B125: Pes 8% / Base 10% / Opt 12% → ingreso directo
A126: Margen sobre redención | B126: Pes 10% / Base 15% / Opt 15% (v3.9 — antes Pes 8%/Base 12%)
A128: COSTOS DIRECTOS
A129: Parámetro | B129: Valor
A130: Provisión errores humanos (% Super Monedas) | B130: 0.015
A131: Provisión fraude (% Super Monedas) | B131: 0.01
A132: Total provisión errores + fraude | B132: 2.5% del bruto transaccionado
A134: Nota: Se provisiona sobre el total de Super Monedas transaccionadas (restaurantes + marcas).
A135: Errores = asignación manual incorrecta de Super Monedas.
...

Sheet Escenarios
A1: ESCENARIOS Y SENSIBILIDAD | H1: 📖 GUÍA PARA EL INVERSIONISTA
A3: SELECTOR DE ESCENARIO | H3: ¿QUÉ ES ESTA HOJA?
A4: Escenario activo → | B4: 1 | C4: ← Cambiar: 1 = Pesimista, 2 = Base, 3 = Optimista | H4: Esta hoja le permite explorar tres versiones del futuro de Super Meseros: una pesimista, una base (la más probable) y una optimista. Cada escenario usa supuestos diferentes sobre cuántos restaurantes se suman, cuántos se van, cuánto pagan y cuánto cuesta operar.
A5: Escenario seleccionado: | B5: =CHOOSE(B4,"PESIMISTA","BASE (actual)","OPTIMISTA")
A7: PARÁMETROS POR ESCENARIO | D7: Pesimista | E7: Base | F7: Optimista | G7: =HYPERLINK("#Escenarios!H1","📖 Ver Guía para el Inversionista →")
A8: ONBOARDING | H8: ¿CÓMO SE USA?
A9: Directos/mes — Fase 1 (Piloto) | B9: rest/mes | C9: =HYPERLINK("#'Supuestos Generales'!B12","→ Sup.Gen B12") | D9: 2 | E9: 3 | F9: 3 | H9: Paso 1 → Cambie el número en la celda B4 (amarilla, arriba a la izquierda):
A10: Directos/mes — Fase 2 (Tracción) | B10: rest/mes | C10: =HYPERLINK("#'Supuestos Generales'!B13","→ Sup.Gen B13") | D10: 4 | E10: 5 | F10: 6 | H10: 1 = Pesimista | 2 = Base (actual) | 3 = Optimista
A11: Directos/mes — Fase 3 (Crecimiento) | B11: rest/mes | C11: =HYPERLINK("#'Supuestos Generales'!B14","→ Sup.Gen B14") | D11: 8 | E11: 9 | F11: 10 | H11: Al cambiar ese número, TODO el modelo financiero se recalcula automáticamente: ingresos, costos, márgenes, caja y los resultados de la sección "Resultados del Escenario Activo" (filas 28-41).
A12: Directos/mes — Fase 4 (Consolidación) | B12: rest/mes | C12: =HYPERLINK("#'Supuestos Generales'!B15","→ Sup.Gen B15") | D12: 14 | E12: 15 | F12: 18
A13: Directos/mes — Fase 5 (Madurez orgánica) | B13: rest/mes | C13: =HYPERLINK("#'Supuestos Generales'!B16","→ Sup.Gen B16") | D13: 20 | E13: 22 | F13: 27 | H13: Paso 2 → Revise la sección "Parámetros por Escenario" (filas 7-26):
H14: Aquí verá los supuestos que alimentan cada escenario en tres columnas: D (Pesimista en rosado), E (Base en verde) y F (Optimista en azul). Estos valores SÍ son editables: si quiere probar qué pasa con un churn de 4% en vez de 3%, simplemente cambie el valor en la celda correspondiente y el modelo se ajustará.
A15: UNIT ECONOMICS
A16: Meseros promedio por restaurante | B16: # | C16: =HYPERLINK("#'Supuestos Generales'!B41","→ Ahora por segmentos (Sup.Gen B41:B52)") | D16: 5 | E16: 8 | F16: 10
A17: Churn mensual restaurantes | B17: % | C17: =HYPERLINK("#'Supuestos Generales'!B18","→ Sup.Gen B18 (fórmula)") | D17: 0.05 | E17: 0.03 | F17: 0.02 | H17: Paso 3 → Consulte los resultados (filas 28-41):
A18: % meseros activos | B18: % | C18: =HYPERLINK("#'Supuestos Generales'!B20","→ Sup.Gen B20 (fórmula)") | D18: 0.75 | E18: 0.85 | F18: 0.95 | H18: Esta sección muestra el resumen financiero a 60 meses del escenario activo: ingresos totales, EBITDA, utilidad neta, caja final, restaurantes activos y el mes en que se alcanza EBITDA positivo. Todos estos valores se actualizan solos al cambiar B4 o cualquier parámetro.
A19: ARPU restaurante (USD/mesero) | B19: USD | C19: =HYPERLINK("#'Supuestos Generales'!B41","→ Ahora por segmentos (Sup.Gen B41:B56)") | D19: 10 | E19: 15 | F19: 20
A20: ARPU marcas (USD/mesero) | B20: USD | C20: =HYPERLINK("#'Supuestos Generales'!B27","→ Sup.Gen B27 (fórmula)") | D20: 7 | E20: 10 | F20: 15
A21: Marcas promedio por restaurante | B21: # | C21: =HYPERLINK("#'Supuestos Generales'!B28","→ Sup.Gen B28 (fórmula)") | D21: 1 | E21: 2 | F21: 3 | H21: ¿QUÉ SIGNIFICAN LOS PARÁMETROS?
A22: SM compra por restaurante (USD/mesero/mes) | B22: USD | C22: → Sup.Gen B31 (fórmula) | D22: 25 | E22: 35 | F22: 50
A23: SM compra por marca (USD/mesero/mes) | B23: USD | C23: → Sup.Gen B32 (fórmula) | D23: 10 | E23: 20 | F23: 25
A24: % SM redimidas por meseros | B24: % | C24: → Sup.Gen B33 (fórmula) | D24: 0.9 | E24: 0.85 | F24: 0.8
A25: % breakage (SM que vencen) | B25: % | C25: → Sup.Gen B34 (fórmula) | D25: 0.08 | E25: 0.1 | F25: 0.12
A26: % redenciones en efectivo | B26: % | C26: → Sup.Gen B36 (fórmula) | D26: 0.8 | E26: 0.7 | F26: 0.6
A27: SEGMENTACIÓN | C27: =HYPERLINK("#'Supuestos Generales'!B41","→ Sup.Gen B41:B43 (fórmula)")
A28: % Restaurantes Pequeños | B28: % | C28: =HYPERLINK("#'Supuestos Generales'!B41","→ Sup.Gen B41 (fórmula)") | D28: 0.7 | E28: 0.5 | F28: 0.35
A29: % Restaurantes Medianos | B29: % | C29: =HYPERLINK("#'Supuestos Generales'!B42","→ Sup.Gen B42 (fórmula)") | D29: 0.25 | E29: 0.35 | F29: 0.35
A30: % Restaurantes Grandes | B30: % | C30: =HYPERLINK("#'Supuestos Generales'!B43","→ Sup.Gen B43 (fórmula)") | D30: 0.05 | E30: 0.15 | F30: 0.3
A31: % Restaurantes que hacen upgrade | B31: % | C31: =HYPERLINK("#'Supuestos Generales'!B59","→ Sup.Gen B59 (fórmula)") | D31: 0.05 | E31: 0.1 | F31: 0.2
H32: ONBOARDING (filas 9-13): Cuántos restaurantes nuevos se captan por mes en cada fase de crecimiento. Fase 1 es el piloto inicial; Fase 5 es escala completa.
A33: COSTOS Y OPEX
A34: Factor escala OPEX fijo | B34: x | C34: =HYPERLINK("#'Supuestos Generales'!B105","→ Sup.Gen B105 (fórmula)") | D34: 0.46 | E34: 1 | F34: 2 | H34: UNIT ECONOMICS (filas 16-20): Las métricas unitarias del negocio. Churn = % de restaurantes que se van cada mes. ARPU = ingreso promedio mensual por mesero activo. Marcas = cuántas marcas patrocinan por restaurante.
A35: Crecimiento semestral OPEX | B35: % | C35: =HYPERLINK("#'Supuestos Generales'!B102","→ Sup.Gen B102 (fórmula)") | D35: 0.15 | E35: 0.1 | F35: 0.08
A36: Soporte por restaurante | B36: USD | C36: =HYPERLINK("#'Supuestos Generales'!B49","→ Sup.Gen B49 (fórmula)") | D36: 30 | E36: 25 | F36: 20 | H36: COSTOS Y OPEX (filas 23-26): OPEX base = gasto fijo mensual (equipo, tecnología, legal). Crecimiento OPEX = cuánto sube cada semestre. Soporte = costo de atender cada restaurante. Caja inicial = capital disponible al arrancar.
A37: Restaurantes por EM | B37: # | C37: =HYPERLINK("#'Supuestos Generales'!B59","→ Sup.Gen B59 (fórmula)") | D37: 75 | E37: 90 | F37: 100
A38: Restaurantes por Agente CS | B38: # | C38: =HYPERLINK("#'Supuestos Generales'!B50","→ Sup.Gen B50 (fórmula)") | D38: 50 | E38: 65 | F38: 80
A39: Margen Super Meseros sobre redención | B39: % | C39: → Sup.Gen B35 (fórmula) | D39: 0.1 | E39: 0.15 | F39: 0.15
A40: Caja inicial (funding) | B40: USD | C40: =HYPERLINK("#'Supuestos Generales'!B8","→ Sup.Gen B8 (editable)") | D40: 500000 | E40: 500000 | F40: 500000
A43: PALANCAS DE ALIANZAS
A44: Toggle Coca-Cola | B44: 0/1 | C44: → Palancas B10 | D44: 1 | E44: 1 | F44: 1
A45: Toggle ACODRES | B45: 0/1 | C45: → Palancas F10 | D45: 1 | E45: 1 | F45: 1
A46: Toggle Bavaria | B46: 0/1 | C46: → Palancas B18 | D46: 0 | E46: 0 | F46: 1
A47: Toggle FEMSA | B47: 0/1 | C47: → Palancas F18 | D47: 0 | E47: 0 | F47: 1
A48: Toggle CC Florida | B48: 0/1 | C48: → Palancas B26 | D48: 0 | E48: 0 | F48: 1
A49: Rest/mes por alianza (grandes) | B49: rest/mes | C49: → Palancas (CC,ACO,BAV,FEMSA) | D49: 15 | E49: 25 | F49: 35
A50: Rest/mes CC Florida | B50: rest/mes | C50: → Palancas B29 | D50: 5 | E50: 10 | F50: 15
A51: Meses ramp-up alianzas | B51: meses | C51: → Palancas (ramp-up gradual) | D51: 24 | E51: 18 | F51: 12
A52: RESULTADOS DEL ESCENARIO ACTIVO | H52: ¿QUÉ SON LAS TABLAS DE SENSIBILIDAD?
A53: Escenario: | B53: =B5 | H53: Las tablas más abajo (filas 44-65) responden la pregunta: "¿Qué tanto cambia el resultado si un supuesto clave resulta diferente al esperado?"
A54: Total Ingresos (60m) | B54: ='Estados Financieros'!BJ8
A55: Total Costos Directos (60m) | B55: ='Estados Financieros'!BJ11 | H55: TABLA 1 — EBITDA Acumulado: Muestra cuánta ganancia operativa genera el negocio en 60 meses combinando distintos niveles de churn (filas) con distintos niveles de ARPU (columnas). Los colores van de rojo (peor) a verde (mejor).
A56: Utilidad Bruta (60m) | B56: ='Estados Financieros'!BJ13
A57: Margen Bruto promedio | B57: =IF(B54=0,0,B56/B54) | H57: TABLA 2 — Caja Final: Muestra cuánto efectivo queda en caja al mes 60 combinando distintas velocidades de crecimiento del OPEX (filas) con distintos ritmos de captación de restaurantes (columnas). La celda amarilla marca el caso base actual.
A58: EBITDA acumulado (60m) | B58: ='Estados Financieros'!BJ22
A59: Margen EBITDA promedio | B59: =IF(B54=0,0,B58/B54) | H59: Ambas tablas cambian automáticamente al seleccionar otro escenario en B4. Los colores van de verde (resultado favorable) a rojo (resultado desfavorable) para facilitar la lectura visual.
A60: Impuestos acumulados (60m) | B60: ='Estados Financieros'!BJ24
A61: Utilidad Neta acumulada (60m) | B61: ='Estados Financieros'!BJ25
A62: Margen Neto promedio | B62: =IF(B54=0,0,B61/B54) | H62: ⚠️ NOTA IMPORTANTE
A63: Caja Final mes 60 | B63: ='Estados Financieros'!BJ31 | H63: Si usted modifica manualmente algún valor en D9:F26, los Resultados (filas 28-41) se actualizarán al instante. Sin embargo, las Tablas de Sensibilidad fueron pre-calculadas con los supuestos originales y NO se recalculan solas. Para regenerarlas con sus nuevos valores, solicite al equipo financiero ejecutar la simulación de sensibilidad.
A64: Restaurantes activos mes 60 | B64: ='Estados Financieros'!BI35
A65: Mes EBITDA positivo | B65: {=MATCH(1,INDEX(('Estados Financieros'!B22:BI22>0)*1,0),0)}
A67: TABLAS DE SENSIBILIDAD
A68: TABLA 1: EBITDA Acumulado (60m)
A69: Churn mensual ↓ / ARPU Restaurante →
B70: 8 | C70: 10 | D70: 12 | E70: 15 | F70: 18 | G70: 20 | H70: 25
A71: 1.0% | B71: =CHOOSE($B$4,-955750,55282470,409843242) | C71: =CHOOSE($B$4,-229189,57623807,416811908) | D71: =CHOOSE($B$4,482393,59965143,423390962) | E71: =CHOOSE($B$4,1479574,63477148,433843960) | F71: =CHOOSE($B$4,2743440,66989153,444296959) | G71: =CHOOSE($B$4,3586017,69330490,451265624) | H71: =CHOOSE($B$4,5507765,75183831,468687288)
A72: 2.0% | B72: =CHOOSE($B$4,-676245,48514966,360342089) | C72: =CHOOSE($B$4,-120430,50527856,366371770) | D72: =CHOOSE($B$4,527869,52540746,372401452) | E72: =CHOOSE($B$4,1349528,55560081,381056362) | F72: =CHOOSE($B$4,2437871,58579416,390100883) | G72: =CHOOSE($B$4,3163434,60592306,396130564) | H72: =CHOOSE($B$4,4792646,65624531,411204767)
A73: 2.5% | B73: =CHOOSE($B$4,-553319,45646965,339177674) | C73: =CHOOSE($B$4,-125378,47520301,344804731) | D73: =CHOOSE($B$4,431792,49393637,350431787) | E73: =CHOOSE($B$4,1295315,52203642,358482760) | F73: =CHOOSE($B$4,2307742,55013646,366923345) | G73: =CHOOSE($B$4,2982694,56886982,372550402) | H73: =CHOOSE($B$4,4485377,61570323,386618043)
A74: 3.0% | B74: =CHOOSE($B$4,-464291,43035241,320109603) | C74: =CHOOSE($B$4,-67704,44781196,325372789) | D74: =CHOOSE($B$4,444657,46527150,330635976) | E74: =CHOOSE($B$4,1240966,49146081,338530757) | F74: =CHOOSE($B$4,2186180,51765012,346035925) | G74: =CHOOSE($B$4,2816322,53510966,351299112) | H74: =CHOOSE($B$4,4206984,57875852,364457079)
A75: 3.5% | B75: =CHOOSE($B$4,-368045,40718478,302827187) | C75: =CHOOSE($B$4,-11460,42350811,307760035) | D75: =CHOOSE($B$4,460899,43983144,312692883) | E75: =CHOOSE($B$4,1197205,46431643,320092155) | F75: =CHOOSE($B$4,2082416,48880143,327101815) | G75: =CHOOSE($B$4,2672556,50512475,332034663) | H75: =CHOOSE($B$4,3963213,54593308,344366784)
A76: 4.0% | B76: =CHOOSE($B$4,-290443,38612836,287129318) | C76: =CHOOSE($B$4,58043,40142121,291761477) | D76: =CHOOSE($B$4,479919,41671407,296393637) | E76: =CHOOSE($B$4,1174139,43965334,303341876) | F76: =CHOOSE($B$4,2003808,46259262,309900503) | G76: =CHOOSE($B$4,2556921,47788547,314532662) | H76: =CHOOSE($B$4,3755009,51611760,326113060)
A77: 5.0% | B77: =CHOOSE($B$4,-218078,34965666,259944454) | C77: =CHOOSE($B$4,139736,36314907,264054340) | D77: =CHOOSE($B$4,361859,37664147,268164227) | E77: =CHOOSE($B$4,1095071,39688008,274329056) | F77: =CHOOSE($B$4,1828283,41711869,280104274) | G77: =CHOOSE($B$4,2317092,43061110,284214161) | H77: =CHOOSE($B$4,3354418,46434212,294488877)
A80: TABLA 2: Caja Final (Mes 60)
A81: Crecimiento OPEX semestral ↓ / Multiplicador ritmo onboarding →
B82: 0.5x | C82: 0.7x | D82: 0.85x | E82: 1.0x | F82: 1.15x | G82: 1.3x | H82: 1.5x
A83: 5% | B83: =CHOOSE($B$4,304428,27524091,236399708) | C83: =CHOOSE($B$4,428930,29441680,245128698) | D83: =CHOOSE($B$4,527411,31285632,251763233) | E83: =CHOOSE($B$4,612700,32702240,258378437) | F83: =CHOOSE($B$4,708294,34131997,265487125) | G83: =CHOOSE($B$4,802109,36206601,271719425) | H83: =CHOOSE($B$4,880230,38261814,281817214)
A84: 7% | B84: =CHOOSE($B$4,283615,27403498,236158522) | C84: =CHOOSE($B$4,408443,29321087,244887512) | D84: =CHOOSE($B$4,506924,31165038,251522047) | E84: =CHOOSE($B$4,592213,32581647,258064464) | F84: =CHOOSE($B$4,687807,34011404,265173151) | G84: =CHOOSE($B$4,781622,36086008,271405451) | H84: =CHOOSE($B$4,838270,38141221,281503241)
A85: 8% | B85: =CHOOSE($B$4,295950,27338910,236029346) | C85: =CHOOSE($B$4,397794,29256499,244758336) | D85: =CHOOSE($B$4,496275,31100451,251392871) | E85: =CHOOSE($B$4,581565,32517059,257894590) | F85: =CHOOSE($B$4,677158,33946816,265003277) | G85: =CHOOSE($B$4,770973,36021420,271235577) | H85: =CHOOSE($B$4,816037,38076634,281333367)
A86: 10% | B86: =CHOOSE($B$4,280564,27200509,235752545) | C86: =CHOOSE($B$4,375657,29118098,244481534) | D86: =CHOOSE($B$4,474138,30962050,251116069) | E86: =CHOOSE($B$4,559427,32378658,257526796) | F86: =CHOOSE($B$4,655021,33808415,264635484) | G86: =CHOOSE($B$4,748836,35883020,270867784) | H86: =CHOOSE($B$4,818370,37938233,280965573)
A87: 12% | B87: =CHOOSE($B$4,264592,27048893,235449313) | C87: =CHOOSE($B$4,352359,28966482,244178303) | D87: =CHOOSE($B$4,450840,30810434,250812838) | E87: =CHOOSE($B$4,536130,32227042,257118329) | F87: =CHOOSE($B$4,631723,33656800,264227017) | G87: =CHOOSE($B$4,725539,35731404,270459316) | H87: =CHOOSE($B$4,781486,37786617,280557106)
A88: 15% | B88: =CHOOSE($B$4,239366,26794102,234939731) | C88: =CHOOSE($B$4,315041,28711691,243668721) | D88: =CHOOSE($B$4,413610,30555643,250303256) | E88: =CHOOSE($B$4,498899,31972251,256419941) | F88: =CHOOSE($B$4,594492,33402009,263528628) | G88: =CHOOSE($B$4,688308,35476613,269760928) | H88: =CHOOSE($B$4,721785,37531826,279858718)
A89: 20% | B89: =CHOOSE($B$4,192993,26285447,233922421) | C89: =CHOOSE($B$4,243566,28203036,242651410) | D89: =CHOOSE($B$4,345032,30046988,249285945) | E89: =CHOOSE($B$4,430322,31463596,254986407) | F89: =CHOOSE($B$4,525915,32893353,262095095) | G89: =CHOOSE($B$4,619731,34967957,268327395) | H89: =CHOOSE($B$4,609488,37023171,278425184)
A91: Notas:
A92: • Celda amarilla = caso base (parámetros actuales del modelo)
A93: • Tabla 1: Varía churn mensual (1%-5%) y ARPU por mesero ($8-$25)
A94: • Tabla 2: Varía crecimiento semestral OPEX (5%-20%) y velocidad de onboarding (0.5x-1.5x del plan base)

Sheet Palancas
A1: PALANCAS DE CRECIMIENTO — Alianzas Estratégicas | F1: ⚡ ESCENARIO
A2: Toggles y velocidades controlados por escenario (Escenarios!B4). Para override manual: editar valores en Escenarios filas 32-38. | F2: =CHOOSE(Escenarios!B4,"PESIMISTA","BASE","OPTIMISTA")
F3: =HYPERLINK("#Escenarios!B4","✏️ Cambiar escenario →")
A4: MODO DE CONTROL | B4: AUTOMÁTICO | C4: ← Toggles y velocidades controlados por escenario. Para override: editar valores en Escenarios filas 32-38.
A6: PARÁMETROS GLOBALES
A7: % Solapamiento entre alianzas | B7: 0.35 | C7: ← Editable
A8: Pipeline neto total (ajust. solapamiento) | B8: =ROUND((B14+F14+B22)*(1-B7)+F22+B30, 0) | C8: restaurantes
A9: CAC por restaurante vía alianzas | B9: 60 | C9: USD / rest
A10: Meses ramp-up alianzas | B10: =CHOOSE(Escenarios!$B$4,Escenarios!$D$51,Escenarios!$E$51,Escenarios!$F$51) | C10: meses
A12: COCA-COLA | B12: Valor | E12: ACODRES | F12: Valor
A13: Toggle ON/OFF | B13: =CHOOSE(Escenarios!$B$4,Escenarios!$D$44,Escenarios!$E$44,Escenarios!$F$44) | C13: 1=ON, 0=OFF | E13: Toggle ON/OFF | F13: =CHOOSE(Escenarios!$B$4,Escenarios!$D$45,Escenarios!$E$45,Escenarios!$F$45) | G13: 1=ON, 0=OFF
A14: Pipeline total | B14: 5000 | C14: rest | E14: Pipeline total | F14: 12000 | G14: rest
A15: Mes de activación | B15: 6 | C15: mes | E15: Mes de activación | F15: 6 | G15: mes
A16: Restaurantes/mes | B16: =CHOOSE(Escenarios!$B$4,Escenarios!$D$49,Escenarios!$E$49,Escenarios!$F$49) | C16: rest/mes | E16: Restaurantes/mes | F16: =CHOOSE(Escenarios!$B$4,Escenarios!$D$49,Escenarios!$E$49,Escenarios!$F$49) | G16: rest/mes
A17: Pipeline neto (ajust. solap.) | B17: =ROUND(B14*(1-$B$7), 0) | C17: rest | E17: Pipeline neto (ajust. solap.) | F17: =ROUND(F14*(1-$B$7), 0) | G17: rest
A18: Meses para agotar pipeline | B18: =IF(B16=0,"-",CEILING(B17/B16,1)) | C18: meses | E18: Meses para agotar pipeline | F18: =IF(F16=0,"-",CEILING(F17/F16,1)) | G18: meses
A20: BAVARIA | B20: Valor | E20: FEMSA VENTURES (México) | F20: Valor
A21: Toggle ON/OFF | B21: =CHOOSE(Escenarios!$B$4,Escenarios!$D$46,Escenarios!$E$46,Escenarios!$F$46) | C21: 1=ON, 0=OFF | E21: Toggle ON/OFF | F21: =CHOOSE(Escenarios!$B$4,Escenarios!$D$47,Escenarios!$E$47,Escenarios!$F$47) | G21: 1=ON, 0=OFF
A22: Pipeline total | B22: 4500 | C22: rest | E22: Pipeline total | F22: 50000 | G22: rest
A23: Mes de activación | B23: 12 | C23: mes | E23: Mes de activación | F23: 24 | G23: mes
A24: Restaurantes/mes | B24: =CHOOSE(Escenarios!$B$4,Escenarios!$D$49,Escenarios!$E$49,Escenarios!$F$49) | C24: rest/mes | E24: Restaurantes/mes | F24: =CHOOSE(Escenarios!$B$4,Escenarios!$D$49,Escenarios!$E$49,Escenarios!$F$49) | G24: rest/mes
A25: Pipeline neto (ajust. solap.) | B25: =ROUND(B22*(1-$B$7), 0) | C25: rest | E25: Pipeline neto (sin solapamiento) | F25: =F22 | G25: rest
A26: Meses para agotar pipeline | B26: =IF(B24=0,"-",CEILING(B25/B24,1)) | C26: meses | E26: Meses para agotar pipeline | F26: =IF(F24=0,"-",CEILING(F25/F24,1)) | G26: meses
A28: COCA-COLA FLORIDA (USA) | B28: Valor
A29: Toggle ON/OFF | B29: =CHOOSE(Escenarios!$B$4,Escenarios!$D$48,Escenarios!$E$48,Escenarios!$F$48) | C29: 1=ON, 0=OFF
A30: Pipeline total | B30: 5000 | C30: rest
A31: Mes de activación | B31: 36 | C31: mes
A32: Restaurantes/mes | B32: =CHOOSE(Escenarios!$B$4,Escenarios!$D$50,Escenarios!$E$50,Escenarios!$F$50) | C32: rest/mes
A33: Pipeline neto (sin solapamiento) | B33: =B30 | C33: rest
A34: Mes fin (auto por pipeline) | B34: =IF(B32=0,60,MIN(60,B31+CEILING(B30/B32,1)-1)) | C34: mes
A35: Meses para agotar pipeline | B35: =IF(B32=0,"-",CEILING(B33/B32,1)) | C35: meses

Sheet Supuestos Generales
A1: SUPUESTOS GENERALES
A2: Super Meseros - SaaS B2B2C - Plataforma Gamificada de Motivación y Reconocimiento para Meseros
A4: PARÁMETROS GENERALES | B4: Valor | C4: Notas
A5: Mes de inicio | B5: 1 | C5: Mes 1 = inicio de operaciones
A6: Horizonte del modelo (meses) | B6: 60 | C6: 5 años de proyección mensual
A7: Moneda | B7: USD | C7: Dólares americanos
A8: Caja inicial (funding) | B8: 500000 | C8: Capital semilla / pre-seed
A10: RESTAURANTES Y ONBOARDING | B10: Valor | C10: Notas
A11: Rampa de onboarding por fase | B11: Mes inicio | C11: Mes fin | D11: Directos/mes
A12: Fase 1 — Piloto | B12: =CHOOSE(Escenarios!$B$4,Escenarios!$D$9,Escenarios!$E$9,Escenarios!$F$9) | C12: 3 | D12: =CHOOSE(Escenarios!$B$4,Escenarios!$D$9,Escenarios!$E$9,Escenarios!$F$9) | E12: =HYPERLINK("#Escenarios!D9","→ Modificar en Escenarios!D9:F9")
A13: Fase 2 — Tracción | B13: =CHOOSE(Escenarios!$B$4,Escenarios!$D$10,Escenarios!$E$10,Escenarios!$F$10) | C13: 6 | D13: =CHOOSE(Escenarios!$B$4,Escenarios!$D$10,Escenarios!$E$10,Escenarios!$F$10) | E13: =HYPERLINK("#Escenarios!D10","→ Modificar en Escenarios!D10:F10")
A14: Fase 3 — Crecimiento | B14: =CHOOSE(Escenarios!$B$4,Escenarios!$D$11,Escenarios!$E$11,Escenarios!$F$11) | C14: 12 | D14: =CHOOSE(Escenarios!$B$4,Escenarios!$D$11,Escenarios!$E$11,Escenarios!$F$11) | E14: =HYPERLINK("#Escenarios!D11","→ Modificar en Escenarios!D11:F11")
A15: Fase 4 — Consolidación | B15: =CHOOSE(Escenarios!$B$4,Escenarios!$D$12,Escenarios!$E$12,Escenarios!$F$12) | C15: 24 | D15: =CHOOSE(Escenarios!$B$4,Escenarios!$D$12,Escenarios!$E$12,Escenarios!$F$12) | E15: =HYPERLINK("#Escenarios!D12","→ Modificar en Escenarios!D12:F12")
A16: Fase 5 — Madurez orgánica | B16: =CHOOSE(Escenarios!$B$4,Escenarios!$D$13,Escenarios!$E$13,Escenarios!$F$13) | C16: 60 | D16: =CHOOSE(Escenarios!$B$4,Escenarios!$D$13,Escenarios!$E$13,Escenarios!$F$13) | E16: =HYPERLINK("#Escenarios!D13","→ Modificar en Escenarios!D13:F13")
A18: Churn mensual de restaurantes (%) | B18: =CHOOSE(Escenarios!$B$4,Escenarios!$D$17,Escenarios!$E$17,Escenarios!$F$17) | C18: % de restaurantes que salen por mes | D18: =HYPERLINK("#Escenarios!D16","→ Modificar en Escenarios!D16:F16")
A19: Meseros promedio por restaurante | B19: =B57 | C19: Promedio de meseros por restaurante | D19: → Modificar en Escenarios!D16:F16
A20: % de meseros activos | B20: =CHOOSE(Escenarios!$B$4,Escenarios!$D$18,Escenarios!$E$18,Escenarios!$F$18) | C20: Meseros que usan activamente la plataforma | D20: =HYPERLINK("#Escenarios!D17","→ Modificar en Escenarios!D17:F17")
A21: Churn mensual de meseros (%) | B21: 0.05 | C21: Rotación natural de meseros
A23: FEES E INGRESOS | B23: Valor | C23: Notas
A24: SetUp Fee por restaurante (one-time) | B24: 500 | C24: Cobro único al incorporar restaurante
A25: Entry Fee por restaurante-marca (one-time) | B25: 300 | C25: Cobro a marca por entrar en un restaurante
A26: ARPU mensual por mesero (restaurante) | B26: =B56 | C26: ← Ahora calculado por mix de segmentos (ver fila 56) | D26: =HYPERLINK("#'Supuestos Generales'!B41","→ Modificar mix en B41:B43, fees en B46:B48")
A27: ARPU mensual por mesero (marcas) | B27: =CHOOSE(Escenarios!$B$4,Escenarios!$D$20,Escenarios!$E$20,Escenarios!$F$20) | C27: Fee recurrente cobrado a marcas | D27: =HYPERLINK("#Escenarios!D19","→ Modificar en Escenarios!D19:F19")
A28: Marcas promedio por restaurante | B28: =CHOOSE(Escenarios!$B$4,Escenarios!$D$21,Escenarios!$E$21,Escenarios!$F$21) | C28: Número de marcas activas por restaurante | D28: =HYPERLINK("#Escenarios!D20","→ Modificar en Escenarios!D20:F20")
A29: Crecimiento mensual de marcas/restaurante (%) | B29: 0.01 | C29: Aumento gradual de marcas por restaurante
A30: — SUPER MONEDAS —
A31: Compra de Super Monedas por restaurante (USD/mes/mesero) | B31: =CHOOSE(Escenarios!$B$4,Escenarios!$D$22,Escenarios!$E$22,Escenarios!$F$22) | C31: Monto que restaurantes compran en monedas por mesero
A32: Compra de Super Monedas por marca (USD/mes/mesero) | B32: =CHOOSE(Escenarios!$B$4,Escenarios!$D$23,Escenarios!$E$23,Escenarios!$F$23) | C32: Monto que marcas compran en monedas por mesero
A33: % de Super Monedas redimidas por meseros | B33: =CHOOSE(Escenarios!$B$4,Escenarios!$D$24,Escenarios!$E$24,Escenarios!$F$24) | C33: Porcentaje que los meseros efectivamente canjean
A34: % de Super Monedas que vencen (breakage) | B34: =CHOOSE(Escenarios!$B$4,Escenarios!$D$25,Escenarios!$E$25,Escenarios!$F$25) | C34: Monedas no redimidas = ingreso para Super Meseros
A35: Margen de Super Meseros sobre redención (%) | B35: =CHOOSE(Escenarios!$B$4,Escenarios!$D$39,Escenarios!$E$39,Escenarios!$F$39) | C35: Ingreso neto = 20% de lo que meseros redimen
A36: % de redenciones Super Monedas en efectivo | B36: =CHOOSE(Escenarios!$B$4,Escenarios!$D$26,Escenarios!$E$26,Escenarios!$F$26) | C36: % de meseros que canjean monedas por dinero en efectivo
A37: Tasa pasarela de pago (%) | B37: 0.035 | C37: Comisión procesador de pagos sobre transacciones
A38: Tasa de impuestos sobre utilidades (%) | B38: 0.35 | C38: Impuesto de renta corporativo (Colombia)
A39: SEGMENTACIÓN DE RESTAURANTES | B39: Valor | C39: Notas
A40: — Mix de Segmentos (% del total de restaurantes) —
A41: % Restaurantes Pequeños (Plan Light) | B41: =CHOOSE(Escenarios!$B$4,Escenarios!$D$28,Escenarios!$E$28,Escenarios!$F$28) | C41: Ventas $10K-$80K/mes, 5 meseros típicos | D41: =HYPERLINK("#Escenarios!D28","→ Modificar en Escenarios!D28:F28")
A42: % Restaurantes Medianos (Plan Standard) | B42: =CHOOSE(Escenarios!$B$4,Escenarios!$D$29,Escenarios!$E$29,Escenarios!$F$29) | C42: Ventas $80K-$200K/mes, 10 meseros típicos | D42: =HYPERLINK("#Escenarios!D29","→ Modificar en Escenarios!D29:F29")
A43: % Restaurantes Grandes (Plan Premium) | B43: =CHOOSE(Escenarios!$B$4,Escenarios!$D$30,Escenarios!$E$30,Escenarios!$F$30) | C43: Ventas $200K-$500K/mes, 25 meseros típicos | D43: =HYPERLINK("#Escenarios!D30","→ Modificar en Escenarios!D30:F30")
A44: Validación mix | B44: =B41+B42+B43 | C44: =IF(B44=1,"✓ Suma 100%","⚠️ NO suma 100%")
A45: — Fee Base por Segmento (USD/mesero/mes) —
A46: Fee Base — Pequeño | B46: 12 | C46: Pricing v2.5 — Plan Light
A47: Fee Base — Mediano | B47: 25 | C47: Pricing v2.5 — Plan Standard
A48: Fee Base — Grande | B48: 45 | C48: Pricing v2.5 — Plan Premium
A49: — Meseros Típicos por Segmento —
A50: Meseros típicos — Pequeño | B50: 5 | C50: Mínimo 5 meseros por restaurante
A51: Meseros típicos — Mediano | B51: 10 | C51: Rango 8-15 meseros
A52: Meseros típicos — Grande | B52: 25 | C52: Rango 15-50+ meseros
A53: — Métricas Calculadas (Ponderadas por Mix) —
A54: ARPU Bruto ponderado (USD/mesero/mes) | B54: =B41*B46+B42*B47+B43*B48 | C54: Fee Base × Mix = ARPU antes de descuentos
A55: % Descuento promedio ponderado | B55: =IF(B54=0,0,1-(B41*B46*(1-IF(B50<=10,0,IF(B50<=15,0.05,IF(B50<=25,0.1,IF(B50<=40,0.15,0.2)))))*(1-IF(B28<1,0,IF(B28<2,0.1,IF(B28<3,0.2,IF(B28<4,0.3,IF(B28<5,0.4,0.5))))))+B42*B47*(1-IF(B51<=10,0,IF(B51<=15,0.05,IF(B51<=25,0.1,IF(B51<=40,0.15,0.2)))))*(1-IF(B28<1,0,IF(B28<2,0.1,IF(B28<3,0.2,IF(B28<4,0.3,IF(B28<5,0.4,0.5))))))+B43*B48*(1-IF(B52<=10,0,IF(B52<=15,0.05,IF(B52<=25,0.1,IF(B52<=40,0.15,0.2)))))*(1-IF(B28<1,0,IF(B28<2,0.1,IF(B28<3,0.2,IF(B28<4,0.3,IF(B28<5,0.4,0.5)))))))/B54) | C55: Basado en desc. vol. meseros + desc. marcas (Pricing v2.5)
A56: ARPU Neto ponderado (USD/mesero/mes) | B56: =B54*(1-B55) | C56: ← Este valor reemplaza el ARPU flat en el modelo
A57: Meseros ponderados por restaurante | B57: =B41*B50+B42*B51+B43*B52 | C57: Meseros típicos × Mix = promedio ponderado
A58: — Fee de Upgrade de Plan —
A59: % restaurantes que hacen upgrade | B59: =CHOOSE(Escenarios!$B$4,Escenarios!$D$31,Escenarios!$E$31,Escenarios!$F$31) | C59: Restaurantes que pagan upgrade a plan superior | D59: =HYPERLINK("#Escenarios!D31","→ Modificar en Escenarios!D31:F31")
A60: Fee Upgrade promedio (USD/rest/mes) | B60: 50 | C60: ~$200K COP ÷ TRM 4,000 ≈ $50 USD promedio
A62: COSTOS DIRECTOS | B62: Valor | C62: Notas
A63: — Provisión Errores y Fraudes —
A64: Provisión errores humanos (% Super Monedas) | B64: 0.015 | C64: Asignación manual incorrecta de Super Monedas
A65: Provisión fraude (% Super Monedas) | B65: 0.01 | C65: Hackeo POS, evidencia falsa de ventas
A66: Total provisión errores + fraude (%) | B66: =B64+B65 | C66: Sobre total Super Monedas transaccionadas (bruto) | D66: =HYPERLINK("#'Supuestos Generales'!B41","→ Modificar B41 y B42")
A68: — Costos Variables —
A69: Incentivos / premios por mesero activo | B69: 3 | C69: Gamificación y premios mensuales
A70: Costo de redención Super Monedas (% del valor redimido) | B70: =1-B35 | C70: Complemento del margen (1 − 20% = 80% va a proveedores de premios) | D70: =HYPERLINK("#'Supuestos Generales'!B35","→ Modificar B35 (Margen redención)")
A71: Infraestructura por mesero activo (hosting) | B71: 0.5 | C71: Servidores, licencias, cloud
A72: Soporte por restaurante activo | B72: =CHOOSE(Escenarios!$B$4,Escenarios!$D$36,Escenarios!$E$36,Escenarios!$F$36) | C72: Costo de soporte técnico por restaurante activo | D72: =HYPERLINK("#Escenarios!D25","→ Modificar en Escenarios!D25:F25")
A73: Restaurantes por Agente de CS | B73: =CHOOSE(Escenarios!$B$4,Escenarios!$D$38,Escenarios!$E$38,Escenarios!$F$38) | C73: Número de restaurantes que soporta 1 agente CS
A74: Costo por Agente de CS (USD/mes) | B74: 1000 | C74: Salario mensual agente CS
A75: — Engagement y Promoción —
A76: — COMUNICACIONES DIGITALES —
A77: Costo comunicaciones por mesero activo (USD/mes) | B77: 1 | C77: WhatsApp diario ($0.90) + Email semanal + SMS + Push ≈ $1.00
A78: — ENGAGEMENT MANAGERS PRESENCIALES —
A79: Salario Engagement Manager (USD/mes) | B79: 1000 | C79: Salario base EM presencial (LATAM)
A80: Viáticos y transporte por EM (USD/mes) | B80: 750 | C80: Incluye viajes a otras ciudades
A81: Total por Engagement Manager (USD/mes) | B81: =B79+B80 | C81: Salario + viáticos | D81: =HYPERLINK("#'Supuestos Generales'!B56","→ Modificar B56 y B57")
A82: Restaurantes por Engagement Manager | B82: =CHOOSE(Escenarios!$B$4,Escenarios!$D$37,Escenarios!$E$37,Escenarios!$F$37) | C82: 1 EM por cada 50 restaurantes activos
A83: — GALA ANUAL DE SUPER MESEROS —
A84: Costo total Gala anual (USD) | B84: 20000 | C84: Venue, producción, premios, catering, marketing, viajes
A85: Costo Gala mensualizado (USD/mes) | B85: =ROUND(B84/12,0) | C85: Prorrateado mensual; +10% anual a partir del año 2 | D85: =HYPERLINK("#'Supuestos Generales'!B61","→ Modificar B61 (Costo Gala anual)")
A86: Plataforma SaaS de comunicaciones (USD/mes) | B86: 200 | C86: OneSignal / Brevo / similar (push + email + WhatsApp API)
A87: CAC Y GO-TO-MARKET | B87: Valor | C87: Notas
A88: CAC directo - Sin palancas (USD) | B88: 100 | C88: Venta directa sin convenios
A89: CAC directo - Con palancas (USD) | B89: 50 | C89: Convenios Coca-Cola / ACODRES
A90: Meseros afiliados por mesero gratis (ratio) | B90: 5 | C90: 1 mesero gratis por cada 5 meseros afiliados vía referidos
A91: Referidos por restaurante adquirido | B91: 2 | C91: 1 llega al mes siguiente, el otro al mes subsiguiente
A92: Costo mesero gratis (USD/mes) | B92: =B26 | C92: ARPU restaurante/mesero (revenue foregone) | D92: =HYPERLINK("#Escenarios!D18","→ Modificar en Escenarios!D18:F18 (ARPU)")
A93: Duración beneficio mesero gratis (meses) | B93: 12 | C93: Máximo 12 meses por mesero gratis otorgado
A94: Escenario activo | B94: 1 | C94: 1 = Sin palancas, 2 = Con palancas
A95: — Mix de Canales de Adquisición —
A96: % restaurantes vía vendedores propios | B96: 0.4 | C96: Del total de restaurantes nuevos directos
A97: % restaurantes vía vendedores externos | B97: 0.2 | C97: Vendedores freelance / independientes
A98: % restaurantes vía aliados estratégicos | B98: 0.15 | C98: ACODRES, asociaciones de restaurantes
A99: % restaurantes vía Partners POS | B99: 0.25 | C99: Programa de Partners exclusivo para desarrolladores POS
A100: Verificación mix canales | B100: =SUM(B96:B99) | C100: =IF(B100=1,"✓ Suma 100%","✗ No suma 100%") | D100: =HYPERLINK("#'Supuestos Generales'!B73","→ Modificar B73:B76 (mix canales)")
A101: — Comisiones sobre SetUp Fee —
A102: Comisión SetUp - Vendedores propios (%) | B102: 0.05 | C102: 5% del SetUp Fee por restaurante vendido
A103: Comisión SetUp - Vendedores externos (%) | B103: 0.15 | C103: 15% — Mayor incentivo (sin salario base)
A104: Comisión SetUp - Aliados estratégicos (%) | B104: 0.08 | C104: 8% — Referral fee para ACODRES y similares
A105: Comisión SetUp - Partners POS (%) | B105: 0.12 | C105: 12% — Integración técnica + volumen potencial
A106: — Comisiones sobre Fees Mensuales (1er año) —
...

Sheet Onboarding
A1: ONBOARDING — Proyección de Restaurantes, Meseros y Marcas
A3: Concepto | B3: 1 | C3: 2 | D3: 3 | E3: 4 | F3: 5 | G3: 6 | H3: 7 | I3: 8 | J3: 9 | K3: 10 | L3: 11 | M3: 12 | N3: 13 | O3: 14 | P3: 15 | Q3: 16 | R3: 17 | S3: 18 | T3: 19 | U3: 20 | V3: 21 | W3: 22 | X3: 23 | Y3: 24 | Z3: 25 | AA3: 26 | AB3: 27 | AC3: 28 | AD3: 29 | AE3: 30 | AF3: 31 | AG3: 32 | AH3: 33 | AI3: 34 | AJ3: 35 | AK3: 36 | AL3: 37 | AM3: 38 | AN3: 39 | AO3: 40 | AP3: 41 | AQ3: 42 | AR3: 43 | AS3: 44 | AT3: 45 | AU3: 46 | AV3: 47 | AW3: 48 | AX3: 49 | AY3: 50 | AZ3: 51 | BA3: 52 | BB3: 53 | BC3: 54 | BD3: 55 | BE3: 56 | BF3: 57 | BG3: 58 | BH3: 59 | BI3: 60
A5: RESTAURANTES
A6: Restaurantes nuevos directos | B6: =IF(B3<='Supuestos Generales'!$C$12,'Supuestos Generales'!$D$12,IF(B3<='Supuestos Generales'!$C$13,'Supuestos Generales'!$D$13,IF(B3<='Supuestos Generales'!$C$14,'Supuestos Generales'!$D$14,IF(B3<='Supuestos Generales'!$C$15,'Supuestos Generales'!$D$15,'Supuestos Generales'!$D$16)))) | C6: =IF(C3<='Supuestos Generales'!$C$12,'Supuestos Generales'!$D$12,IF(C3<='Supuestos Generales'!$C$13,'Supuestos Generales'!$D$13,IF(C3<='Supuestos Generales'!$C$14,'Supuestos Generales'!$D$14,IF(C3<='Supuestos Generales'!$C$15,'Supuestos Generales'!$D$15,'Supuestos Generales'!$D$16)))) | D6: =IF(D3<='Supuestos Generales'!$C$12,'Supuestos Generales'!$D$12,IF(D3<='Supuestos Generales'!$C$13,'Supuestos Generales'!$D$13,IF(D3<='Supuestos Generales'!$C$14,'Supuestos Generales'!$D$14,IF(D3<='Supuestos Generales'!$C$15,'Supuestos Generales'!$D$15,'Supuestos Generales'!$D$16)))) | E6: =IF(E3<='Supuestos Generales'!$C$12,'Supuestos Generales'!$D$12,IF(E3<='Supuestos Generales'!$C$13,'Supuestos Generales'!$D$13,IF(E3<='Supuestos Generales'!$C$14,'Supuestos Generales'!$D$14,IF(E3<='Supuestos Generales'!$C$15,'Supuestos Generales'!$D$15,'Supuestos Generales'!$D$16)))) | F6: =IF(F3<='Supuestos Generales'!$C$12,'Supuestos Generales'!$D$12,IF(F3<='Supuestos Generales'!$C$13,'Supuestos Generales'!$D$13,IF(F3<='Supuestos Generales'!$C$14,'Supuestos Generales'!$D$14,IF(F3<='Supuestos Generales'!$C$15,'Supuestos Generales'!$D$15,'Supuestos Generales'!$D$16)))) | G6: =IF(G3<='Supuestos Generales'!$C$12,'Supuestos Generales'!$D$12,IF(G3<='Supuestos Generales'!$C$13,'Supuestos Generales'!$D$13,IF(G3<='Supuestos Generales'!$C$14,'Supuestos Generales'!$D$14,IF(G3<='Supuestos Generales'!$C$15,'Supuestos Generales'!$D$15,'Supuestos Generales'!$D$16)))) | H6: =IF(H3<='Supuestos Generales'!$C$12,'Supuestos Generales'!$D$12,IF(H3<='Supuestos Generales'!$C$13,'Supuestos Generales'!$D$13,IF(H3<='Supuestos Generales'!$C$14,'Supuestos Generales'!$D$14,IF(H3<='Supuestos Generales'!$C$15,'Supuestos Generales'!$D$15,'Supuestos Generales'!$D$16)))) | I6: =IF(I3<='Supuestos Generales'!$C$12,'Supuestos Generales'!$D$12,IF(I3<='Supuestos Generales'!$C$13,'Supuestos Generales'!$D$13,IF(I3<='Supuestos Generales'!$C$14,'Supuestos Generales'!$D$14,IF(I3<='Supuestos Generales'!$C$15,'Supuestos Generales'!$D$15,'Supuestos Generales'!$D$16)))) | ... BI6: =IF(BI3<='Supuestos Generales'!$C$12,'Supuestos Generales'!$D$12,IF(BI3<='Supuestos Generales'!$C$13,'Supuestos Generales'!$D$13,IF(BI3<='Supuestos Generales'!$C$14,'Supuestos Generales'!$D$14,IF(BI3<='Supuestos Generales'!$C$15,'Supuestos Generales'!$D$15,'Supuestos Generales'!$D$16))))
A7: Referidos (mes anterior) | B7: 0 | C7: =(B6+B9)*'Supuestos Generales'!$B$91/2 | D7: =(C6+C9)*'Supuestos Generales'!$B$91/2 | E7: =(D6+D9)*'Supuestos Generales'!$B$91/2 | F7: =(E6+E9)*'Supuestos Generales'!$B$91/2 | G7: =(F6+F9)*'Supuestos Generales'!$B$91/2 | H7: =(G6+G9)*'Supuestos Generales'!$B$91/2 | I7: =(H6+H9)*'Supuestos Generales'!$B$91/2 | J7: =(I6+I9)*'Supuestos Generales'!$B$91/2 | ... BI7: =(BH6+BH9)*'Supuestos Generales'!$B$91/2
A8: Referidos (2 meses antes) | B8: 0 | C8: 0 | D8: =(B6+B9)*'Supuestos Generales'!$B$91/2 | E8: =(C6+C9)*'Supuestos Generales'!$B$91/2 | F8: =(D6+D9)*'Supuestos Generales'!$B$91/2 | G8: =(E6+E9)*'Supuestos Generales'!$B$91/2 | H8: =(F6+F9)*'Supuestos Generales'!$B$91/2 | I8: =(G6+G9)*'Supuestos Generales'!$B$91/2 | J8: =(H6+H9)*'Supuestos Generales'!$B$91/2 | K8: =(I6+I9)*'Supuestos Generales'!$B$91/2 | ... BI8: =(BG6+BG9)*'Supuestos Generales'!$B$91/2
A9: Restaurantes vía alianzas | B9: =IF(AND(Palancas!$B$13=1,B$3>=Palancas!$B$15),MIN(Palancas!$B$16,ROUND(Palancas!$B$16*(B$3-Palancas!$B$15+1)/Palancas!$B$10,0)),0)+IF(AND(Palancas!$F$13=1,B$3>=Palancas!$F$15),MIN(Palancas!$F$16,ROUND(Palancas!$F$16*(B$3-Palancas!$F$15+1)/Palancas!$B$10,0)),0)+IF(AND(Palancas!$B$21=1,B$3>=Palancas!$B$23),MIN(Palancas!$B$24,ROUND(Palancas!$B$24*(B$3-Palancas!$B$23+1)/Palancas!$B$10,0)),0)+IF(AND(Palancas!$F$21=1,B$3>=Palancas!$F$23),MIN(Palancas!$F$24,ROUND(Palancas!$F$24*(B$3-Palancas!$F$23+1)/Palancas!$B$10,0)),0)+IF(AND(Palancas!$B$29=1,B$3>=Palancas!$B$31,B$3<=Palancas!$B$34),MIN(Palancas!$B$32,ROUND(Palancas!$B$32*(B$3-Palancas!$B$31+1)/Palancas!$B$10,0)),0) | C9: =IF(AND(Palancas!$B$13=1,C$3>=Palancas!$B$15),MIN(Palancas!$B$16,ROUND(Palancas!$B$16*(C$3-Palancas!$B$15+1)/Palancas!$B$10,0)),0)+IF(AND(Palancas!$F$13=1,C$3>=Palancas!$F$15),MIN(Palancas!$F$16,ROUND(Palancas!$F$16*(C$3-Palancas!$F$15+1)/Palancas!$B$10,0)),0)+IF(AND(Palancas!$B$21=1,C$3>=Palancas!$B$23),MIN(Palancas!$B$24,ROUND(Palancas!$B$24*(C$3-Palancas!$B$23+1)/Palancas!$B$10,0)),0)+IF(AND(Palancas!$F$21=1,C$3>=Palancas!$F$23),MIN(Palancas!$F$24,ROUND(Palancas!$F$24*(C$3-Palancas!$F$23+1)/Palancas!$B$10,0)),0)+IF(AND(Palancas!$B$29=1,C$3>=Palancas!$B$31,C$3<=Palancas!$B$34),MIN(Palancas!$B$32,ROUND(Palancas!$B$32*(C$3-Palancas!$B$31+1)/Palancas!$B$10,0)),0) | D9: =IF(AND(Palancas!$B$13=1,D$3>=Palancas!$B$15),MIN(Palancas!$B$16,ROUND(Palancas!$B$16*(D$3-Palancas!$B$15+1)/Palancas!$B$10,0)),0)+IF(AND(Palancas!$F$13=1,D$3>=Palancas!$F$15),MIN(Palancas!$F$16,ROUND(Palancas!$F$16*(D$3-Palancas!$F$15+1)/Palancas!$B$10,0)),0)+IF(AND(Palancas!$B$21=1,D$3>=Palancas!$B$23),MIN(Palancas!$B$24,ROUND(Palancas!$B$24*(D$3-Palancas!$B$23+1)/Palancas!$B$10,0)),0)+IF(AND(Palancas!$F$21=1,D$3>=Palancas!$F$23),MIN(Palancas!$F$24,ROUND(Palancas!$F$24*(D$3-Palancas!$F$23+1)/Palancas!$B$10,0)),0)+IF(AND(Palancas!$B$29=1,D$3>=Palancas!$B$31,D$3<=Palancas!$B$34),MIN(Palancas!$B$32,ROUND(Palancas!$B$32*(D$3-Palancas!$B$31+1)/Palancas!$B$10,0)),0) | E9: =IF(AND(Palancas!$B$13=1,E$3>=Palancas!$B$15),MIN(Palancas!$B$16,ROUND(Palancas!$B$16*(E$3-Palancas!$B$15+1)/Palancas!$B$10,0)),0)+IF(AND(Palancas!$F$13=1,E$3>=Palancas!$F$15),MIN(Palancas!$F$16,ROUND(Palancas!$F$16*(E$3-Palancas!$F$15+1)/Palancas!$B$10,0)),0)+IF(AND(Palancas!$B$21=1,E$3>=Palancas!$B$23),MIN(Palancas!$B$24,ROUND(Palancas!$B$24*(E$3-Palancas!$B$23+1)/Palancas!$B$10,0)),0)+IF(AND(Palancas!$F$21=1,E$3>=Palancas!$F$23),MIN(Palancas!$F$24,ROUND(Palancas!$F$24*(E$3-Palancas!$F$23+1)/Palancas!$B$10,0)),0)+IF(AND(Palancas!$B$29=1,E$3>=Palancas!$B$31,E$3<=Palancas!$B$34),MIN(Palancas!$B$32,ROUND(Palancas!$B$32*(E$3-Palancas!$B$31+1)/Palancas!$B$10,0)),0) | F9: =IF(AND(Palancas!$B$13=1,F$3>=Palancas!$B$15),MIN(Palancas!$B$16,ROUND(Palancas!$B$16*(F$3-Palancas!$B$15+1)/Palancas!$B$10,0)),0)+IF(AND(Palancas!$F$13=1,F$3>=Palancas!$F$15),MIN(Palancas!$F$16,ROUND(Palancas!$F$16*(F$3-Palancas!$F$15+1)/Palancas!$B$10,0)),0)+IF(AND(Palancas!$B$21=1,F$3>=Palancas!$B$23),MIN(Palancas!$B$24,ROUND(Palancas!$B$24*(F$3-Palancas!$B$23+1)/Palancas!$B$10,0)),0)+IF(AND(Palancas!$F$21=1,F$3>=Palancas!$F$23),MIN(Palancas!$F$24,ROUND(Palancas!$F$24*(F$3-Palancas!$F$23+1)/Palancas!$B$10,0)),0)+IF(AND(Palancas!$B$29=1,F$3>=Palancas!$B$31,F$3<=Palancas!$B$34),MIN(Palancas!$B$32,ROUND(Palancas!$B$32*(F$3-Palancas!$B$31+1)/Palancas!$B$10,0)),0) | G9: =IF(AND(Palancas!$B$13=1,G$3>=Palancas!$B$15),MIN(Palancas!$B$16,ROUND(Palancas!$B$16*(G$3-Palancas!$B$15+1)/Palancas!$B$10,0)),0)+IF(AND(Palancas!$F$13=1,G$3>=Palancas!$F$15),MIN(Palancas!$F$16,ROUND(Palancas!$F$16*(G$3-Palancas!$F$15+1)/Palancas!$B$10,0)),0)+IF(AND(Palancas!$B$21=1,G$3>=Palancas!$B$23),MIN(Palancas!$B$24,ROUND(Palancas!$B$24*(G$3-Palancas!$B$23+1)/Palancas!$B$10,0)),0)+IF(AND(Palancas!$F$21=1,G$3>=Palancas!$F$23),MIN(Palancas!$F$24,ROUND(Palancas!$F$24*(G$3-Palancas!$F$23+1)/Palancas!$B$10,0)),0)+IF(AND(Palancas!$B$29=1,G$3>=Palancas!$B$31,G$3<=Palancas!$B$34),MIN(Palancas!$B$32,ROUND(Palancas!$B$32*(G$3-Palancas!$B$31+1)/Palancas!$B$10,0)),0) | H9: =IF(AND(Palancas!$B$13=1,H$3>=Palancas!$B$15),MIN(Palancas!$B$16,ROUND(Palancas!$B$16*(H$3-Palancas!$B$15+1)/Palancas!$B$10,0)),0)+IF(AND(Palancas!$F$13=1,H$3>=Palancas!$F$15),MIN(Palancas!$F$16,ROUND(Palancas!$F$16*(H$3-Palancas!$F$15+1)/Palancas!$B$10,0)),0)+IF(AND(Palancas!$B$21=1,H$3>=Palancas!$B$23),MIN(Palancas!$B$24,ROUND(Palancas!$B$24*(H$3-Palancas!$B$23+1)/Palancas!$B$10,0)),0)+IF(AND(Palancas!$F$21=1,H$3>=Palancas!$F$23),MIN(Palancas!$F$24,ROUND(Palancas!$F$24*(H$3-Palancas!$F$23+1)/Palancas!$B$10,0)),0)+IF(AND(Palancas!$B$29=1,H$3>=Palancas!$B$31,H$3<=Palancas!$B$34),MIN(Palancas!$B$32,ROUND(Palancas!$B$32*(H$3-Palancas!$B$31+1)/Palancas!$B$10,0)),0) | I9: =IF(AND(Palancas!$B$13=1,I$3>=Palancas!$B$15),MIN(Palancas!$B$16,ROUND(Palancas!$B$16*(I$3-Palancas!$B$15+1)/Palancas!$B$10,0)),0)+IF(AND(Palancas!$F$13=1,I$3>=Palancas!$F$15),MIN(Palancas!$F$16,ROUND(Palancas!$F$16*(I$3-Palancas!$F$15+1)/Palancas!$B$10,0)),0)+IF(AND(Palancas!$B$21=1,I$3>=Palancas!$B$23),MIN(Palancas!$B$24,ROUND(Palancas!$B$24*(I$3-Palancas!$B$23+1)/Palancas!$B$10,0)),0)+IF(AND(Palancas!$F$21=1,I$3>=Palancas!$F$23),MIN(Palancas!$F$24,ROUND(Palancas!$F$24*(I$3-Palancas!$F$23+1)/Palancas!$B$10,0)),0)+IF(AND(Palancas!$B$29=1,I$3>=Palancas!$B$31,I$3<=Palancas!$B$34),MIN(Palancas!$B$32,ROUND(Palancas!$B$32*(I$3-Palancas!$B$31+1)/Palancas!$B$10,0)),0) | ... BI9: =IF(AND(Palancas!$B$13=1,BI$3>=Palancas!$B$15),MIN(Palancas!$B$16,ROUND(Palancas!$B$16*(BI$3-Palancas!$B$15+1)/Palancas!$B$10,0)),0)+IF(AND(Palancas!$F$13=1,BI$3>=Palancas!$F$15),MIN(Palancas!$F$16,ROUND(Palancas!$F$16*(BI$3-Palancas!$F$15+1)/Palancas!$B$10,0)),0)+IF(AND(Palancas!$B$21=1,BI$3>=Palancas!$B$23),MIN(Palancas!$B$24,ROUND(Palancas!$B$24*(BI$3-Palancas!$B$23+1)/Palancas!$B$10,0)),0)+IF(AND(Palancas!$F$21=1,BI$3>=Palancas!$F$23),MIN(Palancas!$F$24,ROUND(Palancas!$F$24*(BI$3-Palancas!$F$23+1)/Palancas!$B$10,0)),0)+IF(AND(Palancas!$B$29=1,BI$3>=Palancas!$B$31,BI$3<=Palancas!$B$34),MIN(Palancas!$B$32,ROUND(Palancas!$B$32*(BI$3-Palancas!$B$31+1)/Palancas!$B$10,0)),0)
A10: Total restaurantes nuevos (mes) | B10: =B6+B7+B8+B9 | C10: =C6+C7+C8+C9 | D10: =D6+D7+D8+D9 | E10: =E6+E7+E8+E9 | F10: =F6+F7+F8+F9 | G10: =G6+G7+G8+G9 | H10: =H6+H7+H8+H9 | I10: =I6+I7+I8+I9 | ... BI10: =BI6+BI7+BI8+BI9
A11: Churn de restaurantes | B11: 0 | C11: =ROUND(B12*'Supuestos Generales'!$B$18,0) | D11: =ROUND(C12*'Supuestos Generales'!$B$18,0) | E11: =ROUND(D12*'Supuestos Generales'!$B$18,0) | F11: =ROUND(E12*'Supuestos Generales'!$B$18,0) | G11: =ROUND(F12*'Supuestos Generales'!$B$18,0) | H11: =ROUND(G12*'Supuestos Generales'!$B$18,0) | I11: =ROUND(H12*'Supuestos Generales'!$B$18,0) | J11: =ROUND(I12*'Supuestos Generales'!$B$18,0) | ... BI11: =ROUND(BH12*'Supuestos Generales'!$B$18,0)
A12: Restaurantes activos acumulados | B12: =B10-B11 | C12: =B12+C10-C11 | D12: =C12+D10-D11 | E12: =D12+E10-E11 | F12: =E12+F10-F11 | G12: =F12+G10-G11 | H12: =G12+H10-H11 | I12: =H12+I10-I11 | J12: =I12+J10-J11 | ... BI12: =BH12+BI10-BI11
A13: — Pequeños (Plan Light) | B13: =ROUND(B12*'Supuestos Generales'!$B$41,0) | C13: =ROUND(C12*'Supuestos Generales'!$B$41,0) | D13: =ROUND(D12*'Supuestos Generales'!$B$41,0) | E13: =ROUND(E12*'Supuestos Generales'!$B$41,0) | F13: =ROUND(F12*'Supuestos Generales'!$B$41,0) | G13: =ROUND(G12*'Supuestos Generales'!$B$41,0) | H13: =ROUND(H12*'Supuestos Generales'!$B$41,0) | I13: =ROUND(I12*'Supuestos Generales'!$B$41,0) | ... BI13: =ROUND(BI12*'Supuestos Generales'!$B$41,0)
A14: — Medianos (Plan Standard) | B14: =ROUND(B12*'Supuestos Generales'!$B$42,0) | C14: =ROUND(C12*'Supuestos Generales'!$B$42,0) | D14: =ROUND(D12*'Supuestos Generales'!$B$42,0) | E14: =ROUND(E12*'Supuestos Generales'!$B$42,0) | F14: =ROUND(F12*'Supuestos Generales'!$B$42,0) | G14: =ROUND(G12*'Supuestos Generales'!$B$42,0) | H14: =ROUND(H12*'Supuestos Generales'!$B$42,0) | I14: =ROUND(I12*'Supuestos Generales'!$B$42,0) | ... BI14: =ROUND(BI12*'Supuestos Generales'!$B$42,0)
A15: — Grandes (Plan Premium) | B15: =ROUND(B12*'Supuestos Generales'!$B$43,0) | C15: =ROUND(C12*'Supuestos Generales'!$B$43,0) | D15: =ROUND(D12*'Supuestos Generales'!$B$43,0) | E15: =ROUND(E12*'Supuestos Generales'!$B$43,0) | F15: =ROUND(F12*'Supuestos Generales'!$B$43,0) | G15: =ROUND(G12*'Supuestos Generales'!$B$43,0) | H15: =ROUND(H12*'Supuestos Generales'!$B$43,0) | I15: =ROUND(I12*'Supuestos Generales'!$B$43,0) | ... BI15: =ROUND(BI12*'Supuestos Generales'!$B$43,0)
A17: MESEROS
A18: Meseros totales (activos acum. × meseros/rest.) | B18: =B12*'Supuestos Generales'!$B$19 | C18: =C12*'Supuestos Generales'!$B$19 | D18: =D12*'Supuestos Generales'!$B$19 | E18: =E12*'Supuestos Generales'!$B$19 | F18: =F12*'Supuestos Generales'!$B$19 | G18: =G12*'Supuestos Generales'!$B$19 | H18: =H12*'Supuestos Generales'!$B$19 | I18: =I12*'Supuestos Generales'!$B$19 | ... BI18: =BI12*'Supuestos Generales'!$B$19
A19: Meseros activos (× % activación) | B19: =B18*'Supuestos Generales'!$B$20 | C19: =C18*'Supuestos Generales'!$B$20 | D19: =D18*'Supuestos Generales'!$B$20 | E19: =E18*'Supuestos Generales'!$B$20 | F19: =F18*'Supuestos Generales'!$B$20 | G19: =G18*'Supuestos Generales'!$B$20 | H19: =H18*'Supuestos Generales'!$B$20 | I19: =I18*'Supuestos Generales'!$B$20 | ... BI19: =BI18*'Supuestos Generales'!$B$20
A21: MARCAS
A22: Marcas promedio por restaurante | B22: ='Supuestos Generales'!$B$28 | C22: =B22*(1+'Supuestos Generales'!$B$29) | D22: =C22*(1+'Supuestos Generales'!$B$29) | E22: =D22*(1+'Supuestos Generales'!$B$29) | F22: =E22*(1+'Supuestos Generales'!$B$29) | G22: =F22*(1+'Supuestos Generales'!$B$29) | H22: =G22*(1+'Supuestos Generales'!$B$29) | I22: =H22*(1+'Supuestos Generales'!$B$29) | J22: =I22*(1+'Supuestos Generales'!$B$29) | ... BI22: =BH22*(1+'Supuestos Generales'!$B$29)
A23: Total marcas×restaurantes activos | B23: =B22*B12 | C23: =C22*C12 | D23: =D22*D12 | E23: =E22*E12 | F23: =F22*F12 | G23: =G22*G12 | H23: =H22*H12 | I23: =I22*I12 | ... BI23: =BI22*BI12

Sheet Ingresos
A1: INGRESOS — Proyección Mensual
A3: Concepto | B3: 1 | C3: 2 | D3: 3 | E3: 4 | F3: 5 | G3: 6 | H3: 7 | I3: 8 | J3: 9 | K3: 10 | L3: 11 | M3: 12 | N3: 13 | O3: 14 | P3: 15 | Q3: 16 | R3: 17 | S3: 18 | T3: 19 | U3: 20 | V3: 21 | W3: 22 | X3: 23 | Y3: 24 | Z3: 25 | AA3: 26 | AB3: 27 | AC3: 28 | AD3: 29 | AE3: 30 | AF3: 31 | AG3: 32 | AH3: 33 | AI3: 34 | AJ3: 35 | AK3: 36 | AL3: 37 | AM3: 38 | AN3: 39 | AO3: 40 | AP3: 41 | AQ3: 42 | AR3: 43 | AS3: 44 | AT3: 45 | AU3: 46 | AV3: 47 | AW3: 48 | AX3: 49 | AY3: 50 | AZ3: 51 | BA3: 52 | BB3: 53 | BC3: 54 | BD3: 55 | BE3: 56 | BF3: 57 | BG3: 58 | BH3: 59 | BI3: 60 | BJ3: TOTAL
A5: INGRESOS ONE-OFF
A6: SetUp Fee (restaurantes nuevos) | B6: =Onboarding!B10*'Supuestos Generales'!$B$24 | C6: =Onboarding!C10*'Supuestos Generales'!$B$24 | D6: =Onboarding!D10*'Supuestos Generales'!$B$24 | E6: =Onboarding!E10*'Supuestos Generales'!$B$24 | F6: =Onboarding!F10*'Supuestos Generales'!$B$24 | G6: =Onboarding!G10*'Supuestos Generales'!$B$24 | H6: =Onboarding!H10*'Supuestos Generales'!$B$24 | I6: =Onboarding!I10*'Supuestos Generales'!$B$24 | ... BI6: =Onboarding!BI10*'Supuestos Generales'!$B$24 | BJ6: =SUM(B6:BI6)
A7: Entry Fee (nuevas marcas × restaurantes) | B7: =Onboarding!B10*MAX(Onboarding!B22-1,0)*'Supuestos Generales'!$B$25 | C7: =Onboarding!C10*MAX(Onboarding!C22-1,0)*'Supuestos Generales'!$B$25 | D7: =Onboarding!D10*MAX(Onboarding!D22-1,0)*'Supuestos Generales'!$B$25 | E7: =Onboarding!E10*MAX(Onboarding!E22-1,0)*'Supuestos Generales'!$B$25 | F7: =Onboarding!F10*MAX(Onboarding!F22-1,0)*'Supuestos Generales'!$B$25 | G7: =Onboarding!G10*MAX(Onboarding!G22-1,0)*'Supuestos Generales'!$B$25 | H7: =Onboarding!H10*MAX(Onboarding!H22-1,0)*'Supuestos Generales'!$B$25 | I7: =Onboarding!I10*MAX(Onboarding!I22-1,0)*'Supuestos Generales'!$B$25 | ... BI7: =Onboarding!BI10*MAX(Onboarding!BI22-1,0)*'Supuestos Generales'!$B$25 | BJ7: =SUM(B7:BI7)
A8: Total Ingresos One-Off | B8: =B6+B7 | C8: =C6+C7 | D8: =D6+D7 | E8: =E6+E7 | F8: =F6+F7 | G8: =G6+G7 | H8: =H6+H7 | I8: =I6+I7 | ... BI8: =BI6+BI7 | BJ8: =SUM(B8:BI8)
A10: INGRESOS RECURRENTES
A11: SaaS Fee Restaurante (por mesero) | B11: =Onboarding!B19*'Supuestos Generales'!$B$26 | C11: =Onboarding!C19*'Supuestos Generales'!$B$26 | D11: =Onboarding!D19*'Supuestos Generales'!$B$26 | E11: =Onboarding!E19*'Supuestos Generales'!$B$26 | F11: =Onboarding!F19*'Supuestos Generales'!$B$26 | G11: =Onboarding!G19*'Supuestos Generales'!$B$26 | H11: =Onboarding!H19*'Supuestos Generales'!$B$26 | I11: =Onboarding!I19*'Supuestos Generales'!$B$26 | ... BI11: =Onboarding!BI19*'Supuestos Generales'!$B$26 | BJ11: =SUM(B11:BI11)
A12: SaaS Fee Marcas (por mesero × marcas) | B12: =Onboarding!B19*Onboarding!B22*'Supuestos Generales'!$B$27 | C12: =Onboarding!C19*Onboarding!C22*'Supuestos Generales'!$B$27 | D12: =Onboarding!D19*Onboarding!D22*'Supuestos Generales'!$B$27 | E12: =Onboarding!E19*Onboarding!E22*'Supuestos Generales'!$B$27 | F12: =Onboarding!F19*Onboarding!F22*'Supuestos Generales'!$B$27 | G12: =Onboarding!G19*Onboarding!G22*'Supuestos Generales'!$B$27 | H12: =Onboarding!H19*Onboarding!H22*'Supuestos Generales'!$B$27 | I12: =Onboarding!I19*Onboarding!I22*'Supuestos Generales'!$B$27 | ... BI12: =Onboarding!BI19*Onboarding!BI22*'Supuestos Generales'!$B$27 | BJ12: =SUM(B12:BI12)
A13: Fee Upgrade de Plan | B13: =Onboarding!B12*'Supuestos Generales'!$B$59*'Supuestos Generales'!$B$60 | C13: =Onboarding!C12*'Supuestos Generales'!$B$59*'Supuestos Generales'!$B$60 | D13: =Onboarding!D12*'Supuestos Generales'!$B$59*'Supuestos Generales'!$B$60 | E13: =Onboarding!E12*'Supuestos Generales'!$B$59*'Supuestos Generales'!$B$60 | F13: =Onboarding!F12*'Supuestos Generales'!$B$59*'Supuestos Generales'!$B$60 | G13: =Onboarding!G12*'Supuestos Generales'!$B$59*'Supuestos Generales'!$B$60 | H13: =Onboarding!H12*'Supuestos Generales'!$B$59*'Supuestos Generales'!$B$60 | I13: =Onboarding!I12*'Supuestos Generales'!$B$59*'Supuestos Generales'!$B$60 | ... BI13: =Onboarding!BI12*'Supuestos Generales'!$B$59*'Supuestos Generales'!$B$60 | BJ13: =SUM(B13:BI13)
A14: Super Monedas — Restaurantes (bruto) | B14: =Onboarding!B19*'Supuestos Generales'!$B$31 | C14: =Onboarding!C19*'Supuestos Generales'!$B$31 | D14: =Onboarding!D19*'Supuestos Generales'!$B$31 | E14: =Onboarding!E19*'Supuestos Generales'!$B$31 | F14: =Onboarding!F19*'Supuestos Generales'!$B$31 | G14: =Onboarding!G19*'Supuestos Generales'!$B$31 | H14: =Onboarding!H19*'Supuestos Generales'!$B$31 | I14: =Onboarding!I19*'Supuestos Generales'!$B$31 | ... BI14: =Onboarding!BI19*'Supuestos Generales'!$B$31 | BJ14: =SUM(B14:BI14)
A15: Super Monedas — Marcas (bruto) | B15: =Onboarding!B19*Onboarding!B22*'Supuestos Generales'!$B$32 | C15: =Onboarding!C19*Onboarding!C22*'Supuestos Generales'!$B$32 | D15: =Onboarding!D19*Onboarding!D22*'Supuestos Generales'!$B$32 | E15: =Onboarding!E19*Onboarding!E22*'Supuestos Generales'!$B$32 | F15: =Onboarding!F19*Onboarding!F22*'Supuestos Generales'!$B$32 | G15: =Onboarding!G19*Onboarding!G22*'Supuestos Generales'!$B$32 | H15: =Onboarding!H19*Onboarding!H22*'Supuestos Generales'!$B$32 | I15: =Onboarding!I19*Onboarding!I22*'Supuestos Generales'!$B$32 | ... BI15: =Onboarding!BI19*Onboarding!BI22*'Supuestos Generales'!$B$32 | BJ15: =SUM(B15:BI15)
A16: Total Super Monedas (bruto) | B16: =B14+B15 | C16: =C14+C15 | D16: =D14+D15 | E16: =E14+E15 | F16: =F14+F15 | G16: =G14+G15 | H16: =H14+H15 | I16: =I14+I15 | ... BI16: =BI14+BI15 | BJ16: =SUM(B16:BI16)
A17: Total Ingresos Recurrentes | B17: =B11+B12+B13+B16 | C17: =C11+C12+C13+C16 | D17: =D11+D12+D13+D16 | E17: =E11+E12+E13+E16 | F17: =F11+F12+F13+F16 | G17: =G11+G12+G13+G16 | H17: =H11+H12+H13+H16 | I17: =I11+I12+I13+I16 | ... BJ17: =BJ11+BJ12+BJ13+BJ16
A19: TOTAL INGRESOS | B19: =B8+B17 | C19: =C8+C17 | D19: =D8+D17 | E19: =E8+E17 | F19: =F8+F17 | G19: =G8+G17 | H19: =H8+H17 | I19: =I8+I17 | ... BI19: =BI8+BI17 | BJ19: =SUM(B19:BI19)
A20: Ingresos Acumulados | B20: =B19 | C20: =B20+C19 | D20: =C20+D19 | E20: =D20+E19 | F20: =E20+F19 | G20: =F20+G19 | H20: =G20+H19 | I20: =H20+I19 | J20: =I20+J19 | ... BI20: =BH20+BI19 | BJ20: =BJ19

Sheet Costos Directos
A1: COSTOS DIRECTOS — Proyección Mensual
A3: Concepto | B3: 1 | C3: 2 | D3: 3 | E3: 4 | F3: 5 | G3: 6 | H3: 7 | I3: 8 | J3: 9 | K3: 10 | L3: 11 | M3: 12 | N3: 13 | O3: 14 | P3: 15 | Q3: 16 | R3: 17 | S3: 18 | T3: 19 | U3: 20 | V3: 21 | W3: 22 | X3: 23 | Y3: 24 | Z3: 25 | AA3: 26 | AB3: 27 | AC3: 28 | AD3: 29 | AE3: 30 | AF3: 31 | AG3: 32 | AH3: 33 | AI3: 34 | AJ3: 35 | AK3: 36 | AL3: 37 | AM3: 38 | AN3: 39 | AO3: 40 | AP3: 41 | AQ3: 42 | AR3: 43 | AS3: 44 | AT3: 45 | AU3: 46 | AV3: 47 | AW3: 48 | AX3: 49 | AY3: 50 | AZ3: 51 | BA3: 52 | BB3: 53 | BC3: 54 | BD3: 55 | BE3: 56 | BF3: 57 | BG3: 58 | BH3: 59 | BI3: 60 | BJ3: TOTAL
A5: COSTOS VARIABLES
A6: Incentivos / premios por mesero activo | B6: =Onboarding!B19*'Supuestos Generales'!$B$69 | C6: =Onboarding!C19*'Supuestos Generales'!$B$69 | D6: =Onboarding!D19*'Supuestos Generales'!$B$69 | E6: =Onboarding!E19*'Supuestos Generales'!$B$69 | F6: =Onboarding!F19*'Supuestos Generales'!$B$69 | G6: =Onboarding!G19*'Supuestos Generales'!$B$69 | H6: =Onboarding!H19*'Supuestos Generales'!$B$69 | I6: =Onboarding!I19*'Supuestos Generales'!$B$69 | ... BI6: =Onboarding!BI19*'Supuestos Generales'!$B$69 | BJ6: =SUM(B6:BI6)
A7: Costo redención Super Monedas | B7: =(Ingresos!B14+Ingresos!B15)*'Supuestos Generales'!$B$33*'Supuestos Generales'!$B$70 | C7: =(Ingresos!C14+Ingresos!C15)*'Supuestos Generales'!$B$33*'Supuestos Generales'!$B$70 | D7: =(Ingresos!D14+Ingresos!D15)*'Supuestos Generales'!$B$33*'Supuestos Generales'!$B$70 | E7: =(Ingresos!E14+Ingresos!E15)*'Supuestos Generales'!$B$33*'Supuestos Generales'!$B$70 | F7: =(Ingresos!F14+Ingresos!F15)*'Supuestos Generales'!$B$33*'Supuestos Generales'!$B$70 | G7: =(Ingresos!G14+Ingresos!G15)*'Supuestos Generales'!$B$33*'Supuestos Generales'!$B$70 | H7: =(Ingresos!H14+Ingresos!H15)*'Supuestos Generales'!$B$33*'Supuestos Generales'!$B$70 | I7: =(Ingresos!I14+Ingresos!I15)*'Supuestos Generales'!$B$33*'Supuestos Generales'!$B$70 | ... BI7: =(Ingresos!BI14+Ingresos!BI15)*'Supuestos Generales'!$B$33*'Supuestos Generales'!$B$70 | BJ7: =SUM(B7:BI7)
A8: Infraestructura por mesero activo (hosting) | B8: =Onboarding!B19*'Supuestos Generales'!$B$71 | C8: =Onboarding!C19*'Supuestos Generales'!$B$71 | D8: =Onboarding!D19*'Supuestos Generales'!$B$71 | E8: =Onboarding!E19*'Supuestos Generales'!$B$71 | F8: =Onboarding!F19*'Supuestos Generales'!$B$71 | G8: =Onboarding!G19*'Supuestos Generales'!$B$71 | H8: =Onboarding!H19*'Supuestos Generales'!$B$71 | I8: =Onboarding!I19*'Supuestos Generales'!$B$71 | ... BI8: =Onboarding!BI19*'Supuestos Generales'!$B$71 | BJ8: =SUM(B8:BI8)
A9: Soporte por restaurante activo | B9: =Onboarding!B12*'Supuestos Generales'!$B$72 | C9: =Onboarding!C12*'Supuestos Generales'!$B$72 | D9: =Onboarding!D12*'Supuestos Generales'!$B$72 | E9: =Onboarding!E12*'Supuestos Generales'!$B$72 | F9: =Onboarding!F12*'Supuestos Generales'!$B$72 | G9: =Onboarding!G12*'Supuestos Generales'!$B$72 | H9: =Onboarding!H12*'Supuestos Generales'!$B$72 | I9: =Onboarding!I12*'Supuestos Generales'!$B$72 | ... BI9: =Onboarding!BI12*'Supuestos Generales'!$B$72 | BJ9: =SUM(B9:BI9)
A11: COSTOS DE ENGAGEMENT Y PROMOCIÓN
A12: Comunicaciones digitales por mesero activo | B12: =Onboarding!B19*'Supuestos Generales'!$B$77 | C12: =Onboarding!C19*'Supuestos Generales'!$B$77 | D12: =Onboarding!D19*'Supuestos Generales'!$B$77 | E12: =Onboarding!E19*'Supuestos Generales'!$B$77 | F12: =Onboarding!F19*'Supuestos Generales'!$B$77 | G12: =Onboarding!G19*'Supuestos Generales'!$B$77 | H12: =Onboarding!H19*'Supuestos Generales'!$B$77 | I12: =Onboarding!I19*'Supuestos Generales'!$B$77 | ... BI12: =Onboarding!BI19*'Supuestos Generales'!$B$77 | BJ12: =SUM(B12:BI12)
A13: Engagement Managers (cantidad) | B13: =CEILING(Onboarding!B12/'Supuestos Generales'!$B$82,1) | C13: =CEILING(Onboarding!C12/'Supuestos Generales'!$B$82,1) | D13: =CEILING(Onboarding!D12/'Supuestos Generales'!$B$82,1) | E13: =CEILING(Onboarding!E12/'Supuestos Generales'!$B$82,1) | F13: =CEILING(Onboarding!F12/'Supuestos Generales'!$B$82,1) | G13: =CEILING(Onboarding!G12/'Supuestos Generales'!$B$82,1) | H13: =CEILING(Onboarding!H12/'Supuestos Generales'!$B$82,1) | I13: =CEILING(Onboarding!I12/'Supuestos Generales'!$B$82,1) | ... BI13: =CEILING(Onboarding!BI12/'Supuestos Generales'!$B$82,1)
A14: Costo Engagement Managers | B14: =B13*'Supuestos Generales'!$B$81 | C14: =C13*'Supuestos Generales'!$B$81 | D14: =D13*'Supuestos Generales'!$B$81 | E14: =E13*'Supuestos Generales'!$B$81 | F14: =F13*'Supuestos Generales'!$B$81 | G14: =G13*'Supuestos Generales'!$B$81 | H14: =H13*'Supuestos Generales'!$B$81 | I14: =I13*'Supuestos Generales'!$B$81 | ... BI14: =BI13*'Supuestos Generales'!$B$81 | BJ14: =SUM(B14:BI14)
A15: Agentes de Customer Success (cantidad) | B15: =CEILING(Onboarding!B12/'Supuestos Generales'!$B$73,1) | C15: =CEILING(Onboarding!C12/'Supuestos Generales'!$B$73,1) | D15: =CEILING(Onboarding!D12/'Supuestos Generales'!$B$73,1) | E15: =CEILING(Onboarding!E12/'Supuestos Generales'!$B$73,1) | F15: =CEILING(Onboarding!F12/'Supuestos Generales'!$B$73,1) | G15: =CEILING(Onboarding!G12/'Supuestos Generales'!$B$73,1) | H15: =CEILING(Onboarding!H12/'Supuestos Generales'!$B$73,1) | I15: =CEILING(Onboarding!I12/'Supuestos Generales'!$B$73,1) | ... BI15: =CEILING(Onboarding!BI12/'Supuestos Generales'!$B$73,1)
A16: Costo Agentes CS | B16: =B15*'Supuestos Generales'!$B$74 | C16: =C15*'Supuestos Generales'!$B$74 | D16: =D15*'Supuestos Generales'!$B$74 | E16: =E15*'Supuestos Generales'!$B$74 | F16: =F15*'Supuestos Generales'!$B$74 | G16: =G15*'Supuestos Generales'!$B$74 | H16: =H15*'Supuestos Generales'!$B$74 | I16: =I15*'Supuestos Generales'!$B$74 | ... BI16: =BI15*'Supuestos Generales'!$B$74 | BJ16: =SUM(B16:BI16)
A17: Gala Anual Super Meseros (mensualizado) | B17: ='Supuestos Generales'!$B$85*(1.1^MAX(0,CEILING(B$3/12,1)-1)) | C17: ='Supuestos Generales'!$B$85*(1.1^MAX(0,CEILING(C$3/12,1)-1)) | D17: ='Supuestos Generales'!$B$85*(1.1^MAX(0,CEILING(D$3/12,1)-1)) | E17: ='Supuestos Generales'!$B$85*(1.1^MAX(0,CEILING(E$3/12,1)-1)) | F17: ='Supuestos Generales'!$B$85*(1.1^MAX(0,CEILING(F$3/12,1)-1)) | G17: ='Supuestos Generales'!$B$85*(1.1^MAX(0,CEILING(G$3/12,1)-1)) | H17: ='Supuestos Generales'!$B$85*(1.1^MAX(0,CEILING(H$3/12,1)-1)) | I17: ='Supuestos Generales'!$B$85*(1.1^MAX(0,CEILING(I$3/12,1)-1)) | ... BI17: ='Supuestos Generales'!$B$85*(1.1^MAX(0,CEILING(BI$3/12,1)-1)) | BJ17: =SUM(B17:BI17)
A18: Plataforma SaaS comunicaciones | B18: ='Supuestos Generales'!$B$86 | C18: ='Supuestos Generales'!$B$86 | D18: ='Supuestos Generales'!$B$86 | E18: ='Supuestos Generales'!$B$86 | F18: ='Supuestos Generales'!$B$86 | G18: ='Supuestos Generales'!$B$86 | H18: ='Supuestos Generales'!$B$86 | I18: ='Supuestos Generales'!$B$86 | ... BI18: ='Supuestos Generales'!$B$86 | BJ18: =SUM(B18:BI18)
A19: Total Costos Engagement | B19: =SUM(B12,B14:B18) | C19: =SUM(C12,C14:C18) | D19: =SUM(D12,D14:D18) | E19: =SUM(E12,E14:E18) | F19: =SUM(F12,F14:F18) | G19: =SUM(G12,G14:G18) | H19: =SUM(H12,H14:H18) | I19: =SUM(I12,I14:I18) | ... BI19: =SUM(BI12,BI14:BI18) | BJ19: =SUM(B19:BI19)
A22: DESCUENTO POR REFERIDOS
A23: Meseros afiliados vía referidos (mes) | B23: =(Onboarding!B7+Onboarding!B8)*'Supuestos Generales'!$B$19*'Supuestos Generales'!$B$20 | C23: =(Onboarding!C7+Onboarding!C8)*'Supuestos Generales'!$B$19*'Supuestos Generales'!$B$20 | D23: =(Onboarding!D7+Onboarding!D8)*'Supuestos Generales'!$B$19*'Supuestos Generales'!$B$20 | E23: =(Onboarding!E7+Onboarding!E8)*'Supuestos Generales'!$B$19*'Supuestos Generales'!$B$20 | F23: =(Onboarding!F7+Onboarding!F8)*'Supuestos Generales'!$B$19*'Supuestos Generales'!$B$20 | G23: =(Onboarding!G7+Onboarding!G8)*'Supuestos Generales'!$B$19*'Supuestos Generales'!$B$20 | H23: =(Onboarding!H7+Onboarding!H8)*'Supuestos Generales'!$B$19*'Supuestos Generales'!$B$20 | I23: =(Onboarding!I7+Onboarding!I8)*'Supuestos Generales'!$B$19*'Supuestos Generales'!$B$20 | ... BI23: =(Onboarding!BI7+Onboarding!BI8)*'Supuestos Generales'!$B$19*'Supuestos Generales'!$B$20 | BJ23: =SUM(B23:BI23)
A24: Meseros gratis otorgados (mes) | B24: =FLOOR(B23/'Supuestos Generales'!$B$90,1) | C24: =FLOOR(C23/'Supuestos Generales'!$B$90,1) | D24: =FLOOR(D23/'Supuestos Generales'!$B$90,1) | E24: =FLOOR(E23/'Supuestos Generales'!$B$90,1) | F24: =FLOOR(F23/'Supuestos Generales'!$B$90,1) | G24: =FLOOR(G23/'Supuestos Generales'!$B$90,1) | H24: =FLOOR(H23/'Supuestos Generales'!$B$90,1) | I24: =FLOOR(I23/'Supuestos Generales'!$B$90,1) | ... BI24: =FLOOR(BI23/'Supuestos Generales'!$B$90,1) | BJ24: =SUM(B24:BI24)
A25: Meseros gratis activos (rolling 12m) | B25: =SUM(OFFSET($B24,0,MAX(0,COLUMN(B24)-COLUMN($B24)-'Supuestos Generales'!$B$93+1),1,MIN(COLUMN(B24)-COLUMN($B24)+1,'Supuestos Generales'!$B$93))) | C25: =SUM(OFFSET($B24,0,MAX(0,COLUMN(C24)-COLUMN($B24)-'Supuestos Generales'!$B$93+1),1,MIN(COLUMN(C24)-COLUMN($B24)+1,'Supuestos Generales'!$B$93))) | D25: =SUM(OFFSET($B24,0,MAX(0,COLUMN(D24)-COLUMN($B24)-'Supuestos Generales'!$B$93+1),1,MIN(COLUMN(D24)-COLUMN($B24)+1,'Supuestos Generales'!$B$93))) | E25: =SUM(OFFSET($B24,0,MAX(0,COLUMN(E24)-COLUMN($B24)-'Supuestos Generales'!$B$93+1),1,MIN(COLUMN(E24)-COLUMN($B24)+1,'Supuestos Generales'!$B$93))) | F25: =SUM(OFFSET($B24,0,MAX(0,COLUMN(F24)-COLUMN($B24)-'Supuestos Generales'!$B$93+1),1,MIN(COLUMN(F24)-COLUMN($B24)+1,'Supuestos Generales'!$B$93))) | G25: =SUM(OFFSET($B24,0,MAX(0,COLUMN(G24)-COLUMN($B24)-'Supuestos Generales'!$B$93+1),1,MIN(COLUMN(G24)-COLUMN($B24)+1,'Supuestos Generales'!$B$93))) | H25: =SUM(OFFSET($B24,0,MAX(0,COLUMN(H24)-COLUMN($B24)-'Supuestos Generales'!$B$93+1),1,MIN(COLUMN(H24)-COLUMN($B24)+1,'Supuestos Generales'!$B$93))) | I25: =SUM(OFFSET($B24,0,MAX(0,COLUMN(I24)-COLUMN($B24)-'Supuestos Generales'!$B$93+1),1,MIN(COLUMN(I24)-COLUMN($B24)+1,'Supuestos Generales'!$B$93))) | ... BI25: =SUM(OFFSET($B24,0,MAX(0,COLUMN(BI24)-COLUMN($B24)-'Supuestos Generales'!$B$93+1),1,MIN(COLUMN(BI24)-COLUMN($B24)+1,'Supuestos Generales'!$B$93))) | BJ25: N/A
A26: Costo descuento meseros gratis | B26: =B25*'Supuestos Generales'!$B$92 | C26: =C25*'Supuestos Generales'!$B$92 | D26: =D25*'Supuestos Generales'!$B$92 | E26: =E25*'Supuestos Generales'!$B$92 | F26: =F25*'Supuestos Generales'!$B$92 | G26: =G25*'Supuestos Generales'!$B$92 | H26: =H25*'Supuestos Generales'!$B$92 | I26: =I25*'Supuestos Generales'!$B$92 | ... BI26: =BI25*'Supuestos Generales'!$B$92 | BJ26: =SUM(B26:BI26)
A29: PROVISIÓN ERRORES Y FRAUDES
A30: Provisión errores humanos (Super Monedas) | B30: =(Ingresos!B14+Ingresos!B15)*'Supuestos Generales'!$B$64 | C30: =(Ingresos!C14+Ingresos!C15)*'Supuestos Generales'!$B$64 | D30: =(Ingresos!D14+Ingresos!D15)*'Supuestos Generales'!$B$64 | E30: =(Ingresos!E14+Ingresos!E15)*'Supuestos Generales'!$B$64 | F30: =(Ingresos!F14+Ingresos!F15)*'Supuestos Generales'!$B$64 | G30: =(Ingresos!G14+Ingresos!G15)*'Supuestos Generales'!$B$64 | H30: =(Ingresos!H14+Ingresos!H15)*'Supuestos Generales'!$B$64 | I30: =(Ingresos!I14+Ingresos!I15)*'Supuestos Generales'!$B$64 | ... BI30: =(Ingresos!BI14+Ingresos!BI15)*'Supuestos Generales'!$B$64 | BJ30: =SUM(B30:BI30)
A31: Provisión fraude (Super Monedas) | B31: =(Ingresos!B14+Ingresos!B15)*'Supuestos Generales'!$B$65 | C31: =(Ingresos!C14+Ingresos!C15)*'Supuestos Generales'!$B$65 | D31: =(Ingresos!D14+Ingresos!D15)*'Supuestos Generales'!$B$65 | E31: =(Ingresos!E14+Ingresos!E15)*'Supuestos Generales'!$B$65 | F31: =(Ingresos!F14+Ingresos!F15)*'Supuestos Generales'!$B$65 | G31: =(Ingresos!G14+Ingresos!G15)*'Supuestos Generales'!$B$65 | H31: =(Ingresos!H14+Ingresos!H15)*'Supuestos Generales'!$B$65 | I31: =(Ingresos!I14+Ingresos!I15)*'Supuestos Generales'!$B$65 | ... BI31: =(Ingresos!BI14+Ingresos!BI15)*'Supuestos Generales'!$B$65 | BJ31: =SUM(B31:BI31)
A32: Total Provisión Errores + Fraude | B32: =B30+B31 | C32: =C30+C31 | D32: =D30+D31 | E32: =E30+E31 | F32: =F30+F31 | G32: =G30+G31 | H32: =H30+H31 | I32: =I30+I31 | ... BI32: =BI30+BI31 | BJ32: =SUM(B32:BI32)
A33: Comisión Pasarela de Pago | B33: ='Supuestos Generales'!$B$37*(Ingresos!B11+Ingresos!B12+Ingresos!B13+Ingresos!B16+(Ingresos!B14+Ingresos!B15)*'Supuestos Generales'!$B$33*'Supuestos Generales'!$B$36) | C33: ='Supuestos Generales'!$B$37*(Ingresos!C11+Ingresos!C12+Ingresos!C13+Ingresos!C16+(Ingresos!C14+Ingresos!C15)*'Supuestos Generales'!$B$33*'Supuestos Generales'!$B$36) | D33: ='Supuestos Generales'!$B$37*(Ingresos!D11+Ingresos!D12+Ingresos!D13+Ingresos!D16+(Ingresos!D14+Ingresos!D15)*'Supuestos Generales'!$B$33*'Supuestos Generales'!$B$36) | E33: ='Supuestos Generales'!$B$37*(Ingresos!E11+Ingresos!E12+Ingresos!E13+Ingresos!E16+(Ingresos!E14+Ingresos!E15)*'Supuestos Generales'!$B$33*'Supuestos Generales'!$B$36) | F33: ='Supuestos Generales'!$B$37*(Ingresos!F11+Ingresos!F12+Ingresos!F13+Ingresos!F16+(Ingresos!F14+Ingresos!F15)*'Supuestos Generales'!$B$33*'Supuestos Generales'!$B$36) | G33: ='Supuestos Generales'!$B$37*(Ingresos!G11+Ingresos!G12+Ingresos!G13+Ingresos!G16+(Ingresos!G14+Ingresos!G15)*'Supuestos Generales'!$B$33*'Supuestos Generales'!$B$36) | H33: ='Supuestos Generales'!$B$37*(Ingresos!H11+Ingresos!H12+Ingresos!H13+Ingresos!H16+(Ingresos!H14+Ingresos!H15)*'Supuestos Generales'!$B$33*'Supuestos Generales'!$B$36) | I33: ='Supuestos Generales'!$B$37*(Ingresos!I11+Ingresos!I12+Ingresos!I13+Ingresos!I16+(Ingresos!I14+Ingresos!I15)*'Supuestos Generales'!$B$33*'Supuestos Generales'!$B$36) | ... BJ33: ='Supuestos Generales'!$B$37*(Ingresos!BJ11+Ingresos!BJ12+Ingresos!BJ13+Ingresos!BJ16+(Ingresos!BJ14+Ingresos!BJ15)*'Supuestos Generales'!$B$33*'Supuestos Generales'!$B$36)
A34: TOTAL COSTOS DIRECTOS | B34: =SUM(B6:B9)+B19+B26+B32+B33 | C34: =SUM(C6:C9)+C19+C26+C32+C33 | D34: =SUM(D6:D9)+D19+D26+D32+D33 | E34: =SUM(E6:E9)+E19+E26+E32+E33 | F34: =SUM(F6:F9)+F19+F26+F32+F33 | G34: =SUM(G6:G9)+G19+G26+G32+G33 | H34: =SUM(H6:H9)+H19+H26+H32+H33 | I34: =SUM(I6:I9)+I19+I26+I32+I33 | ... BI34: =SUM(BI6:BI9)+BI19+BI26+BI32+BI33 | BJ34: =SUM(B34:BI34)
A36: MÁRGENES
A37: Ingresos Totales (ref) | B37: =Ingresos!B19 | C37: =Ingresos!C19 | D37: =Ingresos!D19 | E37: =Ingresos!E19 | F37: =Ingresos!F19 | G37: =Ingresos!G19 | H37: =Ingresos!H19 | I37: =Ingresos!I19 | ... BI37: =Ingresos!BI19 | BJ37: =SUM(B37:BI37)
A38: Margen Bruto ($) | B38: =B37-B34 | C38: =C37-C34 | D38: =D37-D34 | E38: =E37-E34 | F38: =F37-F34 | G38: =G37-G34 | H38: =H37-H34 | I38: =I37-I34 | ... BI38: =BI37-BI34 | BJ38: =SUM(B38:BI38)
A39: Margen Bruto (%) | B39: =IF(B37=0,0,B38/B37) | C39: =IF(C37=0,0,C38/C37) | D39: =IF(D37=0,0,D38/D37) | E39: =IF(E37=0,0,E38/E37) | F39: =IF(F37=0,0,F38/F37) | G39: =IF(G37=0,0,G38/G37) | H39: =IF(H37=0,0,H38/H37) | I39: =IF(I37=0,0,I38/I37) | ... BJ39: =IF(BJ37=0,0,BJ38/BJ37)

Sheet CAC y GTM
A1: CAC Y GTM — Proyección Mensual
A3: Concepto | B3: 1 | C3: 2 | D3: 3 | E3: 4 | F3: 5 | G3: 6 | H3: 7 | I3: 8 | J3: 9 | K3: 10 | L3: 11 | M3: 12 | N3: 13 | O3: 14 | P3: 15 | Q3: 16 | R3: 17 | S3: 18 | T3: 19 | U3: 20 | V3: 21 | W3: 22 | X3: 23 | Y3: 24 | Z3: 25 | AA3: 26 | AB3: 27 | AC3: 28 | AD3: 29 | AE3: 30 | AF3: 31 | AG3: 32 | AH3: 33 | AI3: 34 | AJ3: 35 | AK3: 36 | AL3: 37 | AM3: 38 | AN3: 39 | AO3: 40 | AP3: 41 | AQ3: 42 | AR3: 43 | AS3: 44 | AT3: 45 | AU3: 46 | AV3: 47 | AW3: 48 | AX3: 49 | AY3: 50 | AZ3: 51 | BA3: 52 | BB3: 53 | BC3: 54 | BD3: 55 | BE3: 56 | BF3: 57 | BG3: 58 | BH3: 59 | BI3: 60 | BJ3: TOTAL
A5: COSTOS DE ADQUISICIÓN (DIRECTOS)
A6: Restaurantes nuevos directos | B6: =Onboarding!B6 | C6: =Onboarding!C6 | D6: =Onboarding!D6 | E6: =Onboarding!E6 | F6: =Onboarding!F6 | G6: =Onboarding!G6 | H6: =Onboarding!H6 | I6: =Onboarding!I6 | ... BI6: =Onboarding!BI6 | BJ6: =SUM(B6:BI6)
A7: CAC unitario (según escenario) | B7: =IF('Supuestos Generales'!$B$94=1,'Supuestos Generales'!$B$88,'Supuestos Generales'!$B$89) | C7: =IF('Supuestos Generales'!$B$94=1,'Supuestos Generales'!$B$88,'Supuestos Generales'!$B$89) | D7: =IF('Supuestos Generales'!$B$94=1,'Supuestos Generales'!$B$88,'Supuestos Generales'!$B$89) | E7: =IF('Supuestos Generales'!$B$94=1,'Supuestos Generales'!$B$88,'Supuestos Generales'!$B$89) | F7: =IF('Supuestos Generales'!$B$94=1,'Supuestos Generales'!$B$88,'Supuestos Generales'!$B$89) | G7: =IF('Supuestos Generales'!$B$94=1,'Supuestos Generales'!$B$88,'Supuestos Generales'!$B$89) | H7: =IF('Supuestos Generales'!$B$94=1,'Supuestos Generales'!$B$88,'Supuestos Generales'!$B$89) | I7: =IF('Supuestos Generales'!$B$94=1,'Supuestos Generales'!$B$88,'Supuestos Generales'!$B$89) | ... BI7: =IF('Supuestos Generales'!$B$94=1,'Supuestos Generales'!$B$88,'Supuestos Generales'!$B$89) | BJ7: N/A
A8: Costo adquisición directos | B8: =B6*B7 | C8: =C6*C7 | D8: =D6*D7 | E8: =E6*E7 | F8: =F6*F7 | G8: =G6*G7 | H8: =H6*H7 | I8: =I6*I7 | ... BI8: =BI6*BI7 | BJ8: =SUM(B8:BI8)
A9: COSTOS DE ADQUISICIÓN (ALIANZAS)
A10: Restaurantes nuevos vía alianzas | B10: =Onboarding!B9 | C10: =Onboarding!C9 | D10: =Onboarding!D9 | E10: =Onboarding!E9 | F10: =Onboarding!F9 | G10: =Onboarding!G9 | H10: =Onboarding!H9 | I10: =Onboarding!I9 | ... BI10: =Onboarding!BI9
A11: CAC unitario alianzas (mktg/remarketing) | B11: =Palancas!$B$9 | C11: =Palancas!$B$9 | D11: =Palancas!$B$9 | E11: =Palancas!$B$9 | F11: =Palancas!$B$9 | G11: =Palancas!$B$9 | H11: =Palancas!$B$9 | I11: =Palancas!$B$9 | ... BI11: =Palancas!$B$9
A12: Costo adquisición alianzas | B12: =B10*B11 | C12: =C10*C11 | D12: =D10*D11 | E12: =E10*E11 | F12: =F10*F11 | G12: =G10*G11 | H12: =H10*H11 | I12: =I10*I11 | ... BI12: =BI10*BI11
A14: COMISIONES DE VENTA
A15: Comisiones SetUp - Vendedores propios | B15: =Onboarding!B6*'Supuestos Generales'!$B$96*'Supuestos Generales'!$B$24*'Supuestos Generales'!$B$102 | C15: =Onboarding!C6*'Supuestos Generales'!$B$96*'Supuestos Generales'!$B$24*'Supuestos Generales'!$B$102 | D15: =Onboarding!D6*'Supuestos Generales'!$B$96*'Supuestos Generales'!$B$24*'Supuestos Generales'!$B$102 | E15: =Onboarding!E6*'Supuestos Generales'!$B$96*'Supuestos Generales'!$B$24*'Supuestos Generales'!$B$102 | F15: =Onboarding!F6*'Supuestos Generales'!$B$96*'Supuestos Generales'!$B$24*'Supuestos Generales'!$B$102 | G15: =Onboarding!G6*'Supuestos Generales'!$B$96*'Supuestos Generales'!$B$24*'Supuestos Generales'!$B$102 | H15: =Onboarding!H6*'Supuestos Generales'!$B$96*'Supuestos Generales'!$B$24*'Supuestos Generales'!$B$102 | I15: =Onboarding!I6*'Supuestos Generales'!$B$96*'Supuestos Generales'!$B$24*'Supuestos Generales'!$B$102 | ... BI15: =Onboarding!BI6*'Supuestos Generales'!$B$96*'Supuestos Generales'!$B$24*'Supuestos Generales'!$B$102 | BJ15: =SUM(B15:BI15)
A16: Comisiones SetUp - Vendedores externos | B16: =Onboarding!B6*'Supuestos Generales'!$B$97*'Supuestos Generales'!$B$24*'Supuestos Generales'!$B$103 | C16: =Onboarding!C6*'Supuestos Generales'!$B$97*'Supuestos Generales'!$B$24*'Supuestos Generales'!$B$103 | D16: =Onboarding!D6*'Supuestos Generales'!$B$97*'Supuestos Generales'!$B$24*'Supuestos Generales'!$B$103 | E16: =Onboarding!E6*'Supuestos Generales'!$B$97*'Supuestos Generales'!$B$24*'Supuestos Generales'!$B$103 | F16: =Onboarding!F6*'Supuestos Generales'!$B$97*'Supuestos Generales'!$B$24*'Supuestos Generales'!$B$103 | G16: =Onboarding!G6*'Supuestos Generales'!$B$97*'Supuestos Generales'!$B$24*'Supuestos Generales'!$B$103 | H16: =Onboarding!H6*'Supuestos Generales'!$B$97*'Supuestos Generales'!$B$24*'Supuestos Generales'!$B$103 | I16: =Onboarding!I6*'Supuestos Generales'!$B$97*'Supuestos Generales'!$B$24*'Supuestos Generales'!$B$103 | ... BI16: =Onboarding!BI6*'Supuestos Generales'!$B$97*'Supuestos Generales'!$B$24*'Supuestos Generales'!$B$103 | BJ16: =SUM(B16:BI16)
A17: Comisiones SetUp - Aliados estratégicos | B17: =Onboarding!B6*'Supuestos Generales'!$B$98*'Supuestos Generales'!$B$24*'Supuestos Generales'!$B$104 | C17: =Onboarding!C6*'Supuestos Generales'!$B$98*'Supuestos Generales'!$B$24*'Supuestos Generales'!$B$104 | D17: =Onboarding!D6*'Supuestos Generales'!$B$98*'Supuestos Generales'!$B$24*'Supuestos Generales'!$B$104 | E17: =Onboarding!E6*'Supuestos Generales'!$B$98*'Supuestos Generales'!$B$24*'Supuestos Generales'!$B$104 | F17: =Onboarding!F6*'Supuestos Generales'!$B$98*'Supuestos Generales'!$B$24*'Supuestos Generales'!$B$104 | G17: =Onboarding!G6*'Supuestos Generales'!$B$98*'Supuestos Generales'!$B$24*'Supuestos Generales'!$B$104 | H17: =Onboarding!H6*'Supuestos Generales'!$B$98*'Supuestos Generales'!$B$24*'Supuestos Generales'!$B$104 | I17: =Onboarding!I6*'Supuestos Generales'!$B$98*'Supuestos Generales'!$B$24*'Supuestos Generales'!$B$104 | ... BI17: =Onboarding!BI6*'Supuestos Generales'!$B$98*'Supuestos Generales'!$B$24*'Supuestos Generales'!$B$104 | BJ17: =SUM(B17:BI17)
A18: Comisiones SetUp - Partners POS | B18: =Onboarding!B6*'Supuestos Generales'!$B$99*'Supuestos Generales'!$B$24*'Supuestos Generales'!$B$105 | C18: =Onboarding!C6*'Supuestos Generales'!$B$99*'Supuestos Generales'!$B$24*'Supuestos Generales'!$B$105 | D18: =Onboarding!D6*'Supuestos Generales'!$B$99*'Supuestos Generales'!$B$24*'Supuestos Generales'!$B$105 | E18: =Onboarding!E6*'Supuestos Generales'!$B$99*'Supuestos Generales'!$B$24*'Supuestos Generales'!$B$105 | F18: =Onboarding!F6*'Supuestos Generales'!$B$99*'Supuestos Generales'!$B$24*'Supuestos Generales'!$B$105 | G18: =Onboarding!G6*'Supuestos Generales'!$B$99*'Supuestos Generales'!$B$24*'Supuestos Generales'!$B$105 | H18: =Onboarding!H6*'Supuestos Generales'!$B$99*'Supuestos Generales'!$B$24*'Supuestos Generales'!$B$105 | I18: =Onboarding!I6*'Supuestos Generales'!$B$99*'Supuestos Generales'!$B$24*'Supuestos Generales'!$B$105 | ... BI18: =Onboarding!BI6*'Supuestos Generales'!$B$99*'Supuestos Generales'!$B$24*'Supuestos Generales'!$B$105 | BJ18: =SUM(B18:BI18)
A19: Comisiones Fees 1er año - Vend. propios | B19: =SUM(OFFSET(Onboarding!$B6,0,MAX(0,COLUMN(B3)-COLUMN($B$3)-'Supuestos Generales'!$B$111+1),1,MIN(COLUMN(B3)-COLUMN($B$3)+1,'Supuestos Generales'!$B$111)))*'Supuestos Generales'!$B$96*('Supuestos Generales'!$B$26*'Supuestos Generales'!$B$19*'Supuestos Generales'!$B$20+'Supuestos Generales'!$B$27*'Supuestos Generales'!$B$19*'Supuestos Generales'!$B$20*Onboarding!B22)*'Supuestos Generales'!$B$107 | C19: =SUM(OFFSET(Onboarding!$B6,0,MAX(0,COLUMN(C3)-COLUMN($B$3)-'Supuestos Generales'!$B$111+1),1,MIN(COLUMN(C3)-COLUMN($B$3)+1,'Supuestos Generales'!$B$111)))*'Supuestos Generales'!$B$96*('Supuestos Generales'!$B$26*'Supuestos Generales'!$B$19*'Supuestos Generales'!$B$20+'Supuestos Generales'!$B$27*'Supuestos Generales'!$B$19*'Supuestos Generales'!$B$20*Onboarding!C22)*'Supuestos Generales'!$B$107 | D19: =SUM(OFFSET(Onboarding!$B6,0,MAX(0,COLUMN(D3)-COLUMN($B$3)-'Supuestos Generales'!$B$111+1),1,MIN(COLUMN(D3)-COLUMN($B$3)+1,'Supuestos Generales'!$B$111)))*'Supuestos Generales'!$B$96*('Supuestos Generales'!$B$26*'Supuestos Generales'!$B$19*'Supuestos Generales'!$B$20+'Supuestos Generales'!$B$27*'Supuestos Generales'!$B$19*'Supuestos Generales'!$B$20*Onboarding!D22)*'Supuestos Generales'!$B$107 | E19: =SUM(OFFSET(Onboarding!$B6,0,MAX(0,COLUMN(E3)-COLUMN($B$3)-'Supuestos Generales'!$B$111+1),1,MIN(COLUMN(E3)-COLUMN($B$3)+1,'Supuestos Generales'!$B$111)))*'Supuestos Generales'!$B$96*('Supuestos Generales'!$B$26*'Supuestos Generales'!$B$19*'Supuestos Generales'!$B$20+'Supuestos Generales'!$B$27*'Supuestos Generales'!$B$19*'Supuestos Generales'!$B$20*Onboarding!E22)*'Supuestos Generales'!$B$107 | F19: =SUM(OFFSET(Onboarding!$B6,0,MAX(0,COLUMN(F3)-COLUMN($B$3)-'Supuestos Generales'!$B$111+1),1,MIN(COLUMN(F3)-COLUMN($B$3)+1,'Supuestos Generales'!$B$111)))*'Supuestos Generales'!$B$96*('Supuestos Generales'!$B$26*'Supuestos Generales'!$B$19*'Supuestos Generales'!$B$20+'Supuestos Generales'!$B$27*'Supuestos Generales'!$B$19*'Supuestos Generales'!$B$20*Onboarding!F22)*'Supuestos Generales'!$B$107 | G19: =SUM(OFFSET(Onboarding!$B6,0,MAX(0,COLUMN(G3)-COLUMN($B$3)-'Supuestos Generales'!$B$111+1),1,MIN(COLUMN(G3)-COLUMN($B$3)+1,'Supuestos Generales'!$B$111)))*'Supuestos Generales'!$B$96*('Supuestos Generales'!$B$26*'Supuestos Generales'!$B$19*'Supuestos Generales'!$B$20+'Supuestos Generales'!$B$27*'Supuestos Generales'!$B$19*'Supuestos Generales'!$B$20*Onboarding!G22)*'Supuestos Generales'!$B$107 | H19: =SUM(OFFSET(Onboarding!$B6,0,MAX(0,COLUMN(H3)-COLUMN($B$3)-'Supuestos Generales'!$B$111+1),1,MIN(COLUMN(H3)-COLUMN($B$3)+1,'Supuestos Generales'!$B$111)))*'Supuestos Generales'!$B$96*('Supuestos Generales'!$B$26*'Supuestos Generales'!$B$19*'Supuestos Generales'!$B$20+'Supuestos Generales'!$B$27*'Supuestos Generales'!$B$19*'Supuestos Generales'!$B$20*Onboarding!H22)*'Supuestos Generales'!$B$107 | I19: =SUM(OFFSET(Onboarding!$B6,0,MAX(0,COLUMN(I3)-COLUMN($B$3)-'Supuestos Generales'!$B$111+1),1,MIN(COLUMN(I3)-COLUMN($B$3)+1,'Supuestos Generales'!$B$111)))*'Supuestos Generales'!$B$96*('Supuestos Generales'!$B$26*'Supuestos Generales'!$B$19*'Supuestos Generales'!$B$20+'Supuestos Generales'!$B$27*'Supuestos Generales'!$B$19*'Supuestos Generales'!$B$20*Onboarding!I22)*'Supuestos Generales'!$B$107 | ... BI19: =SUM(OFFSET(Onboarding!$B6,0,MAX(0,COLUMN(BI3)-COLUMN($B$3)-'Supuestos Generales'!$B$111+1),1,MIN(COLUMN(BI3)-COLUMN($B$3)+1,'Supuestos Generales'!$B$111)))*'Supuestos Generales'!$B$96*('Supuestos Generales'!$B$26*'Supuestos Generales'!$B$19*'Supuestos Generales'!$B$20+'Supuestos Generales'!$B$27*'Supuestos Generales'!$B$19*'Supuestos Generales'!$B$20*Onboarding!BI22)*'Supuestos Generales'!$B$107 | BJ19: =SUM(B19:BI19)
A20: Comisiones Fees 1er año - Vend. externos | B20: =SUM(OFFSET(Onboarding!$B6,0,MAX(0,COLUMN(B3)-COLUMN($B$3)-'Supuestos Generales'!$B$111+1),1,MIN(COLUMN(B3)-COLUMN($B$3)+1,'Supuestos Generales'!$B$111)))*'Supuestos Generales'!$B$97*('Supuestos Generales'!$B$26*'Supuestos Generales'!$B$19*'Supuestos Generales'!$B$20+'Supuestos Generales'!$B$27*'Supuestos Generales'!$B$19*'Supuestos Generales'!$B$20*Onboarding!B22)*'Supuestos Generales'!$B$108 | C20: =SUM(OFFSET(Onboarding!$B6,0,MAX(0,COLUMN(C3)-COLUMN($B$3)-'Supuestos Generales'!$B$111+1),1,MIN(COLUMN(C3)-COLUMN($B$3)+1,'Supuestos Generales'!$B$111)))*'Supuestos Generales'!$B$97*('Supuestos Generales'!$B$26*'Supuestos Generales'!$B$19*'Supuestos Generales'!$B$20+'Supuestos Generales'!$B$27*'Supuestos Generales'!$B$19*'Supuestos Generales'!$B$20*Onboarding!C22)*'Supuestos Generales'!$B$108 | D20: =SUM(OFFSET(Onboarding!$B6,0,MAX(0,COLUMN(D3)-COLUMN($B$3)-'Supuestos Generales'!$B$111+1),1,MIN(COLUMN(D3)-COLUMN($B$3)+1,'Supuestos Generales'!$B$111)))*'Supuestos Generales'!$B$97*('Supuestos Generales'!$B$26*'Supuestos Generales'!$B$19*'Supuestos Generales'!$B$20+'Supuestos Generales'!$B$27*'Supuestos Generales'!$B$19*'Supuestos Generales'!$B$20*Onboarding!D22)*'Supuestos Generales'!$B$108 | E20: =SUM(OFFSET(Onboarding!$B6,0,MAX(0,COLUMN(E3)-COLUMN($B$3)-'Supuestos Generales'!$B$111+1),1,MIN(COLUMN(E3)-COLUMN($B$3)+1,'Supuestos Generales'!$B$111)))*'Supuestos Generales'!$B$97*('Supuestos Generales'!$B$26*'Supuestos Generales'!$B$19*'Supuestos Generales'!$B$20+'Supuestos Generales'!$B$27*'Supuestos Generales'!$B$19*'Supuestos Generales'!$B$20*Onboarding!E22)*'Supuestos Generales'!$B$108 | F20: =SUM(OFFSET(Onboarding!$B6,0,MAX(0,COLUMN(F3)-COLUMN($B$3)-'Supuestos Generales'!$B$111+1),1,MIN(COLUMN(F3)-COLUMN($B$3)+1,'Supuestos Generales'!$B$111)))*'Supuestos Generales'!$B$97*('Supuestos Generales'!$B$26*'Supuestos Generales'!$B$19*'Supuestos Generales'!$B$20+'Supuestos Generales'!$B$27*'Supuestos Generales'!$B$19*'Supuestos Generales'!$B$20*Onboarding!F22)*'Supuestos Generales'!$B$108 | G20: =SUM(OFFSET(Onboarding!$B6,0,MAX(0,COLUMN(G3)-COLUMN($B$3)-'Supuestos Generales'!$B$111+1),1,MIN(COLUMN(G3)-COLUMN($B$3)+1,'Supuestos Generales'!$B$111)))*'Supuestos Generales'!$B$97*('Supuestos Generales'!$B$26*'Supuestos Generales'!$B$19*'Supuestos Generales'!$B$20+'Supuestos Generales'!$B$27*'Supuestos Generales'!$B$19*'Supuestos Generales'!$B$20*Onboarding!G22)*'Supuestos Generales'!$B$108 | H20: =SUM(OFFSET(Onboarding!$B6,0,MAX(0,COLUMN(H3)-COLUMN($B$3)-'Supuestos Generales'!$B$111+1),1,MIN(COLUMN(H3)-COLUMN($B$3)+1,'Supuestos Generales'!$B$111)))*'Supuestos Generales'!$B$97*('Supuestos Generales'!$B$26*'Supuestos Generales'!$B$19*'Supuestos Generales'!$B$20+'Supuestos Generales'!$B$27*'Supuestos Generales'!$B$19*'Supuestos Generales'!$B$20*Onboarding!H22)*'Supuestos Generales'!$B$108 | I20: =SUM(OFFSET(Onboarding!$B6,0,MAX(0,COLUMN(I3)-COLUMN($B$3)-'Supuestos Generales'!$B$111+1),1,MIN(COLUMN(I3)-COLUMN($B$3)+1,'Supuestos Generales'!$B$111)))*'Supuestos Generales'!$B$97*('Supuestos Generales'!$B$26*'Supuestos Generales'!$B$19*'Supuestos Generales'!$B$20+'Supuestos Generales'!$B$27*'Supuestos Generales'!$B$19*'Supuestos Generales'!$B$20*Onboarding!I22)*'Supuestos Generales'!$B$108 | ... BI20: =SUM(OFFSET(Onboarding!$B6,0,MAX(0,COLUMN(BI3)-COLUMN($B$3)-'Supuestos Generales'!$B$111+1),1,MIN(COLUMN(BI3)-COLUMN($B$3)+1,'Supuestos Generales'!$B$111)))*'Supuestos Generales'!$B$97*('Supuestos Generales'!$B$26*'Supuestos Generales'!$B$19*'Supuestos Generales'!$B$20+'Supuestos Generales'!$B$27*'Supuestos Generales'!$B$19*'Supuestos Generales'!$B$20*Onboarding!BI22)*'Supuestos Generales'!$B$108 | BJ20: =SUM(B20:BI20)
A21: Comisiones Fees 1er año - Aliados | B21: =SUM(OFFSET(Onboarding!$B6,0,MAX(0,COLUMN(B3)-COLUMN($B$3)-'Supuestos Generales'!$B$111+1),1,MIN(COLUMN(B3)-COLUMN($B$3)+1,'Supuestos Generales'!$B$111)))*'Supuestos Generales'!$B$98*('Supuestos Generales'!$B$26*'Supuestos Generales'!$B$19*'Supuestos Generales'!$B$20+'Supuestos Generales'!$B$27*'Supuestos Generales'!$B$19*'Supuestos Generales'!$B$20*Onboarding!B22)*'Supuestos Generales'!$B$109 | C21: =SUM(OFFSET(Onboarding!$B6,0,MAX(0,COLUMN(C3)-COLUMN($B$3)-'Supuestos Generales'!$B$111+1),1,MIN(COLUMN(C3)-COLUMN($B$3)+1,'Supuestos Generales'!$B$111)))*'Supuestos Generales'!$B$98*('Supuestos Generales'!$B$26*'Supuestos Generales'!$B$19*'Supuestos Generales'!$B$20+'Supuestos Generales'!$B$27*'Supuestos Generales'!$B$19*'Supuestos Generales'!$B$20*Onboarding!C22)*'Supuestos Generales'!$B$109 | D21: =SUM(OFFSET(Onboarding!$B6,0,MAX(0,COLUMN(D3)-COLUMN($B$3)-'Supuestos Generales'!$B$111+1),1,MIN(COLUMN(D3)-COLUMN($B$3)+1,'Supuestos Generales'!$B$111)))*'Supuestos Generales'!$B$98*('Supuestos Generales'!$B$26*'Supuestos Generales'!$B$19*'Supuestos Generales'!$B$20+'Supuestos Generales'!$B$27*'Supuestos Generales'!$B$19*'Supuestos Generales'!$B$20*Onboarding!D22)*'Supuestos Generales'!$B$109 | E21: =SUM(OFFSET(Onboarding!$B6,0,MAX(0,COLUMN(E3)-COLUMN($B$3)-'Supuestos Generales'!$B$111+1),1,MIN(COLUMN(E3)-COLUMN($B$3)+1,'Supuestos Generales'!$B$111)))*'Supuestos Generales'!$B$98*('Supuestos Generales'!$B$26*'Supuestos Generales'!$B$19*'Supuestos Generales'!$B$20+'Supuestos Generales'!$B$27*'Supuestos Generales'!$B$19*'Supuestos Generales'!$B$20*Onboarding!E22)*'Supuestos Generales'!$B$109 | F21: =SUM(OFFSET(Onboarding!$B6,0,MAX(0,COLUMN(F3)-COLUMN($B$3)-'Supuestos Generales'!$B$111+1),1,MIN(COLUMN(F3)-COLUMN($B$3)+1,'Supuestos Generales'!$B$111)))*'Supuestos Generales'!$B$98*('Supuestos Generales'!$B$26*'Supuestos Generales'!$B$19*'Supuestos Generales'!$B$20+'Supuestos Generales'!$B$27*'Supuestos Generales'!$B$19*'Supuestos Generales'!$B$20*Onboarding!F22)*'Supuestos Generales'!$B$109 | G21: =SUM(OFFSET(Onboarding!$B6,0,MAX(0,COLUMN(G3)-COLUMN($B$3)-'Supuestos Generales'!$B$111+1),1,MIN(COLUMN(G3)-COLUMN($B$3)+1,'Supuestos Generales'!$B$111)))*'Supuestos Generales'!$B$98*('Supuestos Generales'!$B$26*'Supuestos Generales'!$B$19*'Supuestos Generales'!$B$20+'Supuestos Generales'!$B$27*'Supuestos Generales'!$B$19*'Supuestos Generales'!$B$20*Onboarding!G22)*'Supuestos Generales'!$B$109 | H21: =SUM(OFFSET(Onboarding!$B6,0,MAX(0,COLUMN(H3)-COLUMN($B$3)-'Supuestos Generales'!$B$111+1),1,MIN(COLUMN(H3)-COLUMN($B$3)+1,'Supuestos Generales'!$B$111)))*'Supuestos Generales'!$B$98*('Supuestos Generales'!$B$26*'Supuestos Generales'!$B$19*'Supuestos Generales'!$B$20+'Supuestos Generales'!$B$27*'Supuestos Generales'!$B$19*'Supuestos Generales'!$B$20*Onboarding!H22)*'Supuestos Generales'!$B$109 | I21: =SUM(OFFSET(Onboarding!$B6,0,MAX(0,COLUMN(I3)-COLUMN($B$3)-'Supuestos Generales'!$B$111+1),1,MIN(COLUMN(I3)-COLUMN($B$3)+1,'Supuestos Generales'!$B$111)))*'Supuestos Generales'!$B$98*('Supuestos Generales'!$B$26*'Supuestos Generales'!$B$19*'Supuestos Generales'!$B$20+'Supuestos Generales'!$B$27*'Supuestos Generales'!$B$19*'Supuestos Generales'!$B$20*Onboarding!I22)*'Supuestos Generales'!$B$109 | ... BI21: =SUM(OFFSET(Onboarding!$B6,0,MAX(0,COLUMN(BI3)-COLUMN($B$3)-'Supuestos Generales'!$B$111+1),1,MIN(COLUMN(BI3)-COLUMN($B$3)+1,'Supuestos Generales'!$B$111)))*'Supuestos Generales'!$B$98*('Supuestos Generales'!$B$26*'Supuestos Generales'!$B$19*'Supuestos Generales'!$B$20+'Supuestos Generales'!$B$27*'Supuestos Generales'!$B$19*'Supuestos Generales'!$B$20*Onboarding!BI22)*'Supuestos Generales'!$B$109 | BJ21: =SUM(B21:BI21)
A22: Comisiones Fees 1er año - Partners POS | B22: =SUM(OFFSET(Onboarding!$B6,0,MAX(0,COLUMN(B3)-COLUMN($B$3)-'Supuestos Generales'!$B$111+1),1,MIN(COLUMN(B3)-COLUMN($B$3)+1,'Supuestos Generales'!$B$111)))*'Supuestos Generales'!$B$99*('Supuestos Generales'!$B$26*'Supuestos Generales'!$B$19*'Supuestos Generales'!$B$20+'Supuestos Generales'!$B$27*'Supuestos Generales'!$B$19*'Supuestos Generales'!$B$20*Onboarding!B22)*'Supuestos Generales'!$B$110 | C22: =SUM(OFFSET(Onboarding!$B6,0,MAX(0,COLUMN(C3)-COLUMN($B$3)-'Supuestos Generales'!$B$111+1),1,MIN(COLUMN(C3)-COLUMN($B$3)+1,'Supuestos Generales'!$B$111)))*'Supuestos Generales'!$B$99*('Supuestos Generales'!$B$26*'Supuestos Generales'!$B$19*'Supuestos Generales'!$B$20+'Supuestos Generales'!$B$27*'Supuestos Generales'!$B$19*'Supuestos Generales'!$B$20*Onboarding!C22)*'Supuestos Generales'!$B$110 | D22: =SUM(OFFSET(Onboarding!$B6,0,MAX(0,COLUMN(D3)-COLUMN($B$3)-'Supuestos Generales'!$B$111+1),1,MIN(COLUMN(D3)-COLUMN($B$3)+1,'Supuestos Generales'!$B$111)))*'Supuestos Generales'!$B$99*('Supuestos Generales'!$B$26*'Supuestos Generales'!$B$19*'Supuestos Generales'!$B$20+'Supuestos Generales'!$B$27*'Supuestos Generales'!$B$19*'Supuestos Generales'!$B$20*Onboarding!D22)*'Supuestos Generales'!$B$110 | E22: =SUM(OFFSET(Onboarding!$B6,0,MAX(0,COLUMN(E3)-COLUMN($B$3)-'Supuestos Generales'!$B$111+1),1,MIN(COLUMN(E3)-COLUMN($B$3)+1,'Supuestos Generales'!$B$111)))*'Supuestos Generales'!$B$99*('Supuestos Generales'!$B$26*'Supuestos Generales'!$B$19*'Supuestos Generales'!$B$20+'Supuestos Generales'!$B$27*'Supuestos Generales'!$B$19*'Supuestos Generales'!$B$20*Onboarding!E22)*'Supuestos Generales'!$B$110 | F22: =SUM(OFFSET(Onboarding!$B6,0,MAX(0,COLUMN(F3)-COLUMN($B$3)-'Supuestos Generales'!$B$111+1),1,MIN(COLUMN(F3)-COLUMN($B$3)+1,'Supuestos Generales'!$B$111)))*'Supuestos Generales'!$B$99*('Supuestos Generales'!$B$26*'Supuestos Generales'!$B$19*'Supuestos Generales'!$B$20+'Supuestos Generales'!$B$27*'Supuestos Generales'!$B$19*'Supuestos Generales'!$B$20*Onboarding!F22)*'Supuestos Generales'!$B$110 | G22: =SUM(OFFSET(Onboarding!$B6,0,MAX(0,COLUMN(G3)-COLUMN($B$3)-'Supuestos Generales'!$B$111+1),1,MIN(COLUMN(G3)-COLUMN($B$3)+1,'Supuestos Generales'!$B$111)))*'Supuestos Generales'!$B$99*('Supuestos Generales'!$B$26*'Supuestos Generales'!$B$19*'Supuestos Generales'!$B$20+'Supuestos Generales'!$B$27*'Supuestos Generales'!$B$19*'Supuestos Generales'!$B$20*Onboarding!G22)*'Supuestos Generales'!$B$110 | H22: =SUM(OFFSET(Onboarding!$B6,0,MAX(0,COLUMN(H3)-COLUMN($B$3)-'Supuestos Generales'!$B$111+1),1,MIN(COLUMN(H3)-COLUMN($B$3)+1,'Supuestos Generales'!$B$111)))*'Supuestos Generales'!$B$99*('Supuestos Generales'!$B$26*'Supuestos Generales'!$B$19*'Supuestos Generales'!$B$20+'Supuestos Generales'!$B$27*'Supuestos Generales'!$B$19*'Supuestos Generales'!$B$20*Onboarding!H22)*'Supuestos Generales'!$B$110 | I22: =SUM(OFFSET(Onboarding!$B6,0,MAX(0,COLUMN(I3)-COLUMN($B$3)-'Supuestos Generales'!$B$111+1),1,MIN(COLUMN(I3)-COLUMN($B$3)+1,'Supuestos Generales'!$B$111)))*'Supuestos Generales'!$B$99*('Supuestos Generales'!$B$26*'Supuestos Generales'!$B$19*'Supuestos Generales'!$B$20+'Supuestos Generales'!$B$27*'Supuestos Generales'!$B$19*'Supuestos Generales'!$B$20*Onboarding!I22)*'Supuestos Generales'!$B$110 | ... BI22: =SUM(OFFSET(Onboarding!$B6,0,MAX(0,COLUMN(BI3)-COLUMN($B$3)-'Supuestos Generales'!$B$111+1),1,MIN(COLUMN(BI3)-COLUMN($B$3)+1,'Supuestos Generales'!$B$111)))*'Supuestos Generales'!$B$99*('Supuestos Generales'!$B$26*'Supuestos Generales'!$B$19*'Supuestos Generales'!$B$20+'Supuestos Generales'!$B$27*'Supuestos Generales'!$B$19*'Supuestos Generales'!$B$20*Onboarding!BI22)*'Supuestos Generales'!$B$110 | BJ22: =SUM(B22:BI22)
A23: Total Comisiones de Venta | B23: =SUM(B15:B22) | C23: =SUM(C15:C22) | D23: =SUM(D15:D22) | E23: =SUM(E15:E22) | F23: =SUM(F15:F22) | G23: =SUM(G15:G22) | H23: =SUM(H15:H22) | I23: =SUM(I15:I22) | ... BI23: =SUM(BI15:BI22) | BJ23: =SUM(B23:BI23)
A25: PUBLICIDAD Y MARKETING
A26: Gasto publicidad y marketing | B26: =IF(B$3>='Supuestos Generales'!$B$114,Ingresos!B19*'Supuestos Generales'!$B$113,0) | C26: =IF(C$3>='Supuestos Generales'!$B$114,Ingresos!C19*'Supuestos Generales'!$B$113,0) | D26: =IF(D$3>='Supuestos Generales'!$B$114,Ingresos!D19*'Supuestos Generales'!$B$113,0) | E26: =IF(E$3>='Supuestos Generales'!$B$114,Ingresos!E19*'Supuestos Generales'!$B$113,0) | F26: =IF(F$3>='Supuestos Generales'!$B$114,Ingresos!F19*'Supuestos Generales'!$B$113,0) | G26: =IF(G$3>='Supuestos Generales'!$B$114,Ingresos!G19*'Supuestos Generales'!$B$113,0) | H26: =IF(H$3>='Supuestos Generales'!$B$114,Ingresos!H19*'Supuestos Generales'!$B$113,0) | I26: =IF(I$3>='Supuestos Generales'!$B$114,Ingresos!I19*'Supuestos Generales'!$B$113,0) | ... BI26: =IF(BI$3>='Supuestos Generales'!$B$114,Ingresos!BI19*'Supuestos Generales'!$B$113,0) | BJ26: =SUM(B26:BI26)
A27: Total Publicidad y Marketing | B27: =B26 | C27: =C26 | D27: =D26 | E27: =E26 | F27: =F26 | G27: =G26 | H27: =H26 | I27: =I26 | ... BI27: =BI26 | BJ27: =SUM(B27:BI27)
A28: MÉTRICAS GTM
A29: Total restaurantes nuevos (mes) | B29: =Onboarding!B10 | C29: =Onboarding!C10 | D29: =Onboarding!D10 | E29: =Onboarding!E10 | F29: =Onboarding!F10 | G29: =Onboarding!G10 | H29: =Onboarding!H10 | I29: =Onboarding!I10 | ... BI29: =Onboarding!BI10 | BJ29: =SUM(B29:BI29)
A30: CAC Blended (incl. descuento referidos) | B30: =IF(B29=0,0,(B8+B12+B23+B27+'Costos Directos'!B26)/B29) | C30: =IF(C29=0,0,(C8+C12+C23+C27+'Costos Directos'!C26)/C29) | D30: =IF(D29=0,0,(D8+D12+D23+D27+'Costos Directos'!D26)/D29) | E30: =IF(E29=0,0,(E8+E12+E23+E27+'Costos Directos'!E26)/E29) | F30: =IF(F29=0,0,(F8+F12+F23+F27+'Costos Directos'!F26)/F29) | G30: =IF(G29=0,0,(G8+G12+G23+G27+'Costos Directos'!G26)/G29) | H30: =IF(H29=0,0,(H8+H12+H23+H27+'Costos Directos'!H26)/H29) | I30: =IF(I29=0,0,(I8+I12+I23+I27+'Costos Directos'!I26)/I29) | ... BI30: =IF(BI29=0,0,(BI8+BI12+BI23+BI27+'Costos Directos'!BI26)/BI29) | BJ30: =IF(BJ29=0,0,BJ8/BJ29)
A31: LTV estimado por restaurante (12m) | B31: =IF(Onboarding!B12=0,0,(Ingresos!B17/Onboarding!B12)*12) | C31: =IF(Onboarding!C12=0,0,(Ingresos!C17/Onboarding!C12)*12) | D31: =IF(Onboarding!D12=0,0,(Ingresos!D17/Onboarding!D12)*12) | E31: =IF(Onboarding!E12=0,0,(Ingresos!E17/Onboarding!E12)*12) | F31: =IF(Onboarding!F12=0,0,(Ingresos!F17/Onboarding!F12)*12) | G31: =IF(Onboarding!G12=0,0,(Ingresos!G17/Onboarding!G12)*12) | H31: =IF(Onboarding!H12=0,0,(Ingresos!H17/Onboarding!H12)*12) | I31: =IF(Onboarding!I12=0,0,(Ingresos!I17/Onboarding!I12)*12) | ... BI31: =IF(Onboarding!BI12=0,0,(Ingresos!BI17/Onboarding!BI12)*12) | BJ31: N/A
A32: LTV / CAC Blended | B32: =IF(B30=0,0,B31/B30) | C32: =IF(C30=0,0,C31/C30) | D32: =IF(D30=0,0,D31/D30) | E32: =IF(E30=0,0,E31/E30) | F32: =IF(F30=0,0,F31/F30) | G32: =IF(G30=0,0,G31/G30) | H32: =IF(H30=0,0,H31/H30) | I32: =IF(I30=0,0,I31/I30) | ... BI32: =IF(BI30=0,0,BI31/BI30) | BJ32: N/A
A34: TOTAL CAC | B34: =B8+B12+B23+B27 | C34: =C8+C12+C23+C27 | D34: =D8+D12+D23+D27 | E34: =E8+E12+E23+E27 | F34: =F8+F12+F23+F27 | G34: =G8+G12+G23+G27 | H34: =H8+H12+H23+H27 | I34: =I8+I12+I23+I27 | ... BI34: =BI8+BI12+BI23+BI27 | BJ34: =SUM(B34:BI34)
A36: ACUMULADOS
A37: CAC Acumulado | B37: =B34 | C37: =B37+C34 | D37: =C37+D34 | E37: =D37+E34 | F37: =E37+F34 | G37: =F37+G34 | H37: =G37+H34 | I37: =H37+I34 | J37: =I37+J34 | ... BI37: =BH37+BI34 | BJ37: =BI37

Sheet OPEX
A1: OPEX — Proyección Mensual
A3: Concepto | B3: 1 | C3: 2 | D3: 3 | E3: 4 | F3: 5 | G3: 6 | H3: 7 | I3: 8 | J3: 9 | K3: 10 | L3: 11 | M3: 12 | N3: 13 | O3: 14 | P3: 15 | Q3: 16 | R3: 17 | S3: 18 | T3: 19 | U3: 20 | V3: 21 | W3: 22 | X3: 23 | Y3: 24 | Z3: 25 | AA3: 26 | AB3: 27 | AC3: 28 | AD3: 29 | AE3: 30 | AF3: 31 | AG3: 32 | AH3: 33 | AI3: 34 | AJ3: 35 | AK3: 36 | AL3: 37 | AM3: 38 | AN3: 39 | AO3: 40 | AP3: 41 | AQ3: 42 | AR3: 43 | AS3: 44 | AT3: 45 | AU3: 46 | AV3: 47 | AW3: 48 | AX3: 49 | AY3: 50 | AZ3: 51 | BA3: 52 | BB3: 53 | BC3: 54 | BD3: 55 | BE3: 56 | BF3: 57 | BG3: 58 | BH3: 59 | BI3: 60 | BJ3: TOTAL
A5: COSTOS FIJOS MENSUALES
A6: Equipo Producto (devs, diseño) | B6: ='Supuestos Generales'!$B$118*'Supuestos Generales'!$B$127*(1+'Supuestos Generales'!$B$128)^B$20 | C6: ='Supuestos Generales'!$B$118*'Supuestos Generales'!$B$127*(1+'Supuestos Generales'!$B$128)^C$20 | D6: ='Supuestos Generales'!$B$118*'Supuestos Generales'!$B$127*(1+'Supuestos Generales'!$B$128)^D$20 | E6: ='Supuestos Generales'!$B$118*'Supuestos Generales'!$B$127*(1+'Supuestos Generales'!$B$128)^E$20 | F6: ='Supuestos Generales'!$B$118*'Supuestos Generales'!$B$127*(1+'Supuestos Generales'!$B$128)^F$20 | G6: ='Supuestos Generales'!$B$118*'Supuestos Generales'!$B$127*(1+'Supuestos Generales'!$B$128)^G$20 | H6: ='Supuestos Generales'!$B$118*'Supuestos Generales'!$B$127*(1+'Supuestos Generales'!$B$128)^H$20 | I6: ='Supuestos Generales'!$B$118*'Supuestos Generales'!$B$127*(1+'Supuestos Generales'!$B$128)^I$20 | ... BI6: ='Supuestos Generales'!$B$118*'Supuestos Generales'!$B$127*(1+'Supuestos Generales'!$B$128)^BI$20 | BJ6: =SUM(B6:BI6)
A7: Equipo Analítica | B7: ='Supuestos Generales'!$B$119*'Supuestos Generales'!$B$127*(1+'Supuestos Generales'!$B$128)^B$20 | C7: ='Supuestos Generales'!$B$119*'Supuestos Generales'!$B$127*(1+'Supuestos Generales'!$B$128)^C$20 | D7: ='Supuestos Generales'!$B$119*'Supuestos Generales'!$B$127*(1+'Supuestos Generales'!$B$128)^D$20 | E7: ='Supuestos Generales'!$B$119*'Supuestos Generales'!$B$127*(1+'Supuestos Generales'!$B$128)^E$20 | F7: ='Supuestos Generales'!$B$119*'Supuestos Generales'!$B$127*(1+'Supuestos Generales'!$B$128)^F$20 | G7: ='Supuestos Generales'!$B$119*'Supuestos Generales'!$B$127*(1+'Supuestos Generales'!$B$128)^G$20 | H7: ='Supuestos Generales'!$B$119*'Supuestos Generales'!$B$127*(1+'Supuestos Generales'!$B$128)^H$20 | I7: ='Supuestos Generales'!$B$119*'Supuestos Generales'!$B$127*(1+'Supuestos Generales'!$B$128)^I$20 | ... BI7: ='Supuestos Generales'!$B$119*'Supuestos Generales'!$B$127*(1+'Supuestos Generales'!$B$128)^BI$20 | BJ7: =SUM(B7:BI7)
A8: Equipo Operaciones | B8: ='Supuestos Generales'!$B$120*'Supuestos Generales'!$B$127*(1+'Supuestos Generales'!$B$128)^B$20 | C8: ='Supuestos Generales'!$B$120*'Supuestos Generales'!$B$127*(1+'Supuestos Generales'!$B$128)^C$20 | D8: ='Supuestos Generales'!$B$120*'Supuestos Generales'!$B$127*(1+'Supuestos Generales'!$B$128)^D$20 | E8: ='Supuestos Generales'!$B$120*'Supuestos Generales'!$B$127*(1+'Supuestos Generales'!$B$128)^E$20 | F8: ='Supuestos Generales'!$B$120*'Supuestos Generales'!$B$127*(1+'Supuestos Generales'!$B$128)^F$20 | G8: ='Supuestos Generales'!$B$120*'Supuestos Generales'!$B$127*(1+'Supuestos Generales'!$B$128)^G$20 | H8: ='Supuestos Generales'!$B$120*'Supuestos Generales'!$B$127*(1+'Supuestos Generales'!$B$128)^H$20 | I8: ='Supuestos Generales'!$B$120*'Supuestos Generales'!$B$127*(1+'Supuestos Generales'!$B$128)^I$20 | ... BI8: ='Supuestos Generales'!$B$120*'Supuestos Generales'!$B$127*(1+'Supuestos Generales'!$B$128)^BI$20 | BJ8: =SUM(B8:BI8)
A9: Equipo Ventas | B9: ='Supuestos Generales'!$B$121*'Supuestos Generales'!$B$127*(1+'Supuestos Generales'!$B$128)^B$20 | C9: ='Supuestos Generales'!$B$121*'Supuestos Generales'!$B$127*(1+'Supuestos Generales'!$B$128)^C$20 | D9: ='Supuestos Generales'!$B$121*'Supuestos Generales'!$B$127*(1+'Supuestos Generales'!$B$128)^D$20 | E9: ='Supuestos Generales'!$B$121*'Supuestos Generales'!$B$127*(1+'Supuestos Generales'!$B$128)^E$20 | F9: ='Supuestos Generales'!$B$121*'Supuestos Generales'!$B$127*(1+'Supuestos Generales'!$B$128)^F$20 | G9: ='Supuestos Generales'!$B$121*'Supuestos Generales'!$B$127*(1+'Supuestos Generales'!$B$128)^G$20 | H9: ='Supuestos Generales'!$B$121*'Supuestos Generales'!$B$127*(1+'Supuestos Generales'!$B$128)^H$20 | I9: ='Supuestos Generales'!$B$121*'Supuestos Generales'!$B$127*(1+'Supuestos Generales'!$B$128)^I$20 | ... BI9: ='Supuestos Generales'!$B$121*'Supuestos Generales'!$B$127*(1+'Supuestos Generales'!$B$128)^BI$20 | BJ9: =SUM(B9:BI9)
A10: Administración y Legal | B10: ='Supuestos Generales'!$B$122*'Supuestos Generales'!$B$127*(1+'Supuestos Generales'!$B$128)^B$20 | C10: ='Supuestos Generales'!$B$122*'Supuestos Generales'!$B$127*(1+'Supuestos Generales'!$B$128)^C$20 | D10: ='Supuestos Generales'!$B$122*'Supuestos Generales'!$B$127*(1+'Supuestos Generales'!$B$128)^D$20 | E10: ='Supuestos Generales'!$B$122*'Supuestos Generales'!$B$127*(1+'Supuestos Generales'!$B$128)^E$20 | F10: ='Supuestos Generales'!$B$122*'Supuestos Generales'!$B$127*(1+'Supuestos Generales'!$B$128)^F$20 | G10: ='Supuestos Generales'!$B$122*'Supuestos Generales'!$B$127*(1+'Supuestos Generales'!$B$128)^G$20 | H10: ='Supuestos Generales'!$B$122*'Supuestos Generales'!$B$127*(1+'Supuestos Generales'!$B$128)^H$20 | I10: ='Supuestos Generales'!$B$122*'Supuestos Generales'!$B$127*(1+'Supuestos Generales'!$B$128)^I$20 | ... BI10: ='Supuestos Generales'!$B$122*'Supuestos Generales'!$B$127*(1+'Supuestos Generales'!$B$128)^BI$20 | BJ10: =SUM(B10:BI10)
A11: Marketing base | B11: ='Supuestos Generales'!$B$123*'Supuestos Generales'!$B$127*(1+'Supuestos Generales'!$B$128)^B$20 | C11: ='Supuestos Generales'!$B$123*'Supuestos Generales'!$B$127*(1+'Supuestos Generales'!$B$128)^C$20 | D11: ='Supuestos Generales'!$B$123*'Supuestos Generales'!$B$127*(1+'Supuestos Generales'!$B$128)^D$20 | E11: ='Supuestos Generales'!$B$123*'Supuestos Generales'!$B$127*(1+'Supuestos Generales'!$B$128)^E$20 | F11: ='Supuestos Generales'!$B$123*'Supuestos Generales'!$B$127*(1+'Supuestos Generales'!$B$128)^F$20 | G11: ='Supuestos Generales'!$B$123*'Supuestos Generales'!$B$127*(1+'Supuestos Generales'!$B$128)^G$20 | H11: ='Supuestos Generales'!$B$123*'Supuestos Generales'!$B$127*(1+'Supuestos Generales'!$B$128)^H$20 | I11: ='Supuestos Generales'!$B$123*'Supuestos Generales'!$B$127*(1+'Supuestos Generales'!$B$128)^I$20 | ... BI11: ='Supuestos Generales'!$B$123*'Supuestos Generales'!$B$127*(1+'Supuestos Generales'!$B$128)^BI$20 | BJ11: =SUM(B11:BI11)
A12: Otros gastos fijos | B12: ='Supuestos Generales'!$B$124*'Supuestos Generales'!$B$127*(1+'Supuestos Generales'!$B$128)^B$20 | C12: ='Supuestos Generales'!$B$124*'Supuestos Generales'!$B$127*(1+'Supuestos Generales'!$B$128)^C$20 | D12: ='Supuestos Generales'!$B$124*'Supuestos Generales'!$B$127*(1+'Supuestos Generales'!$B$128)^D$20 | E12: ='Supuestos Generales'!$B$124*'Supuestos Generales'!$B$127*(1+'Supuestos Generales'!$B$128)^E$20 | F12: ='Supuestos Generales'!$B$124*'Supuestos Generales'!$B$127*(1+'Supuestos Generales'!$B$128)^F$20 | G12: ='Supuestos Generales'!$B$124*'Supuestos Generales'!$B$127*(1+'Supuestos Generales'!$B$128)^G$20 | H12: ='Supuestos Generales'!$B$124*'Supuestos Generales'!$B$127*(1+'Supuestos Generales'!$B$128)^H$20 | I12: ='Supuestos Generales'!$B$124*'Supuestos Generales'!$B$127*(1+'Supuestos Generales'!$B$128)^I$20 | ... BI12: ='Supuestos Generales'!$B$124*'Supuestos Generales'!$B$127*(1+'Supuestos Generales'!$B$128)^BI$20 | BJ12: =SUM(B12:BI12)
A13: Gerente General | B13: =MIN(15000, 3000 + MAX(0, FLOOR(Onboarding!B12/100, 1)) * 1000) | C13: =MIN(15000, 3000 + MAX(0, FLOOR(Onboarding!C12/100, 1)) * 1000) | D13: =MIN(15000, 3000 + MAX(0, FLOOR(Onboarding!D12/100, 1)) * 1000) | E13: =MIN(15000, 3000 + MAX(0, FLOOR(Onboarding!E12/100, 1)) * 1000) | F13: =MIN(15000, 3000 + MAX(0, FLOOR(Onboarding!F12/100, 1)) * 1000) | G13: =MIN(15000, 3000 + MAX(0, FLOOR(Onboarding!G12/100, 1)) * 1000) | H13: =MIN(15000, 3000 + MAX(0, FLOOR(Onboarding!H12/100, 1)) * 1000) | I13: =MIN(15000, 3000 + MAX(0, FLOOR(Onboarding!I12/100, 1)) * 1000) | ... BI13: =MIN(15000, 3000 + MAX(0, FLOOR(Onboarding!BI12/100, 1)) * 1000) | BJ13: =SUM(B13:BI13)
A14: Licencia Superlikers | B14: ='Supuestos Generales'!$B$126 | C14: ='Supuestos Generales'!$B$126 | D14: ='Supuestos Generales'!$B$126 | E14: ='Supuestos Generales'!$B$126 | F14: ='Supuestos Generales'!$B$126 | G14: ='Supuestos Generales'!$B$126 | H14: ='Supuestos Generales'!$B$126 | I14: ='Supuestos Generales'!$B$126 | ... BI14: ='Supuestos Generales'!$B$126 | BJ14: =SUM(B14:BI14)
A15: Total OPEX Fijo | B15: =SUM(B6:B14) | C15: =SUM(C6:C14) | D15: =SUM(D6:D14) | E15: =SUM(E6:E14) | F15: =SUM(F6:F14) | G15: =SUM(G6:G14) | H15: =SUM(H6:H14) | I15: =SUM(I6:I14) | ... BJ15: =SUM(BJ6:BJ14)
A17: DETALLE STEP-UP SEMESTRAL
A18: Multiplicador aplicado | B18: =(1+'Supuestos Generales'!$B$128)^B$20 | C18: =(1+'Supuestos Generales'!$B$128)^C$20 | D18: =(1+'Supuestos Generales'!$B$128)^D$20 | E18: =(1+'Supuestos Generales'!$B$128)^E$20 | F18: =(1+'Supuestos Generales'!$B$128)^F$20 | G18: =(1+'Supuestos Generales'!$B$128)^G$20 | H18: =(1+'Supuestos Generales'!$B$128)^H$20 | I18: =(1+'Supuestos Generales'!$B$128)^I$20 | ... BI18: =(1+'Supuestos Generales'!$B$128)^BI$20
A19: Periodo semestral | B19: =INT((B$3-1)/6)+1 | C19: =INT((C$3-1)/6)+1 | D19: =INT((D$3-1)/6)+1 | E19: =INT((E$3-1)/6)+1 | F19: =INT((F$3-1)/6)+1 | G19: =INT((G$3-1)/6)+1 | H19: =INT((H$3-1)/6)+1 | I19: =INT((I$3-1)/6)+1 | ... BI19: =INT((BI$3-1)/6)+1
A20: Step-ups acumulados (condicional) | B20: 0 | C20: =IF(C19>B19, IF('Estados Financieros'!B22>0, B20+1, B20), B20) | D20: =IF(D19>C19, IF('Estados Financieros'!C22>0, C20+1, C20), C20) | E20: =IF(E19>D19, IF('Estados Financieros'!D22>0, D20+1, D20), D20) | F20: =IF(F19>E19, IF('Estados Financieros'!E22>0, E20+1, E20), E20) | G20: =IF(G19>F19, IF('Estados Financieros'!F22>0, F20+1, F20), F20) | H20: =IF(H19>G19, IF('Estados Financieros'!G22>0, G20+1, G20), G20) | I20: =IF(I19>H19, IF('Estados Financieros'!H22>0, H20+1, H20), H20) | J20: =IF(J19>I19, IF('Estados Financieros'!I22>0, I20+1, I20), I20) | ... BI20: =IF(BI19>BH19, IF('Estados Financieros'!BH22>0, BH20+1, BH20), BH20)
A22: OPEX TOTAL
A23: Total OPEX Mensual | B23: =B15 | C23: =C15 | D23: =D15 | E23: =E15 | F23: =F15 | G23: =G15 | H23: =H15 | I23: =I15 | ... BI23: =BI15 | BJ23: =SUM(B23:BI23)
A24: OPEX Acumulado | B24: =B23 | C24: =B24+C23 | D24: =C24+D23 | E24: =D24+E23 | F24: =E24+F23 | G24: =F24+G23 | H24: =G24+H23 | I24: =H24+I23 | J24: =I24+J23 | ... BI24: =BH24+BI23 | BJ24: =BI24
A26: MÉTRICAS
A27: OPEX como % de Ingresos | B27: =IF(Ingresos!B19=0,0,B23/Ingresos!B19) | C27: =IF(Ingresos!C19=0,0,C23/Ingresos!C19) | D27: =IF(Ingresos!D19=0,0,D23/Ingresos!D19) | E27: =IF(Ingresos!E19=0,0,E23/Ingresos!E19) | F27: =IF(Ingresos!F19=0,0,F23/Ingresos!F19) | G27: =IF(Ingresos!G19=0,0,G23/Ingresos!G19) | H27: =IF(Ingresos!H19=0,0,H23/Ingresos!H19) | I27: =IF(Ingresos!I19=0,0,I23/Ingresos!I19) | ... BJ27: =IF(Ingresos!BJ19=0,0,BJ23/Ingresos!BJ19)
A28: OPEX por restaurante activo | B28: =IF(Onboarding!B12=0,0,B23/Onboarding!B12) | C28: =IF(Onboarding!C12=0,0,C23/Onboarding!C12) | D28: =IF(Onboarding!D12=0,0,D23/Onboarding!D12) | E28: =IF(Onboarding!E12=0,0,E23/Onboarding!E12) | F28: =IF(Onboarding!F12=0,0,F23/Onboarding!F12) | G28: =IF(Onboarding!G12=0,0,G23/Onboarding!G12) | H28: =IF(Onboarding!H12=0,0,H23/Onboarding!H12) | I28: =IF(Onboarding!I12=0,0,I23/Onboarding!I12) | ... BI28: =IF(Onboarding!BI12=0,0,BI23/Onboarding!BI12)

Sheet Estados Financieros
A1: ESTADOS FINANCIEROS — Proyección Mensual | BK1: ⚡ ESCENARIO
BK2: =CHOOSE(Escenarios!B4,"PESIMISTA","BASE","OPTIMISTA")
A3: Concepto | B3: 1 | C3: 2 | D3: 3 | E3: 4 | F3: 5 | G3: 6 | H3: 7 | I3: 8 | J3: 9 | K3: 10 | L3: 11 | M3: 12 | N3: 13 | O3: 14 | P3: 15 | Q3: 16 | R3: 17 | S3: 18 | T3: 19 | U3: 20 | V3: 21 | W3: 22 | X3: 23 | Y3: 24 | Z3: 25 | AA3: 26 | AB3: 27 | AC3: 28 | AD3: 29 | AE3: 30 | AF3: 31 | AG3: 32 | AH3: 33 | AI3: 34 | AJ3: 35 | AK3: 36 | AL3: 37 | AM3: 38 | AN3: 39 | AO3: 40 | AP3: 41 | AQ3: 42 | AR3: 43 | AS3: 44 | AT3: 45 | AU3: 46 | AV3: 47 | AW3: 48 | AX3: 49 | AY3: 50 | AZ3: 51 | BA3: 52 | BB3: 53 | BC3: 54 | BD3: 55 | BE3: 56 | BF3: 57 | BG3: 58 | BH3: 59 | BI3: 60 | BJ3: TOTAL | BK3: =HYPERLINK("#Escenarios!B4","✏️ Cambiar escenario →")
A5: INGRESOS
A6: Ingresos One-Off | B6: =Ingresos!B8 | C6: =Ingresos!C8 | D6: =Ingresos!D8 | E6: =Ingresos!E8 | F6: =Ingresos!F8 | G6: =Ingresos!G8 | H6: =Ingresos!H8 | I6: =Ingresos!I8 | ... BI6: =Ingresos!BI8 | BJ6: =SUM(B6:BI6)
A7: Ingresos Recurrentes | B7: =Ingresos!B17 | C7: =Ingresos!C17 | D7: =Ingresos!D17 | E7: =Ingresos!E17 | F7: =Ingresos!F17 | G7: =Ingresos!G17 | H7: =Ingresos!H17 | I7: =Ingresos!I17 | ... BI7: =Ingresos!BI17 | BJ7: =SUM(B7:BI7)
A8: Total Ingresos | B8: =B6+B7 | C8: =C6+C7 | D8: =D6+D7 | E8: =E6+E7 | F8: =F6+F7 | G8: =G6+G7 | H8: =H6+H7 | I8: =I6+I7 | ... BI8: =BI6+BI7 | BJ8: =SUM(B8:BI8)
A10: COSTOS Y GASTOS
A11: Costos Directos | B11: ='Costos Directos'!B34 | C11: ='Costos Directos'!C34 | D11: ='Costos Directos'!D34 | E11: ='Costos Directos'!E34 | F11: ='Costos Directos'!F34 | G11: ='Costos Directos'!G34 | H11: ='Costos Directos'!H34 | I11: ='Costos Directos'!I34 | ... BI11: ='Costos Directos'!BI34 | BJ11: =SUM(B11:BI11)
A12: incl. Provisión Errores/Fraude | B12: ='Costos Directos'!B32 | C12: ='Costos Directos'!C32 | D12: ='Costos Directos'!D32 | E12: ='Costos Directos'!E32 | F12: ='Costos Directos'!F32 | G12: ='Costos Directos'!G32 | H12: ='Costos Directos'!H32 | I12: ='Costos Directos'!I32 | ... BI12: ='Costos Directos'!BI32 | BJ12: =SUM(B12:BI12)
A13: Utilidad Bruta | B13: =B8-B11 | C13: =C8-C11 | D13: =D8-D11 | E13: =E8-E11 | F13: =F8-F11 | G13: =G8-G11 | H13: =H8-H11 | I13: =I8-I11 | ... BI13: =BI8-BI11 | BJ13: =SUM(B13:BI13)
A14: Margen Bruto (%) | B14: =IF(B8=0,0,B13/B8) | C14: =IF(C8=0,0,C13/C8) | D14: =IF(D8=0,0,D13/D8) | E14: =IF(E8=0,0,E13/E8) | F14: =IF(F8=0,0,F13/F8) | G14: =IF(G8=0,0,G13/G8) | H14: =IF(H8=0,0,H13/H8) | I14: =IF(I8=0,0,I13/I8) | ... BJ14: =IF(BJ8=0,0,BJ13/BJ8)
A16: CAC y Go-to-Market | B16: ='CAC y GTM'!B34 | C16: ='CAC y GTM'!C34 | D16: ='CAC y GTM'!D34 | E16: ='CAC y GTM'!E34 | F16: ='CAC y GTM'!F34 | G16: ='CAC y GTM'!G34 | H16: ='CAC y GTM'!H34 | I16: ='CAC y GTM'!I34 | ... BI16: ='CAC y GTM'!BI34 | BJ16: =SUM(B16:BI16)
A17: incl. Comisiones de Venta | B17: ='CAC y GTM'!B23 | C17: ='CAC y GTM'!C23 | D17: ='CAC y GTM'!D23 | E17: ='CAC y GTM'!E23 | F17: ='CAC y GTM'!F23 | G17: ='CAC y GTM'!G23 | H17: ='CAC y GTM'!H23 | I17: ='CAC y GTM'!I23 | ... BI17: ='CAC y GTM'!BI23 | BJ17: =SUM(B17:BI17)
A18: incl. Publicidad y Marketing | B18: ='CAC y GTM'!B27 | C18: ='CAC y GTM'!C27 | D18: ='CAC y GTM'!D27 | E18: ='CAC y GTM'!E27 | F18: ='CAC y GTM'!F27 | G18: ='CAC y GTM'!G27 | H18: ='CAC y GTM'!H27 | I18: ='CAC y GTM'!I27 | ... BI18: ='CAC y GTM'!BI27 | BJ18: =SUM(B18:BI18)
A19: Utilidad Bruta después de CAC | B19: =B13-B16 | C19: =C13-C16 | D19: =D13-D16 | E19: =E13-E16 | F19: =F13-F16 | G19: =G13-G16 | H19: =H13-H16 | I19: =I13-I16 | ... BI19: =BI13-BI16 | BJ19: =SUM(B19:BI19)
A21: OPEX Fijo | B21: =OPEX!B23 | C21: =OPEX!C23 | D21: =OPEX!D23 | E21: =OPEX!E23 | F21: =OPEX!F23 | G21: =OPEX!G23 | H21: =OPEX!H23 | I21: =OPEX!I23 | ... BI21: =OPEX!BI23 | BJ21: =SUM(B21:BI21)
A22: EBITDA | B22: =B19-B21 | C22: =C19-C21 | D22: =D19-D21 | E22: =E19-E21 | F22: =F19-F21 | G22: =G19-G21 | H22: =H19-H21 | I22: =I19-I21 | ... BI22: =BI19-BI21 | BJ22: =SUM(B22:BI22)
A23: Margen EBITDA (%) | B23: =IF(B8=0,0,B22/B8) | C23: =IF(C8=0,0,C22/C8) | D23: =IF(D8=0,0,D22/D8) | E23: =IF(E8=0,0,E22/E8) | F23: =IF(F8=0,0,F22/F8) | G23: =IF(G8=0,0,G22/G8) | H23: =IF(H8=0,0,H22/H8) | I23: =IF(I8=0,0,I22/I8) | ... BJ23: =IF(BJ8=0,0,BJ22/BJ8)
A24: Impuestos sobre utilidades | B24: =MAX(0,B22*'Supuestos Generales'!$B$38) | C24: =MAX(0,C22*'Supuestos Generales'!$B$38) | D24: =MAX(0,D22*'Supuestos Generales'!$B$38) | E24: =MAX(0,E22*'Supuestos Generales'!$B$38) | F24: =MAX(0,F22*'Supuestos Generales'!$B$38) | G24: =MAX(0,G22*'Supuestos Generales'!$B$38) | H24: =MAX(0,H22*'Supuestos Generales'!$B$38) | I24: =MAX(0,I22*'Supuestos Generales'!$B$38) | ... BI24: =MAX(0,BI22*'Supuestos Generales'!$B$38) | BJ24: =SUM(B24:BI24)
A25: Utilidad Neta | B25: =B22-B24 | C25: =C22-C24 | D25: =D22-D24 | E25: =E22-E24 | F25: =F22-F24 | G25: =G22-G24 | H25: =H22-H24 | I25: =I22-I24 | ... BI25: =BI22-BI24 | BJ25: =SUM(B25:BI25)
A26: Margen Neto (%) | B26: =IF(B8=0,0,B25/B8) | C26: =IF(C8=0,0,C25/C8) | D26: =IF(D8=0,0,D25/D8) | E26: =IF(E8=0,0,E25/E8) | F26: =IF(F8=0,0,F25/F8) | G26: =IF(G8=0,0,G25/G8) | H26: =IF(H8=0,0,H25/H8) | I26: =IF(I8=0,0,I25/I8) | ... BJ26: =IF(BJ8=0,0,BJ25/BJ8)
A28: FLUJO DE CAJA
A29: Caja Inicial | B29: ='Supuestos Generales'!$B$8 | C29: =B31 | D29: =C31 | E29: =D31 | F29: =E31 | G29: =F31 | H29: =G31 | I29: =H31 | J29: =I31 | ... BI29: =BH31
A30: Flujo del Mes (= Utilidad Neta) | B30: =B25 | C30: =C25 | D30: =D25 | E30: =E25 | F30: =F25 | G30: =G25 | H30: =H25 | I30: =I25 | ... BI30: =BI25 | BJ30: =SUM(B30:BI30)
A31: Caja Final | B31: =B29+B30 | C31: =C29+C30 | D31: =D29+D30 | E31: =E29+E30 | F31: =F29+F30 | G31: =G29+G30 | H31: =H29+H30 | I31: =I29+I30 | ... BI31: =BI29+BI30 | BJ31: =BI31
A32: Runway (meses) | B32: =IF(B30>=0,"N/A",B31/(-B30)) | C32: =IF(C30>=0,"N/A",C31/(-C30)) | D32: =IF(D30>=0,"N/A",D31/(-D30)) | E32: =IF(E30>=0,"N/A",E31/(-E30)) | F32: =IF(F30>=0,"N/A",F31/(-F30)) | G32: =IF(G30>=0,"N/A",G31/(-G30)) | H32: =IF(H30>=0,"N/A",H31/(-H30)) | I32: =IF(I30>=0,"N/A",I31/(-I30)) | ... BI32: =IF(BI30>=0,"N/A",BI31/(-BI30))
A34: KPIs OPERATIVOS
A35: Restaurantes activos | B35: =Onboarding!B12 | C35: =Onboarding!C12 | D35: =Onboarding!D12 | E35: =Onboarding!E12 | F35: =Onboarding!F12 | G35: =Onboarding!G12 | H35: =Onboarding!H12 | I35: =Onboarding!I12 | ... BI35: =Onboarding!BI12 | BJ35: =BI35
A36: Meseros activos | B36: =Onboarding!B19 | C36: =Onboarding!C19 | D36: =Onboarding!D19 | E36: =Onboarding!E19 | F36: =Onboarding!F19 | G36: =Onboarding!G19 | H36: =Onboarding!H19 | I36: =Onboarding!I19 | ... BI36: =Onboarding!BI19 | BJ36: =BI36
A37: Ingreso por restaurante (USD/mes) | B37: =IF(B35=0,0,B8/B35) | C37: =IF(C35=0,0,C8/C35) | D37: =IF(D35=0,0,D8/D35) | E37: =IF(E35=0,0,E8/E35) | F37: =IF(F35=0,0,F8/F35) | G37: =IF(G35=0,0,G8/G35) | H37: =IF(H35=0,0,H8/H35) | I37: =IF(I35=0,0,I8/I35) | ... BI37: =IF(BI35=0,0,BI8/BI35) | BJ37: =BI37
A38: Costo total por restaurante (USD/mes) | B38: =IF(B35=0,0,(B11+B16+B21)/B35) | C38: =IF(C35=0,0,(C11+C16+C21)/C35) | D38: =IF(D35=0,0,(D11+D16+D21)/D35) | E38: =IF(E35=0,0,(E11+E16+E21)/E35) | F38: =IF(F35=0,0,(F11+F16+F21)/F35) | G38: =IF(G35=0,0,(G11+G16+G21)/G35) | H38: =IF(H35=0,0,(H11+H16+H21)/H35) | I38: =IF(I35=0,0,(I11+I16+I21)/I35) | ... BI38: =IF(BI35=0,0,(BI11+BI16+BI21)/BI35) | BJ38: =BI38

Sheet Valoración
A1: VALORACIÓN PRE-SEMILLA — SUPER MESEROS | H1: ⚡ ESCENARIO
A2: Spin-Off de Superlikers · Modelo de valoración interactivo para inversionistas | H2: =CHOOSE(Escenarios!B4,"PESIMISTA","BASE","OPTIMISTA")
H3: =HYPERLINK("#Escenarios!B4","✏️ Cambiar escenario →")
A4: VARIABLES DE ENTRADA | C4: Valor | D4: Unidad | E4: Notas | H4: 📖 GUÍA PARA EL INVERSIONISTA
A5: Pipeline de Restaurantes | H5: CONTEXTO ESTRATÉGICO
A6: Coca-Cola (exclusividad) | C6: =IF(Palancas!$B$13=1,Palancas!$B$17,0) | D6: rest. | E6: ← Coca-Cola activo; neto de solapamiento si toggle = ON | H6: • Spin-Off de Superlikers (15 años en gamificación)
A7: ACODRES Colombia | C7: =IF(Palancas!$F$13=1,Palancas!$F$17,0) | D7: rest. | E7: ← ACODRES activo; neto de solapamiento si toggle = ON | H7: • PMF validado: Grupo Modelo, Backus, Pernod Ricard
A8: Coca-Cola Florida (piloto USA) | C8: =IF(Palancas!$B$29=1,Palancas!$B$33,0) | D8: rest. | E8: ← CC Florida activo; solo cuenta si toggle = ON | H8: • Coca-Cola: exclusividad + 5,000 rest. pipeline
A9: Bavaria Colombia | C9: =IF(Palancas!$B$21=1,Palancas!$B$25,0) | D9: rest. | E9: ← Bavaria activa; neto de solapamiento si toggle = ON | H9: • Bavaria Colombia: 4,500 rest. buscan implementar SM
A10: FEMSA Ventures (México) | C10: =IF(Palancas!$F$21=1,Palancas!$F$25,0) | D10: rest. | E10: ← FEMSA activa; solo cuenta si toggle = ON | H10: • Pipeline total: 76,500 rest. (5 alianzas estratégicas)
A11: % conversión del pipeline | C11: 0.1 | D11: % | E11: Porcentaje estimado de conversión efectiva a 36 meses | H11: • ACODRES Colombia: canal institucional
H12: • FEMSA Ventures: intención de inversión (México)
A13: Unit Economics | H13: • Coca-Cola Florida: piloto USA → Atlanta
A14: Meseros promedio por restaurante | C14: ='Supuestos Generales'!B19 | D14: meseros | E14: Promedio industria restaurantes LATAM
A15: % meseros activos | C15: ='Supuestos Generales'!B20 | D15: % | E15: ← SupGen!B20 | Cambia con escenario (Pes=75%, Base=85%, Opt=95%) | H15: CÓMO USAR ESTA HOJA
A16: ARPU mensual por mesero (restaurante) | C16: ='Supuestos Generales'!B26 | D16: USD/mes | E16: ← SupGen!B26 | Cambia con escenario (Pes=$10, Base=$15, Opt=$20) | H16: 1. Modifique las celdas amarillas (col C) para ajustar variables del pipeline, unit economics y parámetros de valoración.
A17: ARPU mensual por mesero (marcas) | C17: ='Supuestos Generales'!B27 | D17: USD/mes | E17: ← SupGen!B27 | Cambia con escenario (Pes=$7, Base=$10, Opt=$15) | H17: 2. La sección "Métricas Calculadas" muestra los números derivados automáticamente.
A18: Marcas promedio por restaurante | C18: ='Supuestos Generales'!B28 | D18: marcas | E18: ← SupGen!B28 | Cambia con escenario (Pes=1, Base=2, Opt=3) | H18: 3. Los "Resultados de Valoración" ofrecen 3 métodos: pipeline puro, modelo financiero y promedio ponderado.
H19: 4. Las Tablas de Sensibilidad permiten explorar escenarios cambiando 2 variables simultáneamente.
A20: Parámetros de Valoración | H20: 5. Los datos del modelo financiero (verde) se vinculan automáticamente a la hoja Estados Financieros.
A21: Múltiplo de ARR para valoración | C21: 5 | D21: x ARR | E21: SaaS B2B pre-seed LATAM: 3x-8x; con tracción USA: 5x-15x | H21: Azules = editables | Verdes = vinculadas a Palancas/EF | Negras = fórmulas
A22: Monto a levantar (pre-semilla) | C22: 750000 | D22: USD | E22: Rango típico pre-semilla LATAM: $300K - $1.5M
A23: % Peso Pipeline en valoración | C23: 0.3 | D23: % | E23: 0% = solo modelo real; 100% = solo pipeline. Default: 20%
A24: MÉTRICAS CALCULADAS
A25: Pipeline de Ingresos
A26: Total restaurantes pipeline activo (neto) | C26: =C6+C7+C8+C9+C10 | D26: rest.
A27: Restaurantes efectivos (con conversión activa) | C27: =C26*C11 | D27: rest.
A28: Total meseros activos | C28: =C27*C14*C15 | D28: meseros
A29: MRR por mesero (restaurante + marcas) | C29: =C16+(C17*C18) | D29: USD/mes
A31: Ingresos Proyectados del Pipeline Activo
A32: MRR total del pipeline | C32: =C28*C29+C27*'Supuestos Generales'!B59*'Supuestos Generales'!B60 | D32: USD/mes
A33: ARR del pipeline (MRR × 12) | C33: =C32*12 | D33: USD/año | E33: ← Ingreso recurrente anualizado del pipeline activo
A35: Datos del Modelo Financiero (automático)
A36: ARR del modelo financiero (cierre Año 1) | C36: ='Estados Financieros'!M7*12 | D36: USD/año | E36: ← Ingresos recurrentes anualizados (cierre Año 1)
A37: ARR del modelo financiero (cierre Año 2) | C37: ='Estados Financieros'!Y7*12 | D37: USD/año | E37: ← Ingresos recurrentes anualizados (cierre Año 2)
A38: EBITDA acumulado (60 meses) | C38: ='Estados Financieros'!BJ22 | D38: USD | E38: ← Vinculado a Estados Financieros
A39: Utilidad neta acumulada (60 meses) | C39: ='Estados Financieros'!BJ25 | D39: USD | E39: ← Vinculado a Estados Financieros
A40: Restaurantes activos (mes 60) | C40: ='Estados Financieros'!BJ35 | D40: rest. | E40: ← Vinculado a Estados Financieros
A41: Caja final (mes 60) | C41: ='Estados Financieros'!BJ31 | D41: USD | E41: ← Vinculado a Estados Financieros
A44: RESULTADOS DE VALORACIÓN
A45: Método 1: Múltiplos de ARR Pipeline
A46: Valoración Pre-Money (Múltiplo × ARR Pipeline) | C46: =C21*C33 | D46: USD | E46: ="= "&C21&"x × ARR Pipeline"
A48: Método 2: Múltiplos de ARR del Modelo (Año 1)
A49: Valoración Pre-Money (Múltiplo × ARR Modelo A1) | C49: =C21*C36 | D49: USD | E49: ="= "&C21&"x × ARR Modelo Año 1"
A51: Método 3: Promedio Ponderado
A52: Valoración Pre-Money (Promedio Ponderado) | C52: =(C46*C23)+(C49*(1-C23)) | D52: USD | E52: ="= "&TEXT(C23,"0%")&" Pipeline + "&TEXT(1-C23,"0%")&" Modelo"
A54: DEAL STRUCTURE
A55: Valoración Pre-Money | C55: =C52 | D55: USD
A56: Monto a levantar | C56: =C22 | D56: USD
A57: Valoración Post-Money | C57: =C55+C56 | D57: USD
A58: Dilución del fundador | C58: =C56/C57 | E58: ="El inversionista obtiene "&ROUND(C58*100,1)&"% de la compañía"
A60: TABLAS DE SENSIBILIDAD
A61: Modifique las celdas amarillas de la sección "Variables de Entrada" (filas 6-20) para ver cómo cambian todas las tablas automáticamente.
A63: TABLA 1: Valoración Pre-Money ($M) — Múltiplo ARR vs. % Conversión del Pipeline
A64: Múltiplo ↓ / Conversión → | C64: 0.3 | D64: 0.4 | E64: 0.5 | F64: 0.6 | G64: 0.7 | H64: 0.8 | I64: 1
A65: 0.5 | C65: =$A65*C$64*$C$26*$C$14*$C$15*$C$29*12/1000000 | D65: =$A65*D$64*$C$26*$C$14*$C$15*$C$29*12/1000000 | E65: =$A65*E$64*$C$26*$C$14*$C$15*$C$29*12/1000000 | F65: =$A65*F$64*$C$26*$C$14*$C$15*$C$29*12/1000000 | G65: =$A65*G$64*$C$26*$C$14*$C$15*$C$29*12/1000000 | H65: =$A65*H$64*$C$26*$C$14*$C$15*$C$29*12/1000000 | I65: =$A65*I$64*$C$26*$C$14*$C$15*$C$29*12/1000000
A66: 1 | C66: =$A66*C$64*$C$26*$C$14*$C$15*$C$29*12/1000000 | D66: =$A66*D$64*$C$26*$C$14*$C$15*$C$29*12/1000000 | E66: =$A66*E$64*$C$26*$C$14*$C$15*$C$29*12/1000000 | F66: =$A66*F$64*$C$26*$C$14*$C$15*$C$29*12/1000000 | G66: =$A66*G$64*$C$26*$C$14*$C$15*$C$29*12/1000000 | H66: =$A66*H$64*$C$26*$C$14*$C$15*$C$29*12/1000000 | I66: =$A66*I$64*$C$26*$C$14*$C$15*$C$29*12/1000000
A67: 1.5 | C67: =$A67*C$64*$C$26*$C$14*$C$15*$C$29*12/1000000 | D67: =$A67*D$64*$C$26*$C$14*$C$15*$C$29*12/1000000 | E67: =$A67*E$64*$C$26*$C$14*$C$15*$C$29*12/1000000 | F67: =$A67*F$64*$C$26*$C$14*$C$15*$C$29*12/1000000 | G67: =$A67*G$64*$C$26*$C$14*$C$15*$C$29*12/1000000 | H67: =$A67*H$64*$C$26*$C$14*$C$15*$C$29*12/1000000 | I67: =$A67*I$64*$C$26*$C$14*$C$15*$C$29*12/1000000
A68: 2 | C68: =$A68*C$64*$C$26*$C$14*$C$15*$C$29*12/1000000 | D68: =$A68*D$64*$C$26*$C$14*$C$15*$C$29*12/1000000 | E68: =$A68*E$64*$C$26*$C$14*$C$15*$C$29*12/1000000 | F68: =$A68*F$64*$C$26*$C$14*$C$15*$C$29*12/1000000 | G68: =$A68*G$64*$C$26*$C$14*$C$15*$C$29*12/1000000 | H68: =$A68*H$64*$C$26*$C$14*$C$15*$C$29*12/1000000 | I68: =$A68*I$64*$C$26*$C$14*$C$15*$C$29*12/1000000
A69: 3 | C69: =$A69*C$64*$C$26*$C$14*$C$15*$C$29*12/1000000 | D69: =$A69*D$64*$C$26*$C$14*$C$15*$C$29*12/1000000 | E69: =$A69*E$64*$C$26*$C$14*$C$15*$C$29*12/1000000 | F69: =$A69*F$64*$C$26*$C$14*$C$15*$C$29*12/1000000 | G69: =$A69*G$64*$C$26*$C$14*$C$15*$C$29*12/1000000 | H69: =$A69*H$64*$C$26*$C$14*$C$15*$C$29*12/1000000 | I69: =$A69*I$64*$C$26*$C$14*$C$15*$C$29*12/1000000
A70: 5 | C70: =$A70*C$64*$C$26*$C$14*$C$15*$C$29*12/1000000 | D70: =$A70*D$64*$C$26*$C$14*$C$15*$C$29*12/1000000 | E70: =$A70*E$64*$C$26*$C$14*$C$15*$C$29*12/1000000 | F70: =$A70*F$64*$C$26*$C$14*$C$15*$C$29*12/1000000 | G70: =$A70*G$64*$C$26*$C$14*$C$15*$C$29*12/1000000 | H70: =$A70*H$64*$C$26*$C$14*$C$15*$C$29*12/1000000 | I70: =$A70*I$64*$C$26*$C$14*$C$15*$C$29*12/1000000
A71: 8 | C71: =$A71*C$64*$C$26*$C$14*$C$15*$C$29*12/1000000 | D71: =$A71*D$64*$C$26*$C$14*$C$15*$C$29*12/1000000 | E71: =$A71*E$64*$C$26*$C$14*$C$15*$C$29*12/1000000 | F71: =$A71*F$64*$C$26*$C$14*$C$15*$C$29*12/1000000 | G71: =$A71*G$64*$C$26*$C$14*$C$15*$C$29*12/1000000 | H71: =$A71*H$64*$C$26*$C$14*$C$15*$C$29*12/1000000 | I71: =$A71*I$64*$C$26*$C$14*$C$15*$C$29*12/1000000
A72: Rango pre-seed LATAM típico: 0.5x-2x ARR | Con tracción/anchor: 1x-3x | Con expansión USA: 3x-8x
A74: TABLA 2: Dilución del Fundador (%) — Valoración Pre-Money vs. Monto Levantado
A75: Pre-Money ($M) ↓ / Raise ($K) → | C75: 300000 | D75: 500000 | E75: 750000 | F75: 1000000 | G75: 1500000 | H75: 2000000 | I75: 3000000
A76: 2000000 | C76: =C$75/($A76+C$75) | D76: =D$75/($A76+D$75) | E76: =E$75/($A76+E$75) | F76: =F$75/($A76+F$75) | G76: =G$75/($A76+G$75) | H76: =H$75/($A76+H$75) | I76: =I$75/($A76+I$75)
A77: 3000000 | C77: =C$75/($A77+C$75) | D77: =D$75/($A77+D$75) | E77: =E$75/($A77+E$75) | F77: =F$75/($A77+F$75) | G77: =G$75/($A77+G$75) | H77: =H$75/($A77+H$75) | I77: =I$75/($A77+I$75)
A78: 4000000 | C78: =C$75/($A78+C$75) | D78: =D$75/($A78+D$75) | E78: =E$75/($A78+E$75) | F78: =F$75/($A78+F$75) | G78: =G$75/($A78+G$75) | H78: =H$75/($A78+H$75) | I78: =I$75/($A78+I$75)
A79: 5000000 | C79: =C$75/($A79+C$75) | D79: =D$75/($A79+D$75) | E79: =E$75/($A79+E$75) | F79: =F$75/($A79+F$75) | G79: =G$75/($A79+G$75) | H79: =H$75/($A79+H$75) | I79: =I$75/($A79+I$75)
A80: 6000000 | C80: =C$75/($A80+C$75) | D80: =D$75/($A80+D$75) | E80: =E$75/($A80+E$75) | F80: =F$75/($A80+F$75) | G80: =G$75/($A80+G$75) | H80: =H$75/($A80+H$75) | I80: =I$75/($A80+I$75)
A81: 8000000 | C81: =C$75/($A81+C$75) | D81: =D$75/($A81+D$75) | E81: =E$75/($A81+E$75) | F81: =F$75/($A81+F$75) | G81: =G$75/($A81+G$75) | H81: =H$75/($A81+H$75) | I81: =I$75/($A81+I$75)
A82: 10000000 | C82: =C$75/($A82+C$75) | D82: =D$75/($A82+D$75) | E82: =E$75/($A82+E$75) | F82: =F$75/($A82+F$75) | G82: =G$75/($A82+G$75) | H82: =H$75/($A82+H$75) | I82: =I$75/($A82+I$75)
A85: TABLA 3: Retorno del Inversionista (x) — Valoración Pre-Money vs. Exit Value a 5 años
A86: Pre-Money ($M) ↓ / Exit ($M) → | C86: 20000000 | D86: 40000000 | E86: 60000000 | F86: 100000000 | G86: 150000000 | H86: 250000000 | I86: 500000000
A87: 2000000 | C87: =(C$75/($A87+C$75))*C$86/C$75 | D87: =(D$75/($A87+D$75))*D$86/D$75 | E87: =(E$75/($A87+E$75))*E$86/E$75 | F87: =(F$75/($A87+F$75))*F$86/F$75 | G87: =(G$75/($A87+G$75))*G$86/G$75 | H87: =(H$75/($A87+H$75))*H$86/H$75 | I87: =(I$75/($A87+I$75))*I$86/I$75
A88: 3000000 | C88: =(C$75/($A88+C$75))*C$86/C$75 | D88: =(D$75/($A88+D$75))*D$86/D$75 | E88: =(E$75/($A88+E$75))*E$86/E$75 | F88: =(F$75/($A88+F$75))*F$86/F$75 | G88: =(G$75/($A88+G$75))*G$86/G$75 | H88: =(H$75/($A88+H$75))*H$86/H$75 | I88: =(I$75/($A88+I$75))*I$86/I$75
A89: 4000000 | C89: =(C$75/($A89+C$75))*C$86/C$75 | D89: =(D$75/($A89+D$75))*D$86/D$75 | E89: =(E$75/($A89+E$75))*E$86/E$75 | F89: =(F$75/($A89+F$75))*F$86/F$75 | G89: =(G$75/($A89+G$75))*G$86/G$75 | H89: =(H$75/($A89+H$75))*H$86/H$75 | I89: =(I$75/($A89+I$75))*I$86/I$75
A90: 5000000 | C90: =(C$75/($A90+C$75))*C$86/C$75 | D90: =(D$75/($A90+D$75))*D$86/D$75 | E90: =(E$75/($A90+E$75))*E$86/E$75 | F90: =(F$75/($A90+F$75))*F$86/F$75 | G90: =(G$75/($A90+G$75))*G$86/G$75 | H90: =(H$75/($A90+H$75))*H$86/H$75 | I90: =(I$75/($A90+I$75))*I$86/I$75
A91: 6000000 | C91: =(C$75/($A91+C$75))*C$86/C$75 | D91: =(D$75/($A91+D$75))*D$86/D$75 | E91: =(E$75/($A91+E$75))*E$86/E$75 | F91: =(F$75/($A91+F$75))*F$86/F$75 | G91: =(G$75/($A91+G$75))*G$86/G$75 | H91: =(H$75/($A91+H$75))*H$86/H$75 | I91: =(I$75/($A91+I$75))*I$86/I$75
A92: 8000000 | C92: =(C$75/($A92+C$75))*C$86/C$75 | D92: =(D$75/($A92+D$75))*D$86/D$75 | E92: =(E$75/($A92+E$75))*E$86/E$75 | F92: =(F$75/($A92+F$75))*F$86/F$75 | G92: =(G$75/($A92+G$75))*G$86/G$75 | H92: =(H$75/($A92+H$75))*H$86/H$75 | I92: =(I$75/($A92+I$75))*I$86/I$75
A93: 10000000 | C93: =(C$75/($A93+C$75))*C$86/C$75 | D93: =(D$75/($A93+D$75))*D$86/D$75 | E93: =(E$75/($A93+E$75))*E$86/E$75 | F93: =(F$75/($A93+F$75))*F$86/F$75 | G93: =(G$75/($A93+G$75))*G$86/G$75 | H93: =(H$75/($A93+H$75))*H$86/H$75 | I93: =(I$75/($A93+I$75))*I$86/I$75
A94: Exit Value estimado: ARR Año 5 del pipeline ($12.3M) × múltiplo de salida (5x-10x) = $60M-$120M. Con expansión USA: $150M-$500M
A96: NOTAS
A97: • Celda amarilla = caso base (parámetros actuales)
A98: • Tabla 1: Varía múltiplo ARR (0.5x-8x) y % de conversión del pipeline (30%-100%). Valores en millones USD.
A99: • Tabla 2: Varía valoración pre-money ($2M-$10M) y monto a levantar ($300K-$3M). Muestra dilución del fundador.
A100: • Tabla 3: Retorno del inversionista (múltiplo de su inversión) según valoración pre-money y exit value a 5 años. Asume raise de $750K.
A101: • Para modificar cualquier variable, edite las celdas amarillas en la sección "Variables de Entrada" (filas 6-20). Todas las tablas se recalculan automáticamente.

Sheet Anexos Documentación
A1: ANEXOS TÉCNICOS — DOCUMENTACIÓN DEL MODELO FINANCIERO SUPER MESEROS
A2: Detalle técnico de fórmulas, lógica de construcción y decisiones del usuario. Complemento de la hoja Documentación.
A4: ANEXO 1: CONTEXTO Y PROBLEMA RESUELTO
A6: El modelo financiero original tenía un defecto estructural: al cambiar de escenario Base a Pesimista, los ingresos se reducían proporcionalmente (menor onboarding, mayor churn, menor ARPU), pero los OPEX fijos del equipo permanecían idénticos en $32,500/mes para los 3 escenarios.
A8: Causa raíz: Las fórmulas de OPEX (filas 6-12) leían directamente de Supuestos Generales B95:B101 (Detalle OPEX), que no estaban conectadas al selector de escenario. Adicionalmente, Escenarios!D23 tenía un valor de $15,000 etiquetado como 'OPEX base mensual' pero NINGUNA fórmula lo referenciaba — era un dato huérfano.
A10: Segundo problema: Los step-ups de OPEX (incremento del 15% cada 6 meses en Pesimista) se aplicaban mecánicamente sin importar si el negocio generaba ingresos suficientes para cubrirlos. En Pesimista, el OPEX crecía 3.2× (de $22,950 a $72,592/mes) mientras los ingresos apenas sostenían la operación, produciendo una Utilidad Neta de -$156K al cierre.
A12: Solución implementada: 5 mecanismos de control de costos documentados en los siguientes anexos.
A14: ANEXO 2: FACTOR ESCALA OPEX POR ESCENARIO
A16: Concepto: En lugar de que todos los escenarios operen con el mismo OPEX base ($32,500/mes), se introdujo un Factor escala que multiplica el OPEX base según el escenario seleccionado.
A18: Lógica del factor:
A19: • Pesimista: $15,000 / $32,500 ≈ 0.46 → Opera con el 46% del equipo completo (lean startup)
A20: • Base: $32,500 / $32,500 = 1.00 → Equipo completo como está parametrizado
... A329: Al cambiar B59 y B50 de hardcodes a CHOOSE(), Costos Directos se ajusta automáticamente por escenario.
